package com.parse;

import java.util.List;
import l;

class OfflineStore$29
  implements l<Void, Void>
{
  OfflineStore$29(OfflineStore paramOfflineStore, List paramList) {}
  
  /* Error */
  public Void then(m<Void> paramm)
  {
    // Byte code:
    //   0: aload_0
    //   1: getfield 15	com/parse/OfflineStore$29:this$0	Lcom/parse/OfflineStore;
    //   4: invokestatic 31	com/parse/OfflineStore:access$300	(Lcom/parse/OfflineStore;)Ljava/lang/Object;
    //   7: astore_2
    //   8: aload_2
    //   9: monitorenter
    //   10: aload_0
    //   11: getfield 17	com/parse/OfflineStore$29:val$uuidsToDelete	Ljava/util/List;
    //   14: invokeinterface 37 1 0
    //   19: astore 4
    //   21: aload 4
    //   23: invokeinterface 43 1 0
    //   28: ifeq +70 -> 98
    //   31: aload 4
    //   33: invokeinterface 47 1 0
    //   38: checkcast 49	java/lang/String
    //   41: astore 5
    //   43: aload_0
    //   44: getfield 15	com/parse/OfflineStore$29:this$0	Lcom/parse/OfflineStore;
    //   47: invokestatic 53	com/parse/OfflineStore:access$400	(Lcom/parse/OfflineStore;)Lcom/parse/WeakValueHashMap;
    //   50: aload 5
    //   52: invokevirtual 59	com/parse/WeakValueHashMap:get	(Ljava/lang/Object;)Ljava/lang/Object;
    //   55: checkcast 61	com/parse/ParseObject
    //   58: astore 6
    //   60: aload 6
    //   62: ifnull -41 -> 21
    //   65: aload_0
    //   66: getfield 15	com/parse/OfflineStore$29:this$0	Lcom/parse/OfflineStore;
    //   69: invokestatic 65	com/parse/OfflineStore:access$500	(Lcom/parse/OfflineStore;)Ljava/util/WeakHashMap;
    //   72: aload 6
    //   74: invokevirtual 70	java/util/WeakHashMap:remove	(Ljava/lang/Object;)Ljava/lang/Object;
    //   77: pop
    //   78: aload_0
    //   79: getfield 15	com/parse/OfflineStore$29:this$0	Lcom/parse/OfflineStore;
    //   82: invokestatic 53	com/parse/OfflineStore:access$400	(Lcom/parse/OfflineStore;)Lcom/parse/WeakValueHashMap;
    //   85: aload 5
    //   87: invokevirtual 73	com/parse/WeakValueHashMap:remove	(Ljava/lang/Object;)V
    //   90: goto -69 -> 21
    //   93: astore_3
    //   94: aload_2
    //   95: monitorexit
    //   96: aload_3
    //   97: athrow
    //   98: aload_2
    //   99: monitorexit
    //   100: aconst_null
    //   101: areturn
    // Local variable table:
    //   start	length	slot	name	signature
    //   0	102	0	this	29
    //   0	102	1	paramm	m<Void>
    //   7	92	2	localObject1	Object
    //   93	4	3	localObject2	Object
    //   19	13	4	localIterator	java.util.Iterator
    //   41	45	5	str	java.lang.String
    //   58	15	6	localParseObject	ParseObject
    // Exception table:
    //   from	to	target	type
    //   10	96	93	finally
    //   98	100	93	finally
  }
}


/* Location:           C:\Users\dreadiscool\Desktop\tools\classes-dex2jar.jar
 * Qualified Name:     com.parse.OfflineStore.29
 * JD-Core Version:    0.7.0.1
 */