import java.util.Collections;
import java.util.List;

public final class dK
  extends sl
  implements dN
{
  public static sI<dK> a = new dL();
  private static final dK c;
  private static volatile sH q = null;
  private final rZ d;
  private List<Integer> e;
  private List<Integer> f;
  private List<Integer> g;
  private List<Integer> h;
  private List<Integer> i;
  private List<Integer> j;
  private List<Integer> k;
  private List<Integer> l;
  private List<Integer> m;
  private List<Integer> n;
  private byte o = -1;
  private int p = -1;
  
  static
  {
    c = new dK(true);
    c.E();
  }
  
  /* Error */
  private dK(sc paramsc, sg paramsg)
  {
    // Byte code:
    //   0: aload_0
    //   1: invokespecial 56	sl:<init>	()V
    //   4: aload_0
    //   5: bipush 255
    //   7: putfield 58	dK:o	B
    //   10: aload_0
    //   11: bipush 255
    //   13: putfield 60	dK:p	I
    //   16: aload_0
    //   17: invokespecial 50	dK:E	()V
    //   20: iconst_0
    //   21: istore_3
    //   22: invokestatic 65	rZ:i	()Lsb;
    //   25: astore 4
    //   27: aload 4
    //   29: invokestatic 70	se:a	(Ljava/io/OutputStream;)Lse;
    //   32: astore 5
    //   34: iconst_0
    //   35: istore 6
    //   37: iload 6
    //   39: ifne +1689 -> 1728
    //   42: aload_1
    //   43: invokevirtual 75	sc:a	()I
    //   46: istore 14
    //   48: iload 14
    //   50: lookupswitch	default:+178->228, 0:+1953->2003, 8:+197->247, 10:+471->521, 16:+565->615, 18:+607->657, 24:+682->732, 26:+724->774, 32:+799->849, 34:+844->894, 40:+922->972, 42:+967->1017, 48:+1045->1095, 50:+1090->1140, 56:+1168->1218, 58:+1213->1263, 64:+1291->1341, 66:+1339->1389, 72:+1420->1470, 74:+1468->1518, 80:+1549->1599, 82:+1597->1647
    //   229: aload_1
    //   230: aload 5
    //   232: aload_2
    //   233: iload 14
    //   235: invokevirtual 78	dK:a	(Lsc;Lse;Lsg;I)Z
    //   238: ifne -201 -> 37
    //   241: iconst_1
    //   242: istore 6
    //   244: goto -207 -> 37
    //   247: iload_3
    //   248: iconst_1
    //   249: iand
    //   250: iconst_1
    //   251: if_icmpeq +18 -> 269
    //   254: aload_0
    //   255: new 80	java/util/ArrayList
    //   258: dup
    //   259: invokespecial 81	java/util/ArrayList:<init>	()V
    //   262: putfield 83	dK:e	Ljava/util/List;
    //   265: iload_3
    //   266: iconst_1
    //   267: ior
    //   268: istore_3
    //   269: aload_0
    //   270: getfield 83	dK:e	Ljava/util/List;
    //   273: aload_1
    //   274: invokevirtual 85	sc:f	()I
    //   277: invokestatic 91	java/lang/Integer:valueOf	(I)Ljava/lang/Integer;
    //   280: invokeinterface 97 2 0
    //   285: pop
    //   286: goto -249 -> 37
    //   289: astore 13
    //   291: aload 13
    //   293: aload_0
    //   294: invokevirtual 100	sx:a	(LsE;)Lsx;
    //   297: athrow
    //   298: astore 10
    //   300: iload_3
    //   301: iconst_1
    //   302: iand
    //   303: iconst_1
    //   304: if_icmpne +14 -> 318
    //   307: aload_0
    //   308: aload_0
    //   309: getfield 83	dK:e	Ljava/util/List;
    //   312: invokestatic 106	java/util/Collections:unmodifiableList	(Ljava/util/List;)Ljava/util/List;
    //   315: putfield 83	dK:e	Ljava/util/List;
    //   318: iload_3
    //   319: iconst_2
    //   320: iand
    //   321: iconst_2
    //   322: if_icmpne +14 -> 336
    //   325: aload_0
    //   326: aload_0
    //   327: getfield 108	dK:f	Ljava/util/List;
    //   330: invokestatic 106	java/util/Collections:unmodifiableList	(Ljava/util/List;)Ljava/util/List;
    //   333: putfield 108	dK:f	Ljava/util/List;
    //   336: iload_3
    //   337: iconst_4
    //   338: iand
    //   339: iconst_4
    //   340: if_icmpne +14 -> 354
    //   343: aload_0
    //   344: aload_0
    //   345: getfield 110	dK:g	Ljava/util/List;
    //   348: invokestatic 106	java/util/Collections:unmodifiableList	(Ljava/util/List;)Ljava/util/List;
    //   351: putfield 110	dK:g	Ljava/util/List;
    //   354: iload_3
    //   355: bipush 8
    //   357: iand
    //   358: bipush 8
    //   360: if_icmpne +14 -> 374
    //   363: aload_0
    //   364: aload_0
    //   365: getfield 112	dK:h	Ljava/util/List;
    //   368: invokestatic 106	java/util/Collections:unmodifiableList	(Ljava/util/List;)Ljava/util/List;
    //   371: putfield 112	dK:h	Ljava/util/List;
    //   374: iload_3
    //   375: bipush 16
    //   377: iand
    //   378: bipush 16
    //   380: if_icmpne +14 -> 394
    //   383: aload_0
    //   384: aload_0
    //   385: getfield 114	dK:i	Ljava/util/List;
    //   388: invokestatic 106	java/util/Collections:unmodifiableList	(Ljava/util/List;)Ljava/util/List;
    //   391: putfield 114	dK:i	Ljava/util/List;
    //   394: iload_3
    //   395: bipush 32
    //   397: iand
    //   398: bipush 32
    //   400: if_icmpne +14 -> 414
    //   403: aload_0
    //   404: aload_0
    //   405: getfield 116	dK:j	Ljava/util/List;
    //   408: invokestatic 106	java/util/Collections:unmodifiableList	(Ljava/util/List;)Ljava/util/List;
    //   411: putfield 116	dK:j	Ljava/util/List;
    //   414: iload_3
    //   415: bipush 64
    //   417: iand
    //   418: bipush 64
    //   420: if_icmpne +14 -> 434
    //   423: aload_0
    //   424: aload_0
    //   425: getfield 118	dK:k	Ljava/util/List;
    //   428: invokestatic 106	java/util/Collections:unmodifiableList	(Ljava/util/List;)Ljava/util/List;
    //   431: putfield 118	dK:k	Ljava/util/List;
    //   434: iload_3
    //   435: sipush 128
    //   438: iand
    //   439: sipush 128
    //   442: if_icmpne +14 -> 456
    //   445: aload_0
    //   446: aload_0
    //   447: getfield 120	dK:l	Ljava/util/List;
    //   450: invokestatic 106	java/util/Collections:unmodifiableList	(Ljava/util/List;)Ljava/util/List;
    //   453: putfield 120	dK:l	Ljava/util/List;
    //   456: iload_3
    //   457: sipush 256
    //   460: iand
    //   461: sipush 256
    //   464: if_icmpne +14 -> 478
    //   467: aload_0
    //   468: aload_0
    //   469: getfield 122	dK:m	Ljava/util/List;
    //   472: invokestatic 106	java/util/Collections:unmodifiableList	(Ljava/util/List;)Ljava/util/List;
    //   475: putfield 122	dK:m	Ljava/util/List;
    //   478: iload_3
    //   479: sipush 512
    //   482: iand
    //   483: sipush 512
    //   486: if_icmpne +14 -> 500
    //   489: aload_0
    //   490: aload_0
    //   491: getfield 124	dK:n	Ljava/util/List;
    //   494: invokestatic 106	java/util/Collections:unmodifiableList	(Ljava/util/List;)Ljava/util/List;
    //   497: putfield 124	dK:n	Ljava/util/List;
    //   500: aload 5
    //   502: invokevirtual 126	se:a	()V
    //   505: aload_0
    //   506: aload 4
    //   508: invokevirtual 131	sb:a	()LrZ;
    //   511: putfield 133	dK:d	LrZ;
    //   514: aload_0
    //   515: invokevirtual 136	dK:R	()V
    //   518: aload 10
    //   520: athrow
    //   521: aload_1
    //   522: aload_1
    //   523: invokevirtual 139	sc:s	()I
    //   526: invokevirtual 142	sc:c	(I)I
    //   529: istore 42
    //   531: iload_3
    //   532: iconst_1
    //   533: iand
    //   534: iconst_1
    //   535: if_icmpeq +25 -> 560
    //   538: aload_1
    //   539: invokevirtual 145	sc:w	()I
    //   542: ifle +18 -> 560
    //   545: aload_0
    //   546: new 80	java/util/ArrayList
    //   549: dup
    //   550: invokespecial 81	java/util/ArrayList:<init>	()V
    //   553: putfield 83	dK:e	Ljava/util/List;
    //   556: iload_3
    //   557: iconst_1
    //   558: ior
    //   559: istore_3
    //   560: aload_1
    //   561: invokevirtual 145	sc:w	()I
    //   564: ifle +42 -> 606
    //   567: aload_0
    //   568: getfield 83	dK:e	Ljava/util/List;
    //   571: aload_1
    //   572: invokevirtual 85	sc:f	()I
    //   575: invokestatic 91	java/lang/Integer:valueOf	(I)Ljava/lang/Integer;
    //   578: invokeinterface 97 2 0
    //   583: pop
    //   584: goto -24 -> 560
    //   587: astore 9
    //   589: new 53	sx
    //   592: dup
    //   593: aload 9
    //   595: invokevirtual 149	java/io/IOException:getMessage	()Ljava/lang/String;
    //   598: invokespecial 152	sx:<init>	(Ljava/lang/String;)V
    //   601: aload_0
    //   602: invokevirtual 100	sx:a	(LsE;)Lsx;
    //   605: athrow
    //   606: aload_1
    //   607: iload 42
    //   609: invokevirtual 155	sc:d	(I)V
    //   612: goto -575 -> 37
    //   615: iload_3
    //   616: iconst_2
    //   617: iand
    //   618: iconst_2
    //   619: if_icmpeq +18 -> 637
    //   622: aload_0
    //   623: new 80	java/util/ArrayList
    //   626: dup
    //   627: invokespecial 81	java/util/ArrayList:<init>	()V
    //   630: putfield 108	dK:f	Ljava/util/List;
    //   633: iload_3
    //   634: iconst_2
    //   635: ior
    //   636: istore_3
    //   637: aload_0
    //   638: getfield 108	dK:f	Ljava/util/List;
    //   641: aload_1
    //   642: invokevirtual 85	sc:f	()I
    //   645: invokestatic 91	java/lang/Integer:valueOf	(I)Ljava/lang/Integer;
    //   648: invokeinterface 97 2 0
    //   653: pop
    //   654: goto -617 -> 37
    //   657: aload_1
    //   658: aload_1
    //   659: invokevirtual 139	sc:s	()I
    //   662: invokevirtual 142	sc:c	(I)I
    //   665: istore 39
    //   667: iload_3
    //   668: iconst_2
    //   669: iand
    //   670: iconst_2
    //   671: if_icmpeq +25 -> 696
    //   674: aload_1
    //   675: invokevirtual 145	sc:w	()I
    //   678: ifle +18 -> 696
    //   681: aload_0
    //   682: new 80	java/util/ArrayList
    //   685: dup
    //   686: invokespecial 81	java/util/ArrayList:<init>	()V
    //   689: putfield 108	dK:f	Ljava/util/List;
    //   692: iload_3
    //   693: iconst_2
    //   694: ior
    //   695: istore_3
    //   696: aload_1
    //   697: invokevirtual 145	sc:w	()I
    //   700: ifle +23 -> 723
    //   703: aload_0
    //   704: getfield 108	dK:f	Ljava/util/List;
    //   707: aload_1
    //   708: invokevirtual 85	sc:f	()I
    //   711: invokestatic 91	java/lang/Integer:valueOf	(I)Ljava/lang/Integer;
    //   714: invokeinterface 97 2 0
    //   719: pop
    //   720: goto -24 -> 696
    //   723: aload_1
    //   724: iload 39
    //   726: invokevirtual 155	sc:d	(I)V
    //   729: goto -692 -> 37
    //   732: iload_3
    //   733: iconst_4
    //   734: iand
    //   735: iconst_4
    //   736: if_icmpeq +18 -> 754
    //   739: aload_0
    //   740: new 80	java/util/ArrayList
    //   743: dup
    //   744: invokespecial 81	java/util/ArrayList:<init>	()V
    //   747: putfield 110	dK:g	Ljava/util/List;
    //   750: iload_3
    //   751: iconst_4
    //   752: ior
    //   753: istore_3
    //   754: aload_0
    //   755: getfield 110	dK:g	Ljava/util/List;
    //   758: aload_1
    //   759: invokevirtual 85	sc:f	()I
    //   762: invokestatic 91	java/lang/Integer:valueOf	(I)Ljava/lang/Integer;
    //   765: invokeinterface 97 2 0
    //   770: pop
    //   771: goto -734 -> 37
    //   774: aload_1
    //   775: aload_1
    //   776: invokevirtual 139	sc:s	()I
    //   779: invokevirtual 142	sc:c	(I)I
    //   782: istore 36
    //   784: iload_3
    //   785: iconst_4
    //   786: iand
    //   787: iconst_4
    //   788: if_icmpeq +25 -> 813
    //   791: aload_1
    //   792: invokevirtual 145	sc:w	()I
    //   795: ifle +18 -> 813
    //   798: aload_0
    //   799: new 80	java/util/ArrayList
    //   802: dup
    //   803: invokespecial 81	java/util/ArrayList:<init>	()V
    //   806: putfield 110	dK:g	Ljava/util/List;
    //   809: iload_3
    //   810: iconst_4
    //   811: ior
    //   812: istore_3
    //   813: aload_1
    //   814: invokevirtual 145	sc:w	()I
    //   817: ifle +23 -> 840
    //   820: aload_0
    //   821: getfield 110	dK:g	Ljava/util/List;
    //   824: aload_1
    //   825: invokevirtual 85	sc:f	()I
    //   828: invokestatic 91	java/lang/Integer:valueOf	(I)Ljava/lang/Integer;
    //   831: invokeinterface 97 2 0
    //   836: pop
    //   837: goto -24 -> 813
    //   840: aload_1
    //   841: iload 36
    //   843: invokevirtual 155	sc:d	(I)V
    //   846: goto -809 -> 37
    //   849: iload_3
    //   850: bipush 8
    //   852: iand
    //   853: bipush 8
    //   855: if_icmpeq +19 -> 874
    //   858: aload_0
    //   859: new 80	java/util/ArrayList
    //   862: dup
    //   863: invokespecial 81	java/util/ArrayList:<init>	()V
    //   866: putfield 112	dK:h	Ljava/util/List;
    //   869: iload_3
    //   870: bipush 8
    //   872: ior
    //   873: istore_3
    //   874: aload_0
    //   875: getfield 112	dK:h	Ljava/util/List;
    //   878: aload_1
    //   879: invokevirtual 85	sc:f	()I
    //   882: invokestatic 91	java/lang/Integer:valueOf	(I)Ljava/lang/Integer;
    //   885: invokeinterface 97 2 0
    //   890: pop
    //   891: goto -854 -> 37
    //   894: aload_1
    //   895: aload_1
    //   896: invokevirtual 139	sc:s	()I
    //   899: invokevirtual 142	sc:c	(I)I
    //   902: istore 33
    //   904: iload_3
    //   905: bipush 8
    //   907: iand
    //   908: bipush 8
    //   910: if_icmpeq +26 -> 936
    //   913: aload_1
    //   914: invokevirtual 145	sc:w	()I
    //   917: ifle +19 -> 936
    //   920: aload_0
    //   921: new 80	java/util/ArrayList
    //   924: dup
    //   925: invokespecial 81	java/util/ArrayList:<init>	()V
    //   928: putfield 112	dK:h	Ljava/util/List;
    //   931: iload_3
    //   932: bipush 8
    //   934: ior
    //   935: istore_3
    //   936: aload_1
    //   937: invokevirtual 145	sc:w	()I
    //   940: ifle +23 -> 963
    //   943: aload_0
    //   944: getfield 112	dK:h	Ljava/util/List;
    //   947: aload_1
    //   948: invokevirtual 85	sc:f	()I
    //   951: invokestatic 91	java/lang/Integer:valueOf	(I)Ljava/lang/Integer;
    //   954: invokeinterface 97 2 0
    //   959: pop
    //   960: goto -24 -> 936
    //   963: aload_1
    //   964: iload 33
    //   966: invokevirtual 155	sc:d	(I)V
    //   969: goto -932 -> 37
    //   972: iload_3
    //   973: bipush 16
    //   975: iand
    //   976: bipush 16
    //   978: if_icmpeq +19 -> 997
    //   981: aload_0
    //   982: new 80	java/util/ArrayList
    //   985: dup
    //   986: invokespecial 81	java/util/ArrayList:<init>	()V
    //   989: putfield 114	dK:i	Ljava/util/List;
    //   992: iload_3
    //   993: bipush 16
    //   995: ior
    //   996: istore_3
    //   997: aload_0
    //   998: getfield 114	dK:i	Ljava/util/List;
    //   1001: aload_1
    //   1002: invokevirtual 85	sc:f	()I
    //   1005: invokestatic 91	java/lang/Integer:valueOf	(I)Ljava/lang/Integer;
    //   1008: invokeinterface 97 2 0
    //   1013: pop
    //   1014: goto -977 -> 37
    //   1017: aload_1
    //   1018: aload_1
    //   1019: invokevirtual 139	sc:s	()I
    //   1022: invokevirtual 142	sc:c	(I)I
    //   1025: istore 30
    //   1027: iload_3
    //   1028: bipush 16
    //   1030: iand
    //   1031: bipush 16
    //   1033: if_icmpeq +26 -> 1059
    //   1036: aload_1
    //   1037: invokevirtual 145	sc:w	()I
    //   1040: ifle +19 -> 1059
    //   1043: aload_0
    //   1044: new 80	java/util/ArrayList
    //   1047: dup
    //   1048: invokespecial 81	java/util/ArrayList:<init>	()V
    //   1051: putfield 114	dK:i	Ljava/util/List;
    //   1054: iload_3
    //   1055: bipush 16
    //   1057: ior
    //   1058: istore_3
    //   1059: aload_1
    //   1060: invokevirtual 145	sc:w	()I
    //   1063: ifle +23 -> 1086
    //   1066: aload_0
    //   1067: getfield 114	dK:i	Ljava/util/List;
    //   1070: aload_1
    //   1071: invokevirtual 85	sc:f	()I
    //   1074: invokestatic 91	java/lang/Integer:valueOf	(I)Ljava/lang/Integer;
    //   1077: invokeinterface 97 2 0
    //   1082: pop
    //   1083: goto -24 -> 1059
    //   1086: aload_1
    //   1087: iload 30
    //   1089: invokevirtual 155	sc:d	(I)V
    //   1092: goto -1055 -> 37
    //   1095: iload_3
    //   1096: bipush 32
    //   1098: iand
    //   1099: bipush 32
    //   1101: if_icmpeq +19 -> 1120
    //   1104: aload_0
    //   1105: new 80	java/util/ArrayList
    //   1108: dup
    //   1109: invokespecial 81	java/util/ArrayList:<init>	()V
    //   1112: putfield 116	dK:j	Ljava/util/List;
    //   1115: iload_3
    //   1116: bipush 32
    //   1118: ior
    //   1119: istore_3
    //   1120: aload_0
    //   1121: getfield 116	dK:j	Ljava/util/List;
    //   1124: aload_1
    //   1125: invokevirtual 85	sc:f	()I
    //   1128: invokestatic 91	java/lang/Integer:valueOf	(I)Ljava/lang/Integer;
    //   1131: invokeinterface 97 2 0
    //   1136: pop
    //   1137: goto -1100 -> 37
    //   1140: aload_1
    //   1141: aload_1
    //   1142: invokevirtual 139	sc:s	()I
    //   1145: invokevirtual 142	sc:c	(I)I
    //   1148: istore 27
    //   1150: iload_3
    //   1151: bipush 32
    //   1153: iand
    //   1154: bipush 32
    //   1156: if_icmpeq +26 -> 1182
    //   1159: aload_1
    //   1160: invokevirtual 145	sc:w	()I
    //   1163: ifle +19 -> 1182
    //   1166: aload_0
    //   1167: new 80	java/util/ArrayList
    //   1170: dup
    //   1171: invokespecial 81	java/util/ArrayList:<init>	()V
    //   1174: putfield 116	dK:j	Ljava/util/List;
    //   1177: iload_3
    //   1178: bipush 32
    //   1180: ior
    //   1181: istore_3
    //   1182: aload_1
    //   1183: invokevirtual 145	sc:w	()I
    //   1186: ifle +23 -> 1209
    //   1189: aload_0
    //   1190: getfield 116	dK:j	Ljava/util/List;
    //   1193: aload_1
    //   1194: invokevirtual 85	sc:f	()I
    //   1197: invokestatic 91	java/lang/Integer:valueOf	(I)Ljava/lang/Integer;
    //   1200: invokeinterface 97 2 0
    //   1205: pop
    //   1206: goto -24 -> 1182
    //   1209: aload_1
    //   1210: iload 27
    //   1212: invokevirtual 155	sc:d	(I)V
    //   1215: goto -1178 -> 37
    //   1218: iload_3
    //   1219: bipush 64
    //   1221: iand
    //   1222: bipush 64
    //   1224: if_icmpeq +19 -> 1243
    //   1227: aload_0
    //   1228: new 80	java/util/ArrayList
    //   1231: dup
    //   1232: invokespecial 81	java/util/ArrayList:<init>	()V
    //   1235: putfield 118	dK:k	Ljava/util/List;
    //   1238: iload_3
    //   1239: bipush 64
    //   1241: ior
    //   1242: istore_3
    //   1243: aload_0
    //   1244: getfield 118	dK:k	Ljava/util/List;
    //   1247: aload_1
    //   1248: invokevirtual 85	sc:f	()I
    //   1251: invokestatic 91	java/lang/Integer:valueOf	(I)Ljava/lang/Integer;
    //   1254: invokeinterface 97 2 0
    //   1259: pop
    //   1260: goto -1223 -> 37
    //   1263: aload_1
    //   1264: aload_1
    //   1265: invokevirtual 139	sc:s	()I
    //   1268: invokevirtual 142	sc:c	(I)I
    //   1271: istore 24
    //   1273: iload_3
    //   1274: bipush 64
    //   1276: iand
    //   1277: bipush 64
    //   1279: if_icmpeq +26 -> 1305
    //   1282: aload_1
    //   1283: invokevirtual 145	sc:w	()I
    //   1286: ifle +19 -> 1305
    //   1289: aload_0
    //   1290: new 80	java/util/ArrayList
    //   1293: dup
    //   1294: invokespecial 81	java/util/ArrayList:<init>	()V
    //   1297: putfield 118	dK:k	Ljava/util/List;
    //   1300: iload_3
    //   1301: bipush 64
    //   1303: ior
    //   1304: istore_3
    //   1305: aload_1
    //   1306: invokevirtual 145	sc:w	()I
    //   1309: ifle +23 -> 1332
    //   1312: aload_0
    //   1313: getfield 118	dK:k	Ljava/util/List;
    //   1316: aload_1
    //   1317: invokevirtual 85	sc:f	()I
    //   1320: invokestatic 91	java/lang/Integer:valueOf	(I)Ljava/lang/Integer;
    //   1323: invokeinterface 97 2 0
    //   1328: pop
    //   1329: goto -24 -> 1305
    //   1332: aload_1
    //   1333: iload 24
    //   1335: invokevirtual 155	sc:d	(I)V
    //   1338: goto -1301 -> 37
    //   1341: iload_3
    //   1342: sipush 128
    //   1345: iand
    //   1346: sipush 128
    //   1349: if_icmpeq +20 -> 1369
    //   1352: aload_0
    //   1353: new 80	java/util/ArrayList
    //   1356: dup
    //   1357: invokespecial 81	java/util/ArrayList:<init>	()V
    //   1360: putfield 120	dK:l	Ljava/util/List;
    //   1363: iload_3
    //   1364: sipush 128
    //   1367: ior
    //   1368: istore_3
    //   1369: aload_0
    //   1370: getfield 120	dK:l	Ljava/util/List;
    //   1373: aload_1
    //   1374: invokevirtual 85	sc:f	()I
    //   1377: invokestatic 91	java/lang/Integer:valueOf	(I)Ljava/lang/Integer;
    //   1380: invokeinterface 97 2 0
    //   1385: pop
    //   1386: goto -1349 -> 37
    //   1389: aload_1
    //   1390: aload_1
    //   1391: invokevirtual 139	sc:s	()I
    //   1394: invokevirtual 142	sc:c	(I)I
    //   1397: istore 21
    //   1399: iload_3
    //   1400: sipush 128
    //   1403: iand
    //   1404: sipush 128
    //   1407: if_icmpeq +27 -> 1434
    //   1410: aload_1
    //   1411: invokevirtual 145	sc:w	()I
    //   1414: ifle +20 -> 1434
    //   1417: aload_0
    //   1418: new 80	java/util/ArrayList
    //   1421: dup
    //   1422: invokespecial 81	java/util/ArrayList:<init>	()V
    //   1425: putfield 120	dK:l	Ljava/util/List;
    //   1428: iload_3
    //   1429: sipush 128
    //   1432: ior
    //   1433: istore_3
    //   1434: aload_1
    //   1435: invokevirtual 145	sc:w	()I
    //   1438: ifle +23 -> 1461
    //   1441: aload_0
    //   1442: getfield 120	dK:l	Ljava/util/List;
    //   1445: aload_1
    //   1446: invokevirtual 85	sc:f	()I
    //   1449: invokestatic 91	java/lang/Integer:valueOf	(I)Ljava/lang/Integer;
    //   1452: invokeinterface 97 2 0
    //   1457: pop
    //   1458: goto -24 -> 1434
    //   1461: aload_1
    //   1462: iload 21
    //   1464: invokevirtual 155	sc:d	(I)V
    //   1467: goto -1430 -> 37
    //   1470: iload_3
    //   1471: sipush 256
    //   1474: iand
    //   1475: sipush 256
    //   1478: if_icmpeq +20 -> 1498
    //   1481: aload_0
    //   1482: new 80	java/util/ArrayList
    //   1485: dup
    //   1486: invokespecial 81	java/util/ArrayList:<init>	()V
    //   1489: putfield 122	dK:m	Ljava/util/List;
    //   1492: iload_3
    //   1493: sipush 256
    //   1496: ior
    //   1497: istore_3
    //   1498: aload_0
    //   1499: getfield 122	dK:m	Ljava/util/List;
    //   1502: aload_1
    //   1503: invokevirtual 85	sc:f	()I
    //   1506: invokestatic 91	java/lang/Integer:valueOf	(I)Ljava/lang/Integer;
    //   1509: invokeinterface 97 2 0
    //   1514: pop
    //   1515: goto -1478 -> 37
    //   1518: aload_1
    //   1519: aload_1
    //   1520: invokevirtual 139	sc:s	()I
    //   1523: invokevirtual 142	sc:c	(I)I
    //   1526: istore 18
    //   1528: iload_3
    //   1529: sipush 256
    //   1532: iand
    //   1533: sipush 256
    //   1536: if_icmpeq +27 -> 1563
    //   1539: aload_1
    //   1540: invokevirtual 145	sc:w	()I
    //   1543: ifle +20 -> 1563
    //   1546: aload_0
    //   1547: new 80	java/util/ArrayList
    //   1550: dup
    //   1551: invokespecial 81	java/util/ArrayList:<init>	()V
    //   1554: putfield 122	dK:m	Ljava/util/List;
    //   1557: iload_3
    //   1558: sipush 256
    //   1561: ior
    //   1562: istore_3
    //   1563: aload_1
    //   1564: invokevirtual 145	sc:w	()I
    //   1567: ifle +23 -> 1590
    //   1570: aload_0
    //   1571: getfield 122	dK:m	Ljava/util/List;
    //   1574: aload_1
    //   1575: invokevirtual 85	sc:f	()I
    //   1578: invokestatic 91	java/lang/Integer:valueOf	(I)Ljava/lang/Integer;
    //   1581: invokeinterface 97 2 0
    //   1586: pop
    //   1587: goto -24 -> 1563
    //   1590: aload_1
    //   1591: iload 18
    //   1593: invokevirtual 155	sc:d	(I)V
    //   1596: goto -1559 -> 37
    //   1599: iload_3
    //   1600: sipush 512
    //   1603: iand
    //   1604: sipush 512
    //   1607: if_icmpeq +20 -> 1627
    //   1610: aload_0
    //   1611: new 80	java/util/ArrayList
    //   1614: dup
    //   1615: invokespecial 81	java/util/ArrayList:<init>	()V
    //   1618: putfield 124	dK:n	Ljava/util/List;
    //   1621: iload_3
    //   1622: sipush 512
    //   1625: ior
    //   1626: istore_3
    //   1627: aload_0
    //   1628: getfield 124	dK:n	Ljava/util/List;
    //   1631: aload_1
    //   1632: invokevirtual 85	sc:f	()I
    //   1635: invokestatic 91	java/lang/Integer:valueOf	(I)Ljava/lang/Integer;
    //   1638: invokeinterface 97 2 0
    //   1643: pop
    //   1644: goto -1607 -> 37
    //   1647: aload_1
    //   1648: aload_1
    //   1649: invokevirtual 139	sc:s	()I
    //   1652: invokevirtual 142	sc:c	(I)I
    //   1655: istore 15
    //   1657: iload_3
    //   1658: sipush 512
    //   1661: iand
    //   1662: sipush 512
    //   1665: if_icmpeq +27 -> 1692
    //   1668: aload_1
    //   1669: invokevirtual 145	sc:w	()I
    //   1672: ifle +20 -> 1692
    //   1675: aload_0
    //   1676: new 80	java/util/ArrayList
    //   1679: dup
    //   1680: invokespecial 81	java/util/ArrayList:<init>	()V
    //   1683: putfield 124	dK:n	Ljava/util/List;
    //   1686: iload_3
    //   1687: sipush 512
    //   1690: ior
    //   1691: istore_3
    //   1692: aload_1
    //   1693: invokevirtual 145	sc:w	()I
    //   1696: ifle +23 -> 1719
    //   1699: aload_0
    //   1700: getfield 124	dK:n	Ljava/util/List;
    //   1703: aload_1
    //   1704: invokevirtual 85	sc:f	()I
    //   1707: invokestatic 91	java/lang/Integer:valueOf	(I)Ljava/lang/Integer;
    //   1710: invokeinterface 97 2 0
    //   1715: pop
    //   1716: goto -24 -> 1692
    //   1719: aload_1
    //   1720: iload 15
    //   1722: invokevirtual 155	sc:d	(I)V
    //   1725: goto -1688 -> 37
    //   1728: iload_3
    //   1729: iconst_1
    //   1730: iand
    //   1731: iconst_1
    //   1732: if_icmpne +14 -> 1746
    //   1735: aload_0
    //   1736: aload_0
    //   1737: getfield 83	dK:e	Ljava/util/List;
    //   1740: invokestatic 106	java/util/Collections:unmodifiableList	(Ljava/util/List;)Ljava/util/List;
    //   1743: putfield 83	dK:e	Ljava/util/List;
    //   1746: iload_3
    //   1747: iconst_2
    //   1748: iand
    //   1749: iconst_2
    //   1750: if_icmpne +14 -> 1764
    //   1753: aload_0
    //   1754: aload_0
    //   1755: getfield 108	dK:f	Ljava/util/List;
    //   1758: invokestatic 106	java/util/Collections:unmodifiableList	(Ljava/util/List;)Ljava/util/List;
    //   1761: putfield 108	dK:f	Ljava/util/List;
    //   1764: iload_3
    //   1765: iconst_4
    //   1766: iand
    //   1767: iconst_4
    //   1768: if_icmpne +14 -> 1782
    //   1771: aload_0
    //   1772: aload_0
    //   1773: getfield 110	dK:g	Ljava/util/List;
    //   1776: invokestatic 106	java/util/Collections:unmodifiableList	(Ljava/util/List;)Ljava/util/List;
    //   1779: putfield 110	dK:g	Ljava/util/List;
    //   1782: iload_3
    //   1783: bipush 8
    //   1785: iand
    //   1786: bipush 8
    //   1788: if_icmpne +14 -> 1802
    //   1791: aload_0
    //   1792: aload_0
    //   1793: getfield 112	dK:h	Ljava/util/List;
    //   1796: invokestatic 106	java/util/Collections:unmodifiableList	(Ljava/util/List;)Ljava/util/List;
    //   1799: putfield 112	dK:h	Ljava/util/List;
    //   1802: iload_3
    //   1803: bipush 16
    //   1805: iand
    //   1806: bipush 16
    //   1808: if_icmpne +14 -> 1822
    //   1811: aload_0
    //   1812: aload_0
    //   1813: getfield 114	dK:i	Ljava/util/List;
    //   1816: invokestatic 106	java/util/Collections:unmodifiableList	(Ljava/util/List;)Ljava/util/List;
    //   1819: putfield 114	dK:i	Ljava/util/List;
    //   1822: iload_3
    //   1823: bipush 32
    //   1825: iand
    //   1826: bipush 32
    //   1828: if_icmpne +14 -> 1842
    //   1831: aload_0
    //   1832: aload_0
    //   1833: getfield 116	dK:j	Ljava/util/List;
    //   1836: invokestatic 106	java/util/Collections:unmodifiableList	(Ljava/util/List;)Ljava/util/List;
    //   1839: putfield 116	dK:j	Ljava/util/List;
    //   1842: iload_3
    //   1843: bipush 64
    //   1845: iand
    //   1846: bipush 64
    //   1848: if_icmpne +14 -> 1862
    //   1851: aload_0
    //   1852: aload_0
    //   1853: getfield 118	dK:k	Ljava/util/List;
    //   1856: invokestatic 106	java/util/Collections:unmodifiableList	(Ljava/util/List;)Ljava/util/List;
    //   1859: putfield 118	dK:k	Ljava/util/List;
    //   1862: iload_3
    //   1863: sipush 128
    //   1866: iand
    //   1867: sipush 128
    //   1870: if_icmpne +14 -> 1884
    //   1873: aload_0
    //   1874: aload_0
    //   1875: getfield 120	dK:l	Ljava/util/List;
    //   1878: invokestatic 106	java/util/Collections:unmodifiableList	(Ljava/util/List;)Ljava/util/List;
    //   1881: putfield 120	dK:l	Ljava/util/List;
    //   1884: iload_3
    //   1885: sipush 256
    //   1888: iand
    //   1889: sipush 256
    //   1892: if_icmpne +14 -> 1906
    //   1895: aload_0
    //   1896: aload_0
    //   1897: getfield 122	dK:m	Ljava/util/List;
    //   1900: invokestatic 106	java/util/Collections:unmodifiableList	(Ljava/util/List;)Ljava/util/List;
    //   1903: putfield 122	dK:m	Ljava/util/List;
    //   1906: iload_3
    //   1907: sipush 512
    //   1910: iand
    //   1911: sipush 512
    //   1914: if_icmpne +14 -> 1928
    //   1917: aload_0
    //   1918: aload_0
    //   1919: getfield 124	dK:n	Ljava/util/List;
    //   1922: invokestatic 106	java/util/Collections:unmodifiableList	(Ljava/util/List;)Ljava/util/List;
    //   1925: putfield 124	dK:n	Ljava/util/List;
    //   1928: aload 5
    //   1930: invokevirtual 126	se:a	()V
    //   1933: aload_0
    //   1934: aload 4
    //   1936: invokevirtual 131	sb:a	()LrZ;
    //   1939: putfield 133	dK:d	LrZ;
    //   1942: aload_0
    //   1943: invokevirtual 136	dK:R	()V
    //   1946: return
    //   1947: astore 8
    //   1949: aload_0
    //   1950: aload 4
    //   1952: invokevirtual 131	sb:a	()LrZ;
    //   1955: putfield 133	dK:d	LrZ;
    //   1958: goto -16 -> 1942
    //   1961: astore 7
    //   1963: aload_0
    //   1964: aload 4
    //   1966: invokevirtual 131	sb:a	()LrZ;
    //   1969: putfield 133	dK:d	LrZ;
    //   1972: aload 7
    //   1974: athrow
    //   1975: astore 12
    //   1977: aload_0
    //   1978: aload 4
    //   1980: invokevirtual 131	sb:a	()LrZ;
    //   1983: putfield 133	dK:d	LrZ;
    //   1986: goto -1472 -> 514
    //   1989: astore 11
    //   1991: aload_0
    //   1992: aload 4
    //   1994: invokevirtual 131	sb:a	()LrZ;
    //   1997: putfield 133	dK:d	LrZ;
    //   2000: aload 11
    //   2002: athrow
    //   2003: iconst_1
    //   2004: istore 6
    //   2006: goto -1969 -> 37
    // Local variable table:
    //   start	length	slot	name	signature
    //   0	2009	0	this	dK
    //   0	2009	1	paramsc	sc
    //   0	2009	2	paramsg	sg
    //   21	1890	3	i1	int
    //   25	1968	4	localsb	sb
    //   32	1897	5	localse	se
    //   35	1970	6	i2	int
    //   1961	12	7	localObject1	Object
    //   1947	1	8	localIOException1	java.io.IOException
    //   587	7	9	localIOException2	java.io.IOException
    //   298	221	10	localObject2	Object
    //   1989	12	11	localObject3	Object
    //   1975	1	12	localIOException3	java.io.IOException
    //   289	3	13	localsx	sx
    //   46	188	14	i3	int
    //   1655	66	15	i4	int
    //   1526	66	18	i5	int
    //   1397	66	21	i6	int
    //   1271	63	24	i7	int
    //   1148	63	27	i8	int
    //   1025	63	30	i9	int
    //   902	63	33	i10	int
    //   782	60	36	i11	int
    //   665	60	39	i12	int
    //   529	79	42	i13	int
    // Exception table:
    //   from	to	target	type
    //   42	286	289	sx
    //   521	584	289	sx
    //   606	1725	289	sx
    //   42	286	298	finally
    //   291	298	298	finally
    //   521	584	298	finally
    //   589	606	298	finally
    //   606	1725	298	finally
    //   42	286	587	java/io/IOException
    //   521	584	587	java/io/IOException
    //   606	1725	587	java/io/IOException
    //   1928	1933	1947	java/io/IOException
    //   1928	1933	1961	finally
    //   500	505	1975	java/io/IOException
    //   500	505	1989	finally
  }
  
  private dK(sn paramsn)
  {
    super(paramsn);
    this.d = paramsn.r();
  }
  
  private dK(boolean paramBoolean)
  {
    this.d = rZ.a;
  }
  
  public static dM B()
  {
    return dM.i();
  }
  
  private void E()
  {
    this.e = Collections.emptyList();
    this.f = Collections.emptyList();
    this.g = Collections.emptyList();
    this.h = Collections.emptyList();
    this.i = Collections.emptyList();
    this.j = Collections.emptyList();
    this.k = Collections.emptyList();
    this.l = Collections.emptyList();
    this.m = Collections.emptyList();
    this.n = Collections.emptyList();
  }
  
  public static dK a()
  {
    return c;
  }
  
  public static dM a(dK paramdK)
  {
    return B().a(paramdK);
  }
  
  public int A()
  {
    return this.n.size();
  }
  
  public dM C()
  {
    return B();
  }
  
  public dM D()
  {
    return a(this);
  }
  
  public dK b()
  {
    return c;
  }
  
  public sI<dK> c()
  {
    return a;
  }
  
  public List<Integer> d()
  {
    return this.e;
  }
  
  public int e()
  {
    return this.e.size();
  }
  
  public boolean equals(Object paramObject)
  {
    boolean bool1 = true;
    if (paramObject == this) {}
    label49:
    label309:
    label315:
    label319:
    for (;;)
    {
      return bool1;
      if (!(paramObject instanceof dK))
      {
        bool1 = super.equals(paramObject);
      }
      else
      {
        dK localdK = (dK)paramObject;
        boolean bool2;
        boolean bool3;
        label73:
        boolean bool4;
        label97:
        boolean bool5;
        label121:
        boolean bool6;
        boolean bool7;
        boolean bool8;
        label193:
        boolean bool9;
        if (d().equals(localdK.d()))
        {
          bool2 = bool1;
          if ((!bool2) || (!f().equals(localdK.f()))) {
            break label273;
          }
          bool3 = bool1;
          if ((!bool3) || (!h().equals(localdK.h()))) {
            break label279;
          }
          bool4 = bool1;
          if ((!bool4) || (!k().equals(localdK.k()))) {
            break label285;
          }
          bool5 = bool1;
          if ((!bool5) || (!m().equals(localdK.m()))) {
            break label291;
          }
          bool6 = bool1;
          if ((!bool6) || (!r().equals(localdK.r()))) {
            break label297;
          }
          bool7 = bool1;
          if ((!bool7) || (!t().equals(localdK.t()))) {
            break label303;
          }
          bool8 = bool1;
          if ((!bool8) || (!v().equals(localdK.v()))) {
            break label309;
          }
          bool9 = bool1;
          label217:
          if ((!bool9) || (!x().equals(localdK.x()))) {
            break label315;
          }
        }
        for (boolean bool10 = bool1;; bool10 = false)
        {
          if ((bool10) && (z().equals(localdK.z()))) {
            break label319;
          }
          bool1 = false;
          break;
          bool2 = false;
          break label49;
          bool3 = false;
          break label73;
          bool4 = false;
          break label97;
          bool5 = false;
          break label121;
          bool6 = false;
          break label145;
          bool7 = false;
          break label169;
          bool8 = false;
          break label193;
          bool9 = false;
          break label217;
        }
      }
    }
  }
  
  public List<Integer> f()
  {
    return this.f;
  }
  
  public int g()
  {
    return this.f.size();
  }
  
  public List<Integer> h()
  {
    return this.g;
  }
  
  public int hashCode()
  {
    int i2;
    if (this.b != 0) {
      i2 = this.b;
    }
    for (;;)
    {
      return i2;
      int i1 = 779 + dK.class.hashCode();
      if (e() > 0) {
        i1 = 53 * (1 + i1 * 37) + d().hashCode();
      }
      if (g() > 0) {
        i1 = 53 * (2 + i1 * 37) + f().hashCode();
      }
      if (i() > 0) {
        i1 = 53 * (3 + i1 * 37) + h().hashCode();
      }
      if (l() > 0) {
        i1 = 53 * (4 + i1 * 37) + k().hashCode();
      }
      if (q() > 0) {
        i1 = 53 * (5 + i1 * 37) + m().hashCode();
      }
      if (s() > 0) {
        i1 = 53 * (6 + i1 * 37) + r().hashCode();
      }
      if (u() > 0) {
        i1 = 53 * (7 + i1 * 37) + t().hashCode();
      }
      if (w() > 0) {
        i1 = 53 * (8 + i1 * 37) + v().hashCode();
      }
      if (y() > 0) {
        i1 = 53 * (9 + i1 * 37) + x().hashCode();
      }
      if (A() > 0) {
        i1 = 53 * (10 + i1 * 37) + z().hashCode();
      }
      i2 = i1 * 29 + this.d.hashCode();
      this.b = i2;
    }
  }
  
  public int i()
  {
    return this.g.size();
  }
  
  public final boolean j()
  {
    int i1 = 1;
    int i2 = this.o;
    if (i2 != -1) {
      if (i2 != i1) {}
    }
    for (;;)
    {
      return i1;
      i1 = 0;
      continue;
      this.o = i1;
    }
  }
  
  public List<Integer> k()
  {
    return this.h;
  }
  
  public int l()
  {
    return this.h.size();
  }
  
  public List<Integer> m()
  {
    return this.i;
  }
  
  public int q()
  {
    return this.i.size();
  }
  
  public List<Integer> r()
  {
    return this.j;
  }
  
  public int s()
  {
    return this.j.size();
  }
  
  public List<Integer> t()
  {
    return this.k;
  }
  
  public int u()
  {
    return this.k.size();
  }
  
  public List<Integer> v()
  {
    return this.l;
  }
  
  public int w()
  {
    return this.l.size();
  }
  
  public List<Integer> x()
  {
    return this.m;
  }
  
  public int y()
  {
    return this.m.size();
  }
  
  public List<Integer> z()
  {
    return this.n;
  }
}


/* Location:           C:\Users\dreadiscool\Desktop\tools\classes-dex2jar.jar
 * Qualified Name:     dK
 * JD-Core Version:    0.7.0.1
 */