import org.json.JSONObject;

class FT
  implements Runnable
{
  FT(FS paramFS, JSONObject paramJSONObject) {}
  
  /* Error */
  public void run()
  {
    // Byte code:
    //   0: iconst_1
    //   1: istore_1
    //   2: aload_0
    //   3: getfield 14	FT:b	LFS;
    //   6: getfield 30	FS:c	Lcom/yik/yak/data/models/YakkerLocation;
    //   9: invokevirtual 36	com/yik/yak/data/models/YakkerLocation:getProvider	()Ljava/lang/String;
    //   12: ldc 38
    //   14: invokevirtual 44	java/lang/String:equals	(Ljava/lang/Object;)Z
    //   17: ifeq +169 -> 186
    //   20: aload_0
    //   21: getfield 14	FT:b	LFS;
    //   24: getfield 48	FS:f	LFR;
    //   27: new 50	java/util/ArrayList
    //   30: dup
    //   31: invokespecial 51	java/util/ArrayList:<init>	()V
    //   34: putfield 57	FR:l	Ljava/util/ArrayList;
    //   37: new 59	CK
    //   40: dup
    //   41: invokespecial 60	CK:<init>	()V
    //   44: astore 30
    //   46: aload 30
    //   48: aload_0
    //   49: getfield 14	FT:b	LFS;
    //   52: getfield 48	FS:f	LFR;
    //   55: invokevirtual 64	FR:getResources	()Landroid/content/res/Resources;
    //   58: ldc 65
    //   60: invokevirtual 71	android/content/res/Resources:getString	(I)Ljava/lang/String;
    //   63: putfield 75	CK:k	Ljava/lang/String;
    //   66: aload 30
    //   68: iload_1
    //   69: putfield 79	CK:h	I
    //   72: aload_0
    //   73: getfield 14	FT:b	LFS;
    //   76: getfield 83	FS:d	LCM;
    //   79: invokevirtual 88	CM:d	()Z
    //   82: ifeq +273 -> 355
    //   85: aload_0
    //   86: getfield 14	FT:b	LFS;
    //   89: getfield 83	FS:d	LCM;
    //   92: invokevirtual 90	CM:c	()Z
    //   95: ifne +260 -> 355
    //   98: aload 30
    //   100: aload_0
    //   101: getfield 14	FT:b	LFS;
    //   104: getfield 48	FS:f	LFR;
    //   107: invokevirtual 64	FR:getResources	()Landroid/content/res/Resources;
    //   110: ldc 91
    //   112: invokevirtual 71	android/content/res/Resources:getString	(I)Ljava/lang/String;
    //   115: putfield 93	CK:l	Ljava/lang/String;
    //   118: aload 30
    //   120: iconst_0
    //   121: putfield 95	CK:f	I
    //   124: aload 30
    //   126: iload_1
    //   127: putfield 98	CK:g	I
    //   130: aload 30
    //   132: ldc 99
    //   134: putfield 101	CK:d	I
    //   137: aload 30
    //   139: ldc 102
    //   141: putfield 105	CK:i	I
    //   144: aload_0
    //   145: getfield 14	FT:b	LFS;
    //   148: getfield 48	FS:f	LFR;
    //   151: aconst_null
    //   152: putfield 108	FR:m	Ljava/util/ArrayList;
    //   155: aload_0
    //   156: getfield 14	FT:b	LFS;
    //   159: getfield 48	FS:f	LFR;
    //   162: getstatic 113	Fn:a	LFn;
    //   165: putfield 116	FR:v	LFn;
    //   168: aload_0
    //   169: getfield 14	FT:b	LFS;
    //   172: getfield 48	FS:f	LFR;
    //   175: getfield 57	FR:l	Ljava/util/ArrayList;
    //   178: aload 30
    //   180: invokevirtual 119	java/util/ArrayList:add	(Ljava/lang/Object;)Z
    //   183: pop
    //   184: iconst_0
    //   185: istore_1
    //   186: new 50	java/util/ArrayList
    //   189: dup
    //   190: invokespecial 51	java/util/ArrayList:<init>	()V
    //   193: astore_2
    //   194: aload_0
    //   195: getfield 16	FT:a	Lorg/json/JSONObject;
    //   198: ldc 121
    //   200: invokevirtual 127	org/json/JSONObject:getJSONArray	(Ljava/lang/String;)Lorg/json/JSONArray;
    //   203: astore 19
    //   205: aload_0
    //   206: getfield 14	FT:b	LFS;
    //   209: aload 19
    //   211: invokevirtual 133	org/json/JSONArray:length	()I
    //   214: putfield 135	FS:b	I
    //   217: iload_1
    //   218: ifeq +184 -> 402
    //   221: iconst_1
    //   222: anewarray 4	java/lang/Object
    //   225: astore 20
    //   227: aload 20
    //   229: iconst_0
    //   230: ldc 137
    //   232: aastore
    //   233: aload_0
    //   234: aload 20
    //   236: invokestatic 142	Iq:a	(Ljava/lang/Object;[Ljava/lang/Object;)V
    //   239: iconst_0
    //   240: istore 21
    //   242: iload 21
    //   244: aload_0
    //   245: getfield 14	FT:b	LFS;
    //   248: getfield 135	FS:b	I
    //   251: if_icmpge +284 -> 535
    //   254: new 59	CK
    //   257: dup
    //   258: aload 19
    //   260: iload 21
    //   262: invokevirtual 146	org/json/JSONArray:getJSONObject	(I)Lorg/json/JSONObject;
    //   265: aload_0
    //   266: getfield 14	FT:b	LFS;
    //   269: getfield 48	FS:f	LFR;
    //   272: getfield 149	FR:c	Z
    //   275: aload_0
    //   276: getfield 14	FT:b	LFS;
    //   279: getfield 48	FS:f	LFR;
    //   282: getfield 151	FR:d	Z
    //   285: aload_0
    //   286: getfield 14	FT:b	LFS;
    //   289: getfield 48	FS:f	LFR;
    //   292: getfield 154	FR:e	Z
    //   295: aload_0
    //   296: getfield 14	FT:b	LFS;
    //   299: getfield 157	FS:e	Landroid/content/Context;
    //   302: aload_0
    //   303: getfield 14	FT:b	LFS;
    //   306: getfield 135	FS:b	I
    //   309: iload 21
    //   311: isub
    //   312: invokespecial 160	CK:<init>	(Lorg/json/JSONObject;ZZZLandroid/content/Context;I)V
    //   315: astore 22
    //   317: aload_0
    //   318: getfield 14	FT:b	LFS;
    //   321: getfield 48	FS:f	LFR;
    //   324: getfield 116	FR:v	LFn;
    //   327: getstatic 162	Fn:b	LFn;
    //   330: if_acmpne +48 -> 378
    //   333: aload_0
    //   334: getfield 14	FT:b	LFS;
    //   337: getfield 48	FS:f	LFR;
    //   340: getfield 108	FR:m	Ljava/util/ArrayList;
    //   343: aload 22
    //   345: invokevirtual 119	java/util/ArrayList:add	(Ljava/lang/Object;)Z
    //   348: pop
    //   349: iinc 21 1
    //   352: goto -110 -> 242
    //   355: aload 30
    //   357: aload_0
    //   358: getfield 14	FT:b	LFS;
    //   361: getfield 48	FS:f	LFR;
    //   364: invokevirtual 64	FR:getResources	()Landroid/content/res/Resources;
    //   367: ldc 163
    //   369: invokevirtual 71	android/content/res/Resources:getString	(I)Ljava/lang/String;
    //   372: putfield 93	CK:l	Ljava/lang/String;
    //   375: goto -257 -> 118
    //   378: aload_0
    //   379: getfield 14	FT:b	LFS;
    //   382: getfield 48	FS:f	LFR;
    //   385: getfield 57	FR:l	Ljava/util/ArrayList;
    //   388: aload 22
    //   390: invokevirtual 119	java/util/ArrayList:add	(Ljava/lang/Object;)Z
    //   393: pop
    //   394: goto -45 -> 349
    //   397: astore_3
    //   398: aload_3
    //   399: invokevirtual 166	org/json/JSONException:printStackTrace	()V
    //   402: aload_0
    //   403: getfield 16	FT:a	Lorg/json/JSONObject;
    //   406: ldc 168
    //   408: invokevirtual 172	org/json/JSONObject:has	(Ljava/lang/String;)Z
    //   411: ifeq +433 -> 844
    //   414: aload_2
    //   415: new 174	CG
    //   418: dup
    //   419: ldc 176
    //   421: ldc 176
    //   423: iconst_0
    //   424: ldc 178
    //   426: iconst_0
    //   427: iconst_0
    //   428: iconst_0
    //   429: invokespecial 181	CG:<init>	(Ljava/lang/String;Ljava/lang/String;ILjava/lang/String;III)V
    //   432: invokeinterface 184 2 0
    //   437: pop
    //   438: aload_0
    //   439: getfield 16	FT:a	Lorg/json/JSONObject;
    //   442: ldc 168
    //   444: invokevirtual 127	org/json/JSONObject:getJSONArray	(Ljava/lang/String;)Lorg/json/JSONArray;
    //   447: astore 15
    //   449: iconst_0
    //   450: istore 16
    //   452: iload 16
    //   454: aload 15
    //   456: invokevirtual 133	org/json/JSONArray:length	()I
    //   459: if_icmpge +223 -> 682
    //   462: aload 15
    //   464: iload 16
    //   466: invokevirtual 146	org/json/JSONArray:getJSONObject	(I)Lorg/json/JSONObject;
    //   469: astore 17
    //   471: aload_2
    //   472: new 174	CG
    //   475: dup
    //   476: ldc 176
    //   478: aload 17
    //   480: ldc 186
    //   482: invokevirtual 189	org/json/JSONObject:getString	(Ljava/lang/String;)Ljava/lang/String;
    //   485: aload 17
    //   487: ldc 191
    //   489: invokevirtual 195	org/json/JSONObject:getInt	(Ljava/lang/String;)I
    //   492: aload 17
    //   494: ldc 197
    //   496: invokevirtual 189	org/json/JSONObject:getString	(Ljava/lang/String;)Ljava/lang/String;
    //   499: aload 17
    //   501: ldc 199
    //   503: invokevirtual 195	org/json/JSONObject:getInt	(Ljava/lang/String;)I
    //   506: aload 17
    //   508: ldc 201
    //   510: invokevirtual 195	org/json/JSONObject:getInt	(Ljava/lang/String;)I
    //   513: aload 17
    //   515: ldc 203
    //   517: invokevirtual 195	org/json/JSONObject:getInt	(Ljava/lang/String;)I
    //   520: invokespecial 181	CG:<init>	(Ljava/lang/String;Ljava/lang/String;ILjava/lang/String;III)V
    //   523: invokeinterface 184 2 0
    //   528: pop
    //   529: iinc 16 1
    //   532: goto -80 -> 452
    //   535: aload_0
    //   536: getfield 16	FT:a	Lorg/json/JSONObject;
    //   539: ldc 205
    //   541: invokevirtual 172	org/json/JSONObject:has	(Ljava/lang/String;)Z
    //   544: ifeq +34 -> 578
    //   547: aload_0
    //   548: getfield 16	FT:a	Lorg/json/JSONObject;
    //   551: ldc 205
    //   553: invokevirtual 189	org/json/JSONObject:getString	(Ljava/lang/String;)Ljava/lang/String;
    //   556: astore 29
    //   558: aload 29
    //   560: ifnull +18 -> 578
    //   563: aload 29
    //   565: ldc 207
    //   567: invokevirtual 44	java/lang/String:equals	(Ljava/lang/Object;)Z
    //   570: ifne +8 -> 578
    //   573: aload 29
    //   575: invokestatic 212	BV:c	(Ljava/lang/String;)V
    //   578: aload_0
    //   579: getfield 16	FT:a	Lorg/json/JSONObject;
    //   582: ldc 214
    //   584: invokevirtual 172	org/json/JSONObject:has	(Ljava/lang/String;)Z
    //   587: istore 25
    //   589: iload 25
    //   591: ifeq +22 -> 613
    //   594: ldc 214
    //   596: aload_0
    //   597: getfield 16	FT:a	Lorg/json/JSONObject;
    //   600: ldc 214
    //   602: invokevirtual 189	org/json/JSONObject:getString	(Ljava/lang/String;)Ljava/lang/String;
    //   605: ldc 216
    //   607: invokevirtual 44	java/lang/String:equals	(Ljava/lang/Object;)Z
    //   610: invokestatic 221	CR:b	(Ljava/lang/String;Z)V
    //   613: aload_0
    //   614: getfield 16	FT:a	Lorg/json/JSONObject;
    //   617: ldc 223
    //   619: invokevirtual 172	org/json/JSONObject:has	(Ljava/lang/String;)Z
    //   622: istore 26
    //   624: iload 26
    //   626: ifeq +45 -> 671
    //   629: ldc 223
    //   631: aload_0
    //   632: getfield 16	FT:a	Lorg/json/JSONObject;
    //   635: ldc 223
    //   637: invokevirtual 189	org/json/JSONObject:getString	(Ljava/lang/String;)Ljava/lang/String;
    //   640: ldc 216
    //   642: invokevirtual 44	java/lang/String:equals	(Ljava/lang/Object;)Z
    //   645: invokestatic 221	CR:b	(Ljava/lang/String;Z)V
    //   648: goto -246 -> 402
    //   651: astore 27
    //   653: aload 27
    //   655: invokevirtual 224	java/lang/Exception:printStackTrace	()V
    //   658: goto -256 -> 402
    //   661: astore 28
    //   663: aload 28
    //   665: invokevirtual 224	java/lang/Exception:printStackTrace	()V
    //   668: goto -55 -> 613
    //   671: ldc 223
    //   673: iconst_0
    //   674: invokestatic 221	CR:b	(Ljava/lang/String;Z)V
    //   677: goto -275 -> 402
    //   680: astore 5
    //   682: aload_2
    //   683: new 174	CG
    //   686: dup
    //   687: ldc 226
    //   689: ldc 226
    //   691: iconst_0
    //   692: ldc 207
    //   694: iconst_0
    //   695: iconst_0
    //   696: iconst_0
    //   697: invokespecial 181	CG:<init>	(Ljava/lang/String;Ljava/lang/String;ILjava/lang/String;III)V
    //   700: invokeinterface 184 2 0
    //   705: pop
    //   706: aload_2
    //   707: invokestatic 231	CV:d	()Ljava/util/List;
    //   710: invokeinterface 235 2 0
    //   715: pop
    //   716: aload_2
    //   717: new 174	CG
    //   720: dup
    //   721: ldc 237
    //   723: ldc 237
    //   725: iconst_0
    //   726: ldc 178
    //   728: iconst_0
    //   729: iconst_0
    //   730: iconst_0
    //   731: invokespecial 181	CG:<init>	(Ljava/lang/String;Ljava/lang/String;ILjava/lang/String;III)V
    //   734: invokeinterface 184 2 0
    //   739: pop
    //   740: aload_0
    //   741: getfield 16	FT:a	Lorg/json/JSONObject;
    //   744: ldc 239
    //   746: invokevirtual 127	org/json/JSONObject:getJSONArray	(Ljava/lang/String;)Lorg/json/JSONArray;
    //   749: astore 10
    //   751: iconst_0
    //   752: istore 11
    //   754: iload 11
    //   756: aload 10
    //   758: invokevirtual 133	org/json/JSONArray:length	()I
    //   761: if_icmpge +83 -> 844
    //   764: aload 10
    //   766: iload 11
    //   768: invokevirtual 146	org/json/JSONArray:getJSONObject	(I)Lorg/json/JSONObject;
    //   771: astore 12
    //   773: aload_2
    //   774: new 174	CG
    //   777: dup
    //   778: ldc 237
    //   780: aload 12
    //   782: ldc 186
    //   784: invokevirtual 189	org/json/JSONObject:getString	(Ljava/lang/String;)Ljava/lang/String;
    //   787: aload 12
    //   789: ldc 191
    //   791: invokevirtual 195	org/json/JSONObject:getInt	(Ljava/lang/String;)I
    //   794: aload 12
    //   796: ldc 197
    //   798: invokevirtual 189	org/json/JSONObject:getString	(Ljava/lang/String;)Ljava/lang/String;
    //   801: aload 12
    //   803: ldc 199
    //   805: invokevirtual 195	org/json/JSONObject:getInt	(Ljava/lang/String;)I
    //   808: aload 12
    //   810: ldc 201
    //   812: invokevirtual 195	org/json/JSONObject:getInt	(Ljava/lang/String;)I
    //   815: aload 12
    //   817: ldc 203
    //   819: invokevirtual 195	org/json/JSONObject:getInt	(Ljava/lang/String;)I
    //   822: invokespecial 181	CG:<init>	(Ljava/lang/String;Ljava/lang/String;ILjava/lang/String;III)V
    //   825: invokeinterface 184 2 0
    //   830: pop
    //   831: iinc 11 1
    //   834: goto -80 -> 754
    //   837: astore 8
    //   839: aload 8
    //   841: invokevirtual 166	org/json/JSONException:printStackTrace	()V
    //   844: aload_0
    //   845: getfield 14	FT:b	LFS;
    //   848: getfield 48	FS:f	LFR;
    //   851: aload_0
    //   852: getfield 14	FT:b	LFS;
    //   855: getfield 48	FS:f	LFR;
    //   858: getfield 243	FR:p	Ljava/util/Comparator;
    //   861: aload_0
    //   862: getfield 14	FT:b	LFS;
    //   865: getfield 48	FS:f	LFR;
    //   868: getfield 243	FR:p	Ljava/util/Comparator;
    //   871: invokevirtual 246	FR:a	(Ljava/util/Comparator;Ljava/util/Comparator;)V
    //   874: aload_2
    //   875: invokeinterface 249 1 0
    //   880: ifle +7 -> 887
    //   883: aload_2
    //   884: invokestatic 252	CV:a	(Ljava/util/List;)V
    //   887: aload_0
    //   888: getfield 14	FT:b	LFS;
    //   891: getfield 48	FS:f	LFR;
    //   894: invokevirtual 256	FR:getActivity	()Landroid/support/v4/app/FragmentActivity;
    //   897: checkcast 258	com/yik/yak/ui/activity/MainActivity
    //   900: invokevirtual 260	com/yik/yak/ui/activity/MainActivity:c	()V
    //   903: aload_0
    //   904: getfield 14	FT:b	LFS;
    //   907: getfield 48	FS:f	LFR;
    //   910: getfield 264	FR:D	Lcom/yik/yak/ui/view/RefreshListView;
    //   913: iconst_0
    //   914: invokevirtual 270	com/yik/yak/ui/view/RefreshListView:setRefreshing	(Z)V
    //   917: aload_0
    //   918: getfield 14	FT:b	LFS;
    //   921: getfield 48	FS:f	LFR;
    //   924: invokevirtual 272	FR:h	()V
    //   927: invokestatic 277	CY:a	()LCY;
    //   930: aload_0
    //   931: getfield 14	FT:b	LFS;
    //   934: getfield 48	FS:f	LFR;
    //   937: invokevirtual 256	FR:getActivity	()Landroid/support/v4/app/FragmentActivity;
    //   940: invokevirtual 280	CY:a	(Landroid/app/Activity;)V
    //   943: return
    //   944: astore 4
    //   946: aload 4
    //   948: invokevirtual 224	java/lang/Exception:printStackTrace	()V
    //   951: goto -48 -> 903
    // Local variable table:
    //   start	length	slot	name	signature
    //   0	954	0	this	FT
    //   1	217	1	i	int
    //   193	691	2	localArrayList	java.util.ArrayList
    //   397	2	3	localJSONException1	org.json.JSONException
    //   944	3	4	localException1	java.lang.Exception
    //   680	1	5	localJSONException2	org.json.JSONException
    //   837	3	8	localJSONException3	org.json.JSONException
    //   749	16	10	localJSONArray1	org.json.JSONArray
    //   752	80	11	j	int
    //   771	45	12	localJSONObject1	JSONObject
    //   447	16	15	localJSONArray2	org.json.JSONArray
    //   450	80	16	k	int
    //   469	45	17	localJSONObject2	JSONObject
    //   203	56	19	localJSONArray3	org.json.JSONArray
    //   225	10	20	arrayOfObject	Object[]
    //   240	110	21	m	int
    //   315	74	22	localCK1	CK
    //   587	3	25	bool1	boolean
    //   622	3	26	bool2	boolean
    //   651	3	27	localException2	java.lang.Exception
    //   661	3	28	localException3	java.lang.Exception
    //   556	18	29	str	java.lang.String
    //   44	312	30	localCK2	CK
    // Exception table:
    //   from	to	target	type
    //   194	349	397	org/json/JSONException
    //   378	394	397	org/json/JSONException
    //   535	589	397	org/json/JSONException
    //   594	613	397	org/json/JSONException
    //   613	624	397	org/json/JSONException
    //   629	648	397	org/json/JSONException
    //   653	677	397	org/json/JSONException
    //   629	648	651	java/lang/Exception
    //   594	613	661	java/lang/Exception
    //   414	529	680	org/json/JSONException
    //   716	831	837	org/json/JSONException
    //   844	903	944	java/lang/Exception
  }
}


/* Location:           C:\Users\dreadiscool\Desktop\tools\classes-dex2jar.jar
 * Qualified Name:     FT
 * JD-Core Version:    0.7.0.1
 */