import android.os.IBinder;

class hR
  implements hP
{
  private IBinder a;
  
  hR(IBinder paramIBinder)
  {
    this.a = paramIBinder;
  }
  
  /* Error */
  public void a(hM paramhM, int paramInt)
  {
    // Byte code:
    //   0: invokestatic 22	android/os/Parcel:obtain	()Landroid/os/Parcel;
    //   3: astore_3
    //   4: invokestatic 22	android/os/Parcel:obtain	()Landroid/os/Parcel;
    //   7: astore 4
    //   9: aload_3
    //   10: ldc 24
    //   12: invokevirtual 28	android/os/Parcel:writeInterfaceToken	(Ljava/lang/String;)V
    //   15: aload_1
    //   16: ifnull +52 -> 68
    //   19: aload_1
    //   20: invokeinterface 34 1 0
    //   25: astore 6
    //   27: aload_3
    //   28: aload 6
    //   30: invokevirtual 37	android/os/Parcel:writeStrongBinder	(Landroid/os/IBinder;)V
    //   33: aload_3
    //   34: iload_2
    //   35: invokevirtual 41	android/os/Parcel:writeInt	(I)V
    //   38: aload_0
    //   39: getfield 15	hR:a	Landroid/os/IBinder;
    //   42: iconst_4
    //   43: aload_3
    //   44: aload 4
    //   46: iconst_0
    //   47: invokeinterface 47 5 0
    //   52: pop
    //   53: aload 4
    //   55: invokevirtual 50	android/os/Parcel:readException	()V
    //   58: aload 4
    //   60: invokevirtual 53	android/os/Parcel:recycle	()V
    //   63: aload_3
    //   64: invokevirtual 53	android/os/Parcel:recycle	()V
    //   67: return
    //   68: aconst_null
    //   69: astore 6
    //   71: goto -44 -> 27
    //   74: astore 5
    //   76: aload 4
    //   78: invokevirtual 53	android/os/Parcel:recycle	()V
    //   81: aload_3
    //   82: invokevirtual 53	android/os/Parcel:recycle	()V
    //   85: aload 5
    //   87: athrow
    // Local variable table:
    //   start	length	slot	name	signature
    //   0	88	0	this	hR
    //   0	88	1	paramhM	hM
    //   0	88	2	paramInt	int
    //   3	79	3	localParcel1	android.os.Parcel
    //   7	70	4	localParcel2	android.os.Parcel
    //   74	12	5	localObject	Object
    //   25	45	6	localIBinder	IBinder
    // Exception table:
    //   from	to	target	type
    //   9	58	74	finally
  }
  
  /* Error */
  public void a(hM paramhM, int paramInt, java.lang.String paramString)
  {
    // Byte code:
    //   0: invokestatic 22	android/os/Parcel:obtain	()Landroid/os/Parcel;
    //   3: astore 4
    //   5: invokestatic 22	android/os/Parcel:obtain	()Landroid/os/Parcel;
    //   8: astore 5
    //   10: aload 4
    //   12: ldc 24
    //   14: invokevirtual 28	android/os/Parcel:writeInterfaceToken	(Ljava/lang/String;)V
    //   17: aload_1
    //   18: ifnull +62 -> 80
    //   21: aload_1
    //   22: invokeinterface 34 1 0
    //   27: astore 7
    //   29: aload 4
    //   31: aload 7
    //   33: invokevirtual 37	android/os/Parcel:writeStrongBinder	(Landroid/os/IBinder;)V
    //   36: aload 4
    //   38: iload_2
    //   39: invokevirtual 41	android/os/Parcel:writeInt	(I)V
    //   42: aload 4
    //   44: aload_3
    //   45: invokevirtual 57	android/os/Parcel:writeString	(Ljava/lang/String;)V
    //   48: aload_0
    //   49: getfield 15	hR:a	Landroid/os/IBinder;
    //   52: iconst_3
    //   53: aload 4
    //   55: aload 5
    //   57: iconst_0
    //   58: invokeinterface 47 5 0
    //   63: pop
    //   64: aload 5
    //   66: invokevirtual 50	android/os/Parcel:readException	()V
    //   69: aload 5
    //   71: invokevirtual 53	android/os/Parcel:recycle	()V
    //   74: aload 4
    //   76: invokevirtual 53	android/os/Parcel:recycle	()V
    //   79: return
    //   80: aconst_null
    //   81: astore 7
    //   83: goto -54 -> 29
    //   86: astore 6
    //   88: aload 5
    //   90: invokevirtual 53	android/os/Parcel:recycle	()V
    //   93: aload 4
    //   95: invokevirtual 53	android/os/Parcel:recycle	()V
    //   98: aload 6
    //   100: athrow
    // Local variable table:
    //   start	length	slot	name	signature
    //   0	101	0	this	hR
    //   0	101	1	paramhM	hM
    //   0	101	2	paramInt	int
    //   0	101	3	paramString	java.lang.String
    //   3	91	4	localParcel1	android.os.Parcel
    //   8	81	5	localParcel2	android.os.Parcel
    //   86	13	6	localObject	Object
    //   27	55	7	localIBinder	IBinder
    // Exception table:
    //   from	to	target	type
    //   10	69	86	finally
  }
  
  /* Error */
  public void a(hM paramhM, int paramInt, java.lang.String paramString, android.os.Bundle paramBundle)
  {
    // Byte code:
    //   0: invokestatic 22	android/os/Parcel:obtain	()Landroid/os/Parcel;
    //   3: astore 5
    //   5: invokestatic 22	android/os/Parcel:obtain	()Landroid/os/Parcel;
    //   8: astore 6
    //   10: aload 5
    //   12: ldc 24
    //   14: invokevirtual 28	android/os/Parcel:writeInterfaceToken	(Ljava/lang/String;)V
    //   17: aload_1
    //   18: ifnull +81 -> 99
    //   21: aload_1
    //   22: invokeinterface 34 1 0
    //   27: astore 8
    //   29: aload 5
    //   31: aload 8
    //   33: invokevirtual 37	android/os/Parcel:writeStrongBinder	(Landroid/os/IBinder;)V
    //   36: aload 5
    //   38: iload_2
    //   39: invokevirtual 41	android/os/Parcel:writeInt	(I)V
    //   42: aload 5
    //   44: aload_3
    //   45: invokevirtual 57	android/os/Parcel:writeString	(Ljava/lang/String;)V
    //   48: aload 4
    //   50: ifnull +55 -> 105
    //   53: aload 5
    //   55: iconst_1
    //   56: invokevirtual 41	android/os/Parcel:writeInt	(I)V
    //   59: aload 4
    //   61: aload 5
    //   63: iconst_0
    //   64: invokevirtual 64	android/os/Bundle:writeToParcel	(Landroid/os/Parcel;I)V
    //   67: aload_0
    //   68: getfield 15	hR:a	Landroid/os/IBinder;
    //   71: iconst_2
    //   72: aload 5
    //   74: aload 6
    //   76: iconst_0
    //   77: invokeinterface 47 5 0
    //   82: pop
    //   83: aload 6
    //   85: invokevirtual 50	android/os/Parcel:readException	()V
    //   88: aload 6
    //   90: invokevirtual 53	android/os/Parcel:recycle	()V
    //   93: aload 5
    //   95: invokevirtual 53	android/os/Parcel:recycle	()V
    //   98: return
    //   99: aconst_null
    //   100: astore 8
    //   102: goto -73 -> 29
    //   105: aload 5
    //   107: iconst_0
    //   108: invokevirtual 41	android/os/Parcel:writeInt	(I)V
    //   111: goto -44 -> 67
    //   114: astore 7
    //   116: aload 6
    //   118: invokevirtual 53	android/os/Parcel:recycle	()V
    //   121: aload 5
    //   123: invokevirtual 53	android/os/Parcel:recycle	()V
    //   126: aload 7
    //   128: athrow
    // Local variable table:
    //   start	length	slot	name	signature
    //   0	129	0	this	hR
    //   0	129	1	paramhM	hM
    //   0	129	2	paramInt	int
    //   0	129	3	paramString	java.lang.String
    //   0	129	4	paramBundle	android.os.Bundle
    //   3	119	5	localParcel1	android.os.Parcel
    //   8	109	6	localParcel2	android.os.Parcel
    //   114	13	7	localObject	Object
    //   27	74	8	localIBinder	IBinder
    // Exception table:
    //   from	to	target	type
    //   10	88	114	finally
    //   105	111	114	finally
  }
  
  /* Error */
  public void a(hM paramhM, int paramInt, java.lang.String paramString, IBinder paramIBinder, android.os.Bundle paramBundle)
  {
    // Byte code:
    //   0: invokestatic 22	android/os/Parcel:obtain	()Landroid/os/Parcel;
    //   3: astore 6
    //   5: invokestatic 22	android/os/Parcel:obtain	()Landroid/os/Parcel;
    //   8: astore 7
    //   10: aload 6
    //   12: ldc 24
    //   14: invokevirtual 28	android/os/Parcel:writeInterfaceToken	(Ljava/lang/String;)V
    //   17: aload_1
    //   18: ifnull +89 -> 107
    //   21: aload_1
    //   22: invokeinterface 34 1 0
    //   27: astore 9
    //   29: aload 6
    //   31: aload 9
    //   33: invokevirtual 37	android/os/Parcel:writeStrongBinder	(Landroid/os/IBinder;)V
    //   36: aload 6
    //   38: iload_2
    //   39: invokevirtual 41	android/os/Parcel:writeInt	(I)V
    //   42: aload 6
    //   44: aload_3
    //   45: invokevirtual 57	android/os/Parcel:writeString	(Ljava/lang/String;)V
    //   48: aload 6
    //   50: aload 4
    //   52: invokevirtual 37	android/os/Parcel:writeStrongBinder	(Landroid/os/IBinder;)V
    //   55: aload 5
    //   57: ifnull +56 -> 113
    //   60: aload 6
    //   62: iconst_1
    //   63: invokevirtual 41	android/os/Parcel:writeInt	(I)V
    //   66: aload 5
    //   68: aload 6
    //   70: iconst_0
    //   71: invokevirtual 64	android/os/Bundle:writeToParcel	(Landroid/os/Parcel;I)V
    //   74: aload_0
    //   75: getfield 15	hR:a	Landroid/os/IBinder;
    //   78: bipush 19
    //   80: aload 6
    //   82: aload 7
    //   84: iconst_0
    //   85: invokeinterface 47 5 0
    //   90: pop
    //   91: aload 7
    //   93: invokevirtual 50	android/os/Parcel:readException	()V
    //   96: aload 7
    //   98: invokevirtual 53	android/os/Parcel:recycle	()V
    //   101: aload 6
    //   103: invokevirtual 53	android/os/Parcel:recycle	()V
    //   106: return
    //   107: aconst_null
    //   108: astore 9
    //   110: goto -81 -> 29
    //   113: aload 6
    //   115: iconst_0
    //   116: invokevirtual 41	android/os/Parcel:writeInt	(I)V
    //   119: goto -45 -> 74
    //   122: astore 8
    //   124: aload 7
    //   126: invokevirtual 53	android/os/Parcel:recycle	()V
    //   129: aload 6
    //   131: invokevirtual 53	android/os/Parcel:recycle	()V
    //   134: aload 8
    //   136: athrow
    // Local variable table:
    //   start	length	slot	name	signature
    //   0	137	0	this	hR
    //   0	137	1	paramhM	hM
    //   0	137	2	paramInt	int
    //   0	137	3	paramString	java.lang.String
    //   0	137	4	paramIBinder	IBinder
    //   0	137	5	paramBundle	android.os.Bundle
    //   3	127	6	localParcel1	android.os.Parcel
    //   8	117	7	localParcel2	android.os.Parcel
    //   122	13	8	localObject	Object
    //   27	82	9	localIBinder	IBinder
    // Exception table:
    //   from	to	target	type
    //   10	96	122	finally
    //   113	119	122	finally
  }
  
  /* Error */
  public void a(hM paramhM, int paramInt, java.lang.String paramString1, java.lang.String paramString2)
  {
    // Byte code:
    //   0: invokestatic 22	android/os/Parcel:obtain	()Landroid/os/Parcel;
    //   3: astore 5
    //   5: invokestatic 22	android/os/Parcel:obtain	()Landroid/os/Parcel;
    //   8: astore 6
    //   10: aload 5
    //   12: ldc 24
    //   14: invokevirtual 28	android/os/Parcel:writeInterfaceToken	(Ljava/lang/String;)V
    //   17: aload_1
    //   18: ifnull +70 -> 88
    //   21: aload_1
    //   22: invokeinterface 34 1 0
    //   27: astore 8
    //   29: aload 5
    //   31: aload 8
    //   33: invokevirtual 37	android/os/Parcel:writeStrongBinder	(Landroid/os/IBinder;)V
    //   36: aload 5
    //   38: iload_2
    //   39: invokevirtual 41	android/os/Parcel:writeInt	(I)V
    //   42: aload 5
    //   44: aload_3
    //   45: invokevirtual 57	android/os/Parcel:writeString	(Ljava/lang/String;)V
    //   48: aload 5
    //   50: aload 4
    //   52: invokevirtual 57	android/os/Parcel:writeString	(Ljava/lang/String;)V
    //   55: aload_0
    //   56: getfield 15	hR:a	Landroid/os/IBinder;
    //   59: bipush 34
    //   61: aload 5
    //   63: aload 6
    //   65: iconst_0
    //   66: invokeinterface 47 5 0
    //   71: pop
    //   72: aload 6
    //   74: invokevirtual 50	android/os/Parcel:readException	()V
    //   77: aload 6
    //   79: invokevirtual 53	android/os/Parcel:recycle	()V
    //   82: aload 5
    //   84: invokevirtual 53	android/os/Parcel:recycle	()V
    //   87: return
    //   88: aconst_null
    //   89: astore 8
    //   91: goto -62 -> 29
    //   94: astore 7
    //   96: aload 6
    //   98: invokevirtual 53	android/os/Parcel:recycle	()V
    //   101: aload 5
    //   103: invokevirtual 53	android/os/Parcel:recycle	()V
    //   106: aload 7
    //   108: athrow
    // Local variable table:
    //   start	length	slot	name	signature
    //   0	109	0	this	hR
    //   0	109	1	paramhM	hM
    //   0	109	2	paramInt	int
    //   0	109	3	paramString1	java.lang.String
    //   0	109	4	paramString2	java.lang.String
    //   3	99	5	localParcel1	android.os.Parcel
    //   8	89	6	localParcel2	android.os.Parcel
    //   94	13	7	localObject	Object
    //   27	63	8	localIBinder	IBinder
    // Exception table:
    //   from	to	target	type
    //   10	77	94	finally
  }
  
  /* Error */
  public void a(hM paramhM, int paramInt, java.lang.String paramString1, java.lang.String paramString2, java.lang.String paramString3, java.lang.String[] paramArrayOfString)
  {
    // Byte code:
    //   0: invokestatic 22	android/os/Parcel:obtain	()Landroid/os/Parcel;
    //   3: astore 7
    //   5: invokestatic 22	android/os/Parcel:obtain	()Landroid/os/Parcel;
    //   8: astore 8
    //   10: aload 7
    //   12: ldc 24
    //   14: invokevirtual 28	android/os/Parcel:writeInterfaceToken	(Ljava/lang/String;)V
    //   17: aload_1
    //   18: ifnull +84 -> 102
    //   21: aload_1
    //   22: invokeinterface 34 1 0
    //   27: astore 10
    //   29: aload 7
    //   31: aload 10
    //   33: invokevirtual 37	android/os/Parcel:writeStrongBinder	(Landroid/os/IBinder;)V
    //   36: aload 7
    //   38: iload_2
    //   39: invokevirtual 41	android/os/Parcel:writeInt	(I)V
    //   42: aload 7
    //   44: aload_3
    //   45: invokevirtual 57	android/os/Parcel:writeString	(Ljava/lang/String;)V
    //   48: aload 7
    //   50: aload 4
    //   52: invokevirtual 57	android/os/Parcel:writeString	(Ljava/lang/String;)V
    //   55: aload 7
    //   57: aload 5
    //   59: invokevirtual 57	android/os/Parcel:writeString	(Ljava/lang/String;)V
    //   62: aload 7
    //   64: aload 6
    //   66: invokevirtual 71	android/os/Parcel:writeStringArray	([Ljava/lang/String;)V
    //   69: aload_0
    //   70: getfield 15	hR:a	Landroid/os/IBinder;
    //   73: bipush 33
    //   75: aload 7
    //   77: aload 8
    //   79: iconst_0
    //   80: invokeinterface 47 5 0
    //   85: pop
    //   86: aload 8
    //   88: invokevirtual 50	android/os/Parcel:readException	()V
    //   91: aload 8
    //   93: invokevirtual 53	android/os/Parcel:recycle	()V
    //   96: aload 7
    //   98: invokevirtual 53	android/os/Parcel:recycle	()V
    //   101: return
    //   102: aconst_null
    //   103: astore 10
    //   105: goto -76 -> 29
    //   108: astore 9
    //   110: aload 8
    //   112: invokevirtual 53	android/os/Parcel:recycle	()V
    //   115: aload 7
    //   117: invokevirtual 53	android/os/Parcel:recycle	()V
    //   120: aload 9
    //   122: athrow
    // Local variable table:
    //   start	length	slot	name	signature
    //   0	123	0	this	hR
    //   0	123	1	paramhM	hM
    //   0	123	2	paramInt	int
    //   0	123	3	paramString1	java.lang.String
    //   0	123	4	paramString2	java.lang.String
    //   0	123	5	paramString3	java.lang.String
    //   0	123	6	paramArrayOfString	java.lang.String[]
    //   3	113	7	localParcel1	android.os.Parcel
    //   8	103	8	localParcel2	android.os.Parcel
    //   108	13	9	localObject	Object
    //   27	77	10	localIBinder	IBinder
    // Exception table:
    //   from	to	target	type
    //   10	91	108	finally
  }
  
  /* Error */
  public void a(hM paramhM, int paramInt, java.lang.String paramString1, java.lang.String paramString2, java.lang.String[] paramArrayOfString)
  {
    // Byte code:
    //   0: invokestatic 22	android/os/Parcel:obtain	()Landroid/os/Parcel;
    //   3: astore 6
    //   5: invokestatic 22	android/os/Parcel:obtain	()Landroid/os/Parcel;
    //   8: astore 7
    //   10: aload 6
    //   12: ldc 24
    //   14: invokevirtual 28	android/os/Parcel:writeInterfaceToken	(Ljava/lang/String;)V
    //   17: aload_1
    //   18: ifnull +77 -> 95
    //   21: aload_1
    //   22: invokeinterface 34 1 0
    //   27: astore 9
    //   29: aload 6
    //   31: aload 9
    //   33: invokevirtual 37	android/os/Parcel:writeStrongBinder	(Landroid/os/IBinder;)V
    //   36: aload 6
    //   38: iload_2
    //   39: invokevirtual 41	android/os/Parcel:writeInt	(I)V
    //   42: aload 6
    //   44: aload_3
    //   45: invokevirtual 57	android/os/Parcel:writeString	(Ljava/lang/String;)V
    //   48: aload 6
    //   50: aload 4
    //   52: invokevirtual 57	android/os/Parcel:writeString	(Ljava/lang/String;)V
    //   55: aload 6
    //   57: aload 5
    //   59: invokevirtual 71	android/os/Parcel:writeStringArray	([Ljava/lang/String;)V
    //   62: aload_0
    //   63: getfield 15	hR:a	Landroid/os/IBinder;
    //   66: bipush 10
    //   68: aload 6
    //   70: aload 7
    //   72: iconst_0
    //   73: invokeinterface 47 5 0
    //   78: pop
    //   79: aload 7
    //   81: invokevirtual 50	android/os/Parcel:readException	()V
    //   84: aload 7
    //   86: invokevirtual 53	android/os/Parcel:recycle	()V
    //   89: aload 6
    //   91: invokevirtual 53	android/os/Parcel:recycle	()V
    //   94: return
    //   95: aconst_null
    //   96: astore 9
    //   98: goto -69 -> 29
    //   101: astore 8
    //   103: aload 7
    //   105: invokevirtual 53	android/os/Parcel:recycle	()V
    //   108: aload 6
    //   110: invokevirtual 53	android/os/Parcel:recycle	()V
    //   113: aload 8
    //   115: athrow
    // Local variable table:
    //   start	length	slot	name	signature
    //   0	116	0	this	hR
    //   0	116	1	paramhM	hM
    //   0	116	2	paramInt	int
    //   0	116	3	paramString1	java.lang.String
    //   0	116	4	paramString2	java.lang.String
    //   0	116	5	paramArrayOfString	java.lang.String[]
    //   3	106	6	localParcel1	android.os.Parcel
    //   8	96	7	localParcel2	android.os.Parcel
    //   101	13	8	localObject	Object
    //   27	70	9	localIBinder	IBinder
    // Exception table:
    //   from	to	target	type
    //   10	84	101	finally
  }
  
  /* Error */
  public void a(hM paramhM, int paramInt, java.lang.String paramString1, java.lang.String paramString2, java.lang.String[] paramArrayOfString, android.os.Bundle paramBundle)
  {
    // Byte code:
    //   0: invokestatic 22	android/os/Parcel:obtain	()Landroid/os/Parcel;
    //   3: astore 7
    //   5: invokestatic 22	android/os/Parcel:obtain	()Landroid/os/Parcel;
    //   8: astore 8
    //   10: aload 7
    //   12: ldc 24
    //   14: invokevirtual 28	android/os/Parcel:writeInterfaceToken	(Ljava/lang/String;)V
    //   17: aload_1
    //   18: ifnull +96 -> 114
    //   21: aload_1
    //   22: invokeinterface 34 1 0
    //   27: astore 10
    //   29: aload 7
    //   31: aload 10
    //   33: invokevirtual 37	android/os/Parcel:writeStrongBinder	(Landroid/os/IBinder;)V
    //   36: aload 7
    //   38: iload_2
    //   39: invokevirtual 41	android/os/Parcel:writeInt	(I)V
    //   42: aload 7
    //   44: aload_3
    //   45: invokevirtual 57	android/os/Parcel:writeString	(Ljava/lang/String;)V
    //   48: aload 7
    //   50: aload 4
    //   52: invokevirtual 57	android/os/Parcel:writeString	(Ljava/lang/String;)V
    //   55: aload 7
    //   57: aload 5
    //   59: invokevirtual 71	android/os/Parcel:writeStringArray	([Ljava/lang/String;)V
    //   62: aload 6
    //   64: ifnull +56 -> 120
    //   67: aload 7
    //   69: iconst_1
    //   70: invokevirtual 41	android/os/Parcel:writeInt	(I)V
    //   73: aload 6
    //   75: aload 7
    //   77: iconst_0
    //   78: invokevirtual 64	android/os/Bundle:writeToParcel	(Landroid/os/Parcel;I)V
    //   81: aload_0
    //   82: getfield 15	hR:a	Landroid/os/IBinder;
    //   85: bipush 30
    //   87: aload 7
    //   89: aload 8
    //   91: iconst_0
    //   92: invokeinterface 47 5 0
    //   97: pop
    //   98: aload 8
    //   100: invokevirtual 50	android/os/Parcel:readException	()V
    //   103: aload 8
    //   105: invokevirtual 53	android/os/Parcel:recycle	()V
    //   108: aload 7
    //   110: invokevirtual 53	android/os/Parcel:recycle	()V
    //   113: return
    //   114: aconst_null
    //   115: astore 10
    //   117: goto -88 -> 29
    //   120: aload 7
    //   122: iconst_0
    //   123: invokevirtual 41	android/os/Parcel:writeInt	(I)V
    //   126: goto -45 -> 81
    //   129: astore 9
    //   131: aload 8
    //   133: invokevirtual 53	android/os/Parcel:recycle	()V
    //   136: aload 7
    //   138: invokevirtual 53	android/os/Parcel:recycle	()V
    //   141: aload 9
    //   143: athrow
    // Local variable table:
    //   start	length	slot	name	signature
    //   0	144	0	this	hR
    //   0	144	1	paramhM	hM
    //   0	144	2	paramInt	int
    //   0	144	3	paramString1	java.lang.String
    //   0	144	4	paramString2	java.lang.String
    //   0	144	5	paramArrayOfString	java.lang.String[]
    //   0	144	6	paramBundle	android.os.Bundle
    //   3	134	7	localParcel1	android.os.Parcel
    //   8	124	8	localParcel2	android.os.Parcel
    //   129	13	9	localObject	Object
    //   27	89	10	localIBinder	IBinder
    // Exception table:
    //   from	to	target	type
    //   10	103	129	finally
    //   120	126	129	finally
  }
  
  /* Error */
  public void a(hM paramhM, int paramInt, java.lang.String paramString1, java.lang.String paramString2, java.lang.String[] paramArrayOfString, java.lang.String paramString3, android.os.Bundle paramBundle)
  {
    // Byte code:
    //   0: invokestatic 22	android/os/Parcel:obtain	()Landroid/os/Parcel;
    //   3: astore 8
    //   5: invokestatic 22	android/os/Parcel:obtain	()Landroid/os/Parcel;
    //   8: astore 9
    //   10: aload 8
    //   12: ldc 24
    //   14: invokevirtual 28	android/os/Parcel:writeInterfaceToken	(Ljava/lang/String;)V
    //   17: aload_1
    //   18: ifnull +102 -> 120
    //   21: aload_1
    //   22: invokeinterface 34 1 0
    //   27: astore 11
    //   29: aload 8
    //   31: aload 11
    //   33: invokevirtual 37	android/os/Parcel:writeStrongBinder	(Landroid/os/IBinder;)V
    //   36: aload 8
    //   38: iload_2
    //   39: invokevirtual 41	android/os/Parcel:writeInt	(I)V
    //   42: aload 8
    //   44: aload_3
    //   45: invokevirtual 57	android/os/Parcel:writeString	(Ljava/lang/String;)V
    //   48: aload 8
    //   50: aload 4
    //   52: invokevirtual 57	android/os/Parcel:writeString	(Ljava/lang/String;)V
    //   55: aload 8
    //   57: aload 5
    //   59: invokevirtual 71	android/os/Parcel:writeStringArray	([Ljava/lang/String;)V
    //   62: aload 8
    //   64: aload 6
    //   66: invokevirtual 57	android/os/Parcel:writeString	(Ljava/lang/String;)V
    //   69: aload 7
    //   71: ifnull +55 -> 126
    //   74: aload 8
    //   76: iconst_1
    //   77: invokevirtual 41	android/os/Parcel:writeInt	(I)V
    //   80: aload 7
    //   82: aload 8
    //   84: iconst_0
    //   85: invokevirtual 64	android/os/Bundle:writeToParcel	(Landroid/os/Parcel;I)V
    //   88: aload_0
    //   89: getfield 15	hR:a	Landroid/os/IBinder;
    //   92: iconst_1
    //   93: aload 8
    //   95: aload 9
    //   97: iconst_0
    //   98: invokeinterface 47 5 0
    //   103: pop
    //   104: aload 9
    //   106: invokevirtual 50	android/os/Parcel:readException	()V
    //   109: aload 9
    //   111: invokevirtual 53	android/os/Parcel:recycle	()V
    //   114: aload 8
    //   116: invokevirtual 53	android/os/Parcel:recycle	()V
    //   119: return
    //   120: aconst_null
    //   121: astore 11
    //   123: goto -94 -> 29
    //   126: aload 8
    //   128: iconst_0
    //   129: invokevirtual 41	android/os/Parcel:writeInt	(I)V
    //   132: goto -44 -> 88
    //   135: astore 10
    //   137: aload 9
    //   139: invokevirtual 53	android/os/Parcel:recycle	()V
    //   142: aload 8
    //   144: invokevirtual 53	android/os/Parcel:recycle	()V
    //   147: aload 10
    //   149: athrow
    // Local variable table:
    //   start	length	slot	name	signature
    //   0	150	0	this	hR
    //   0	150	1	paramhM	hM
    //   0	150	2	paramInt	int
    //   0	150	3	paramString1	java.lang.String
    //   0	150	4	paramString2	java.lang.String
    //   0	150	5	paramArrayOfString	java.lang.String[]
    //   0	150	6	paramString3	java.lang.String
    //   0	150	7	paramBundle	android.os.Bundle
    //   3	140	8	localParcel1	android.os.Parcel
    //   8	130	9	localParcel2	android.os.Parcel
    //   135	13	10	localObject	Object
    //   27	95	11	localIBinder	IBinder
    // Exception table:
    //   from	to	target	type
    //   10	109	135	finally
    //   126	132	135	finally
  }
  
  /* Error */
  public void a(hM paramhM, int paramInt, java.lang.String paramString1, java.lang.String paramString2, java.lang.String[] paramArrayOfString, java.lang.String paramString3, IBinder paramIBinder, java.lang.String paramString4, android.os.Bundle paramBundle)
  {
    // Byte code:
    //   0: invokestatic 22	android/os/Parcel:obtain	()Landroid/os/Parcel;
    //   3: astore 10
    //   5: invokestatic 22	android/os/Parcel:obtain	()Landroid/os/Parcel;
    //   8: astore 11
    //   10: aload 10
    //   12: ldc 24
    //   14: invokevirtual 28	android/os/Parcel:writeInterfaceToken	(Ljava/lang/String;)V
    //   17: aload_1
    //   18: ifnull +117 -> 135
    //   21: aload_1
    //   22: invokeinterface 34 1 0
    //   27: astore 13
    //   29: aload 10
    //   31: aload 13
    //   33: invokevirtual 37	android/os/Parcel:writeStrongBinder	(Landroid/os/IBinder;)V
    //   36: aload 10
    //   38: iload_2
    //   39: invokevirtual 41	android/os/Parcel:writeInt	(I)V
    //   42: aload 10
    //   44: aload_3
    //   45: invokevirtual 57	android/os/Parcel:writeString	(Ljava/lang/String;)V
    //   48: aload 10
    //   50: aload 4
    //   52: invokevirtual 57	android/os/Parcel:writeString	(Ljava/lang/String;)V
    //   55: aload 10
    //   57: aload 5
    //   59: invokevirtual 71	android/os/Parcel:writeStringArray	([Ljava/lang/String;)V
    //   62: aload 10
    //   64: aload 6
    //   66: invokevirtual 57	android/os/Parcel:writeString	(Ljava/lang/String;)V
    //   69: aload 10
    //   71: aload 7
    //   73: invokevirtual 37	android/os/Parcel:writeStrongBinder	(Landroid/os/IBinder;)V
    //   76: aload 10
    //   78: aload 8
    //   80: invokevirtual 57	android/os/Parcel:writeString	(Ljava/lang/String;)V
    //   83: aload 9
    //   85: ifnull +56 -> 141
    //   88: aload 10
    //   90: iconst_1
    //   91: invokevirtual 41	android/os/Parcel:writeInt	(I)V
    //   94: aload 9
    //   96: aload 10
    //   98: iconst_0
    //   99: invokevirtual 64	android/os/Bundle:writeToParcel	(Landroid/os/Parcel;I)V
    //   102: aload_0
    //   103: getfield 15	hR:a	Landroid/os/IBinder;
    //   106: bipush 9
    //   108: aload 10
    //   110: aload 11
    //   112: iconst_0
    //   113: invokeinterface 47 5 0
    //   118: pop
    //   119: aload 11
    //   121: invokevirtual 50	android/os/Parcel:readException	()V
    //   124: aload 11
    //   126: invokevirtual 53	android/os/Parcel:recycle	()V
    //   129: aload 10
    //   131: invokevirtual 53	android/os/Parcel:recycle	()V
    //   134: return
    //   135: aconst_null
    //   136: astore 13
    //   138: goto -109 -> 29
    //   141: aload 10
    //   143: iconst_0
    //   144: invokevirtual 41	android/os/Parcel:writeInt	(I)V
    //   147: goto -45 -> 102
    //   150: astore 12
    //   152: aload 11
    //   154: invokevirtual 53	android/os/Parcel:recycle	()V
    //   157: aload 10
    //   159: invokevirtual 53	android/os/Parcel:recycle	()V
    //   162: aload 12
    //   164: athrow
    // Local variable table:
    //   start	length	slot	name	signature
    //   0	165	0	this	hR
    //   0	165	1	paramhM	hM
    //   0	165	2	paramInt	int
    //   0	165	3	paramString1	java.lang.String
    //   0	165	4	paramString2	java.lang.String
    //   0	165	5	paramArrayOfString	java.lang.String[]
    //   0	165	6	paramString3	java.lang.String
    //   0	165	7	paramIBinder	IBinder
    //   0	165	8	paramString4	java.lang.String
    //   0	165	9	paramBundle	android.os.Bundle
    //   3	155	10	localParcel1	android.os.Parcel
    //   8	145	11	localParcel2	android.os.Parcel
    //   150	13	12	localObject	Object
    //   27	110	13	localIBinder	IBinder
    // Exception table:
    //   from	to	target	type
    //   10	124	150	finally
    //   141	147	150	finally
  }
  
  /* Error */
  public void a(hM paramhM, int paramInt, java.lang.String paramString1, java.lang.String[] paramArrayOfString, java.lang.String paramString2, android.os.Bundle paramBundle)
  {
    // Byte code:
    //   0: invokestatic 22	android/os/Parcel:obtain	()Landroid/os/Parcel;
    //   3: astore 7
    //   5: invokestatic 22	android/os/Parcel:obtain	()Landroid/os/Parcel;
    //   8: astore 8
    //   10: aload 7
    //   12: ldc 24
    //   14: invokevirtual 28	android/os/Parcel:writeInterfaceToken	(Ljava/lang/String;)V
    //   17: aload_1
    //   18: ifnull +96 -> 114
    //   21: aload_1
    //   22: invokeinterface 34 1 0
    //   27: astore 10
    //   29: aload 7
    //   31: aload 10
    //   33: invokevirtual 37	android/os/Parcel:writeStrongBinder	(Landroid/os/IBinder;)V
    //   36: aload 7
    //   38: iload_2
    //   39: invokevirtual 41	android/os/Parcel:writeInt	(I)V
    //   42: aload 7
    //   44: aload_3
    //   45: invokevirtual 57	android/os/Parcel:writeString	(Ljava/lang/String;)V
    //   48: aload 7
    //   50: aload 4
    //   52: invokevirtual 71	android/os/Parcel:writeStringArray	([Ljava/lang/String;)V
    //   55: aload 7
    //   57: aload 5
    //   59: invokevirtual 57	android/os/Parcel:writeString	(Ljava/lang/String;)V
    //   62: aload 6
    //   64: ifnull +56 -> 120
    //   67: aload 7
    //   69: iconst_1
    //   70: invokevirtual 41	android/os/Parcel:writeInt	(I)V
    //   73: aload 6
    //   75: aload 7
    //   77: iconst_0
    //   78: invokevirtual 64	android/os/Bundle:writeToParcel	(Landroid/os/Parcel;I)V
    //   81: aload_0
    //   82: getfield 15	hR:a	Landroid/os/IBinder;
    //   85: bipush 20
    //   87: aload 7
    //   89: aload 8
    //   91: iconst_0
    //   92: invokeinterface 47 5 0
    //   97: pop
    //   98: aload 8
    //   100: invokevirtual 50	android/os/Parcel:readException	()V
    //   103: aload 8
    //   105: invokevirtual 53	android/os/Parcel:recycle	()V
    //   108: aload 7
    //   110: invokevirtual 53	android/os/Parcel:recycle	()V
    //   113: return
    //   114: aconst_null
    //   115: astore 10
    //   117: goto -88 -> 29
    //   120: aload 7
    //   122: iconst_0
    //   123: invokevirtual 41	android/os/Parcel:writeInt	(I)V
    //   126: goto -45 -> 81
    //   129: astore 9
    //   131: aload 8
    //   133: invokevirtual 53	android/os/Parcel:recycle	()V
    //   136: aload 7
    //   138: invokevirtual 53	android/os/Parcel:recycle	()V
    //   141: aload 9
    //   143: athrow
    // Local variable table:
    //   start	length	slot	name	signature
    //   0	144	0	this	hR
    //   0	144	1	paramhM	hM
    //   0	144	2	paramInt	int
    //   0	144	3	paramString1	java.lang.String
    //   0	144	4	paramArrayOfString	java.lang.String[]
    //   0	144	5	paramString2	java.lang.String
    //   0	144	6	paramBundle	android.os.Bundle
    //   3	134	7	localParcel1	android.os.Parcel
    //   8	124	8	localParcel2	android.os.Parcel
    //   129	13	9	localObject	Object
    //   27	89	10	localIBinder	IBinder
    // Exception table:
    //   from	to	target	type
    //   10	103	129	finally
    //   120	126	129	finally
  }
  
  /* Error */
  public void a(hM paramhM, com.google.android.gms.internal.jj paramjj)
  {
    // Byte code:
    //   0: invokestatic 22	android/os/Parcel:obtain	()Landroid/os/Parcel;
    //   3: astore_3
    //   4: invokestatic 22	android/os/Parcel:obtain	()Landroid/os/Parcel;
    //   7: astore 4
    //   9: aload_3
    //   10: ldc 24
    //   12: invokevirtual 28	android/os/Parcel:writeInterfaceToken	(Ljava/lang/String;)V
    //   15: aload_1
    //   16: ifnull +63 -> 79
    //   19: aload_1
    //   20: invokeinterface 34 1 0
    //   25: astore 6
    //   27: aload_3
    //   28: aload 6
    //   30: invokevirtual 37	android/os/Parcel:writeStrongBinder	(Landroid/os/IBinder;)V
    //   33: aload_2
    //   34: ifnull +51 -> 85
    //   37: aload_3
    //   38: iconst_1
    //   39: invokevirtual 41	android/os/Parcel:writeInt	(I)V
    //   42: aload_2
    //   43: aload_3
    //   44: iconst_0
    //   45: invokevirtual 80	com/google/android/gms/internal/jj:writeToParcel	(Landroid/os/Parcel;I)V
    //   48: aload_0
    //   49: getfield 15	hR:a	Landroid/os/IBinder;
    //   52: bipush 46
    //   54: aload_3
    //   55: aload 4
    //   57: iconst_0
    //   58: invokeinterface 47 5 0
    //   63: pop
    //   64: aload 4
    //   66: invokevirtual 50	android/os/Parcel:readException	()V
    //   69: aload 4
    //   71: invokevirtual 53	android/os/Parcel:recycle	()V
    //   74: aload_3
    //   75: invokevirtual 53	android/os/Parcel:recycle	()V
    //   78: return
    //   79: aconst_null
    //   80: astore 6
    //   82: goto -55 -> 27
    //   85: aload_3
    //   86: iconst_0
    //   87: invokevirtual 41	android/os/Parcel:writeInt	(I)V
    //   90: goto -42 -> 48
    //   93: astore 5
    //   95: aload 4
    //   97: invokevirtual 53	android/os/Parcel:recycle	()V
    //   100: aload_3
    //   101: invokevirtual 53	android/os/Parcel:recycle	()V
    //   104: aload 5
    //   106: athrow
    // Local variable table:
    //   start	length	slot	name	signature
    //   0	107	0	this	hR
    //   0	107	1	paramhM	hM
    //   0	107	2	paramjj	com.google.android.gms.internal.jj
    //   3	98	3	localParcel1	android.os.Parcel
    //   7	89	4	localParcel2	android.os.Parcel
    //   93	12	5	localObject	Object
    //   25	56	6	localIBinder	IBinder
    // Exception table:
    //   from	to	target	type
    //   9	69	93	finally
    //   85	90	93	finally
  }
  
  public IBinder asBinder()
  {
    return this.a;
  }
  
  /* Error */
  public void b(hM paramhM, int paramInt, java.lang.String paramString)
  {
    // Byte code:
    //   0: invokestatic 22	android/os/Parcel:obtain	()Landroid/os/Parcel;
    //   3: astore 4
    //   5: invokestatic 22	android/os/Parcel:obtain	()Landroid/os/Parcel;
    //   8: astore 5
    //   10: aload 4
    //   12: ldc 24
    //   14: invokevirtual 28	android/os/Parcel:writeInterfaceToken	(Ljava/lang/String;)V
    //   17: aload_1
    //   18: ifnull +63 -> 81
    //   21: aload_1
    //   22: invokeinterface 34 1 0
    //   27: astore 7
    //   29: aload 4
    //   31: aload 7
    //   33: invokevirtual 37	android/os/Parcel:writeStrongBinder	(Landroid/os/IBinder;)V
    //   36: aload 4
    //   38: iload_2
    //   39: invokevirtual 41	android/os/Parcel:writeInt	(I)V
    //   42: aload 4
    //   44: aload_3
    //   45: invokevirtual 57	android/os/Parcel:writeString	(Ljava/lang/String;)V
    //   48: aload_0
    //   49: getfield 15	hR:a	Landroid/os/IBinder;
    //   52: bipush 21
    //   54: aload 4
    //   56: aload 5
    //   58: iconst_0
    //   59: invokeinterface 47 5 0
    //   64: pop
    //   65: aload 5
    //   67: invokevirtual 50	android/os/Parcel:readException	()V
    //   70: aload 5
    //   72: invokevirtual 53	android/os/Parcel:recycle	()V
    //   75: aload 4
    //   77: invokevirtual 53	android/os/Parcel:recycle	()V
    //   80: return
    //   81: aconst_null
    //   82: astore 7
    //   84: goto -55 -> 29
    //   87: astore 6
    //   89: aload 5
    //   91: invokevirtual 53	android/os/Parcel:recycle	()V
    //   94: aload 4
    //   96: invokevirtual 53	android/os/Parcel:recycle	()V
    //   99: aload 6
    //   101: athrow
    // Local variable table:
    //   start	length	slot	name	signature
    //   0	102	0	this	hR
    //   0	102	1	paramhM	hM
    //   0	102	2	paramInt	int
    //   0	102	3	paramString	java.lang.String
    //   3	92	4	localParcel1	android.os.Parcel
    //   8	82	5	localParcel2	android.os.Parcel
    //   87	13	6	localObject	Object
    //   27	56	7	localIBinder	IBinder
    // Exception table:
    //   from	to	target	type
    //   10	70	87	finally
  }
  
  /* Error */
  public void b(hM paramhM, int paramInt, java.lang.String paramString, android.os.Bundle paramBundle)
  {
    // Byte code:
    //   0: invokestatic 22	android/os/Parcel:obtain	()Landroid/os/Parcel;
    //   3: astore 5
    //   5: invokestatic 22	android/os/Parcel:obtain	()Landroid/os/Parcel;
    //   8: astore 6
    //   10: aload 5
    //   12: ldc 24
    //   14: invokevirtual 28	android/os/Parcel:writeInterfaceToken	(Ljava/lang/String;)V
    //   17: aload_1
    //   18: ifnull +81 -> 99
    //   21: aload_1
    //   22: invokeinterface 34 1 0
    //   27: astore 8
    //   29: aload 5
    //   31: aload 8
    //   33: invokevirtual 37	android/os/Parcel:writeStrongBinder	(Landroid/os/IBinder;)V
    //   36: aload 5
    //   38: iload_2
    //   39: invokevirtual 41	android/os/Parcel:writeInt	(I)V
    //   42: aload 5
    //   44: aload_3
    //   45: invokevirtual 57	android/os/Parcel:writeString	(Ljava/lang/String;)V
    //   48: aload 4
    //   50: ifnull +55 -> 105
    //   53: aload 5
    //   55: iconst_1
    //   56: invokevirtual 41	android/os/Parcel:writeInt	(I)V
    //   59: aload 4
    //   61: aload 5
    //   63: iconst_0
    //   64: invokevirtual 64	android/os/Bundle:writeToParcel	(Landroid/os/Parcel;I)V
    //   67: aload_0
    //   68: getfield 15	hR:a	Landroid/os/IBinder;
    //   71: iconst_5
    //   72: aload 5
    //   74: aload 6
    //   76: iconst_0
    //   77: invokeinterface 47 5 0
    //   82: pop
    //   83: aload 6
    //   85: invokevirtual 50	android/os/Parcel:readException	()V
    //   88: aload 6
    //   90: invokevirtual 53	android/os/Parcel:recycle	()V
    //   93: aload 5
    //   95: invokevirtual 53	android/os/Parcel:recycle	()V
    //   98: return
    //   99: aconst_null
    //   100: astore 8
    //   102: goto -73 -> 29
    //   105: aload 5
    //   107: iconst_0
    //   108: invokevirtual 41	android/os/Parcel:writeInt	(I)V
    //   111: goto -44 -> 67
    //   114: astore 7
    //   116: aload 6
    //   118: invokevirtual 53	android/os/Parcel:recycle	()V
    //   121: aload 5
    //   123: invokevirtual 53	android/os/Parcel:recycle	()V
    //   126: aload 7
    //   128: athrow
    // Local variable table:
    //   start	length	slot	name	signature
    //   0	129	0	this	hR
    //   0	129	1	paramhM	hM
    //   0	129	2	paramInt	int
    //   0	129	3	paramString	java.lang.String
    //   0	129	4	paramBundle	android.os.Bundle
    //   3	119	5	localParcel1	android.os.Parcel
    //   8	109	6	localParcel2	android.os.Parcel
    //   114	13	7	localObject	Object
    //   27	74	8	localIBinder	IBinder
    // Exception table:
    //   from	to	target	type
    //   10	88	114	finally
    //   105	111	114	finally
  }
  
  /* Error */
  public void b(hM paramhM, int paramInt, java.lang.String paramString1, java.lang.String paramString2, java.lang.String[] paramArrayOfString)
  {
    // Byte code:
    //   0: invokestatic 22	android/os/Parcel:obtain	()Landroid/os/Parcel;
    //   3: astore 6
    //   5: invokestatic 22	android/os/Parcel:obtain	()Landroid/os/Parcel;
    //   8: astore 7
    //   10: aload 6
    //   12: ldc 24
    //   14: invokevirtual 28	android/os/Parcel:writeInterfaceToken	(Ljava/lang/String;)V
    //   17: aload_1
    //   18: ifnull +77 -> 95
    //   21: aload_1
    //   22: invokeinterface 34 1 0
    //   27: astore 9
    //   29: aload 6
    //   31: aload 9
    //   33: invokevirtual 37	android/os/Parcel:writeStrongBinder	(Landroid/os/IBinder;)V
    //   36: aload 6
    //   38: iload_2
    //   39: invokevirtual 41	android/os/Parcel:writeInt	(I)V
    //   42: aload 6
    //   44: aload_3
    //   45: invokevirtual 57	android/os/Parcel:writeString	(Ljava/lang/String;)V
    //   48: aload 6
    //   50: aload 4
    //   52: invokevirtual 57	android/os/Parcel:writeString	(Ljava/lang/String;)V
    //   55: aload 6
    //   57: aload 5
    //   59: invokevirtual 71	android/os/Parcel:writeStringArray	([Ljava/lang/String;)V
    //   62: aload_0
    //   63: getfield 15	hR:a	Landroid/os/IBinder;
    //   66: bipush 28
    //   68: aload 6
    //   70: aload 7
    //   72: iconst_0
    //   73: invokeinterface 47 5 0
    //   78: pop
    //   79: aload 7
    //   81: invokevirtual 50	android/os/Parcel:readException	()V
    //   84: aload 7
    //   86: invokevirtual 53	android/os/Parcel:recycle	()V
    //   89: aload 6
    //   91: invokevirtual 53	android/os/Parcel:recycle	()V
    //   94: return
    //   95: aconst_null
    //   96: astore 9
    //   98: goto -69 -> 29
    //   101: astore 8
    //   103: aload 7
    //   105: invokevirtual 53	android/os/Parcel:recycle	()V
    //   108: aload 6
    //   110: invokevirtual 53	android/os/Parcel:recycle	()V
    //   113: aload 8
    //   115: athrow
    // Local variable table:
    //   start	length	slot	name	signature
    //   0	116	0	this	hR
    //   0	116	1	paramhM	hM
    //   0	116	2	paramInt	int
    //   0	116	3	paramString1	java.lang.String
    //   0	116	4	paramString2	java.lang.String
    //   0	116	5	paramArrayOfString	java.lang.String[]
    //   3	106	6	localParcel1	android.os.Parcel
    //   8	96	7	localParcel2	android.os.Parcel
    //   101	13	8	localObject	Object
    //   27	70	9	localIBinder	IBinder
    // Exception table:
    //   from	to	target	type
    //   10	84	101	finally
  }
  
  /* Error */
  public void c(hM paramhM, int paramInt, java.lang.String paramString)
  {
    // Byte code:
    //   0: invokestatic 22	android/os/Parcel:obtain	()Landroid/os/Parcel;
    //   3: astore 4
    //   5: invokestatic 22	android/os/Parcel:obtain	()Landroid/os/Parcel;
    //   8: astore 5
    //   10: aload 4
    //   12: ldc 24
    //   14: invokevirtual 28	android/os/Parcel:writeInterfaceToken	(Ljava/lang/String;)V
    //   17: aload_1
    //   18: ifnull +63 -> 81
    //   21: aload_1
    //   22: invokeinterface 34 1 0
    //   27: astore 7
    //   29: aload 4
    //   31: aload 7
    //   33: invokevirtual 37	android/os/Parcel:writeStrongBinder	(Landroid/os/IBinder;)V
    //   36: aload 4
    //   38: iload_2
    //   39: invokevirtual 41	android/os/Parcel:writeInt	(I)V
    //   42: aload 4
    //   44: aload_3
    //   45: invokevirtual 57	android/os/Parcel:writeString	(Ljava/lang/String;)V
    //   48: aload_0
    //   49: getfield 15	hR:a	Landroid/os/IBinder;
    //   52: bipush 22
    //   54: aload 4
    //   56: aload 5
    //   58: iconst_0
    //   59: invokeinterface 47 5 0
    //   64: pop
    //   65: aload 5
    //   67: invokevirtual 50	android/os/Parcel:readException	()V
    //   70: aload 5
    //   72: invokevirtual 53	android/os/Parcel:recycle	()V
    //   75: aload 4
    //   77: invokevirtual 53	android/os/Parcel:recycle	()V
    //   80: return
    //   81: aconst_null
    //   82: astore 7
    //   84: goto -55 -> 29
    //   87: astore 6
    //   89: aload 5
    //   91: invokevirtual 53	android/os/Parcel:recycle	()V
    //   94: aload 4
    //   96: invokevirtual 53	android/os/Parcel:recycle	()V
    //   99: aload 6
    //   101: athrow
    // Local variable table:
    //   start	length	slot	name	signature
    //   0	102	0	this	hR
    //   0	102	1	paramhM	hM
    //   0	102	2	paramInt	int
    //   0	102	3	paramString	java.lang.String
    //   3	92	4	localParcel1	android.os.Parcel
    //   8	82	5	localParcel2	android.os.Parcel
    //   87	13	6	localObject	Object
    //   27	56	7	localIBinder	IBinder
    // Exception table:
    //   from	to	target	type
    //   10	70	87	finally
  }
  
  /* Error */
  public void c(hM paramhM, int paramInt, java.lang.String paramString, android.os.Bundle paramBundle)
  {
    // Byte code:
    //   0: invokestatic 22	android/os/Parcel:obtain	()Landroid/os/Parcel;
    //   3: astore 5
    //   5: invokestatic 22	android/os/Parcel:obtain	()Landroid/os/Parcel;
    //   8: astore 6
    //   10: aload 5
    //   12: ldc 24
    //   14: invokevirtual 28	android/os/Parcel:writeInterfaceToken	(Ljava/lang/String;)V
    //   17: aload_1
    //   18: ifnull +82 -> 100
    //   21: aload_1
    //   22: invokeinterface 34 1 0
    //   27: astore 8
    //   29: aload 5
    //   31: aload 8
    //   33: invokevirtual 37	android/os/Parcel:writeStrongBinder	(Landroid/os/IBinder;)V
    //   36: aload 5
    //   38: iload_2
    //   39: invokevirtual 41	android/os/Parcel:writeInt	(I)V
    //   42: aload 5
    //   44: aload_3
    //   45: invokevirtual 57	android/os/Parcel:writeString	(Ljava/lang/String;)V
    //   48: aload 4
    //   50: ifnull +56 -> 106
    //   53: aload 5
    //   55: iconst_1
    //   56: invokevirtual 41	android/os/Parcel:writeInt	(I)V
    //   59: aload 4
    //   61: aload 5
    //   63: iconst_0
    //   64: invokevirtual 64	android/os/Bundle:writeToParcel	(Landroid/os/Parcel;I)V
    //   67: aload_0
    //   68: getfield 15	hR:a	Landroid/os/IBinder;
    //   71: bipush 6
    //   73: aload 5
    //   75: aload 6
    //   77: iconst_0
    //   78: invokeinterface 47 5 0
    //   83: pop
    //   84: aload 6
    //   86: invokevirtual 50	android/os/Parcel:readException	()V
    //   89: aload 6
    //   91: invokevirtual 53	android/os/Parcel:recycle	()V
    //   94: aload 5
    //   96: invokevirtual 53	android/os/Parcel:recycle	()V
    //   99: return
    //   100: aconst_null
    //   101: astore 8
    //   103: goto -74 -> 29
    //   106: aload 5
    //   108: iconst_0
    //   109: invokevirtual 41	android/os/Parcel:writeInt	(I)V
    //   112: goto -45 -> 67
    //   115: astore 7
    //   117: aload 6
    //   119: invokevirtual 53	android/os/Parcel:recycle	()V
    //   122: aload 5
    //   124: invokevirtual 53	android/os/Parcel:recycle	()V
    //   127: aload 7
    //   129: athrow
    // Local variable table:
    //   start	length	slot	name	signature
    //   0	130	0	this	hR
    //   0	130	1	paramhM	hM
    //   0	130	2	paramInt	int
    //   0	130	3	paramString	java.lang.String
    //   0	130	4	paramBundle	android.os.Bundle
    //   3	120	5	localParcel1	android.os.Parcel
    //   8	110	6	localParcel2	android.os.Parcel
    //   115	13	7	localObject	Object
    //   27	75	8	localIBinder	IBinder
    // Exception table:
    //   from	to	target	type
    //   10	89	115	finally
    //   106	112	115	finally
  }
  
  /* Error */
  public void d(hM paramhM, int paramInt, java.lang.String paramString)
  {
    // Byte code:
    //   0: invokestatic 22	android/os/Parcel:obtain	()Landroid/os/Parcel;
    //   3: astore 4
    //   5: invokestatic 22	android/os/Parcel:obtain	()Landroid/os/Parcel;
    //   8: astore 5
    //   10: aload 4
    //   12: ldc 24
    //   14: invokevirtual 28	android/os/Parcel:writeInterfaceToken	(Ljava/lang/String;)V
    //   17: aload_1
    //   18: ifnull +63 -> 81
    //   21: aload_1
    //   22: invokeinterface 34 1 0
    //   27: astore 7
    //   29: aload 4
    //   31: aload 7
    //   33: invokevirtual 37	android/os/Parcel:writeStrongBinder	(Landroid/os/IBinder;)V
    //   36: aload 4
    //   38: iload_2
    //   39: invokevirtual 41	android/os/Parcel:writeInt	(I)V
    //   42: aload 4
    //   44: aload_3
    //   45: invokevirtual 57	android/os/Parcel:writeString	(Ljava/lang/String;)V
    //   48: aload_0
    //   49: getfield 15	hR:a	Landroid/os/IBinder;
    //   52: bipush 24
    //   54: aload 4
    //   56: aload 5
    //   58: iconst_0
    //   59: invokeinterface 47 5 0
    //   64: pop
    //   65: aload 5
    //   67: invokevirtual 50	android/os/Parcel:readException	()V
    //   70: aload 5
    //   72: invokevirtual 53	android/os/Parcel:recycle	()V
    //   75: aload 4
    //   77: invokevirtual 53	android/os/Parcel:recycle	()V
    //   80: return
    //   81: aconst_null
    //   82: astore 7
    //   84: goto -55 -> 29
    //   87: astore 6
    //   89: aload 5
    //   91: invokevirtual 53	android/os/Parcel:recycle	()V
    //   94: aload 4
    //   96: invokevirtual 53	android/os/Parcel:recycle	()V
    //   99: aload 6
    //   101: athrow
    // Local variable table:
    //   start	length	slot	name	signature
    //   0	102	0	this	hR
    //   0	102	1	paramhM	hM
    //   0	102	2	paramInt	int
    //   0	102	3	paramString	java.lang.String
    //   3	92	4	localParcel1	android.os.Parcel
    //   8	82	5	localParcel2	android.os.Parcel
    //   87	13	6	localObject	Object
    //   27	56	7	localIBinder	IBinder
    // Exception table:
    //   from	to	target	type
    //   10	70	87	finally
  }
  
  /* Error */
  public void d(hM paramhM, int paramInt, java.lang.String paramString, android.os.Bundle paramBundle)
  {
    // Byte code:
    //   0: invokestatic 22	android/os/Parcel:obtain	()Landroid/os/Parcel;
    //   3: astore 5
    //   5: invokestatic 22	android/os/Parcel:obtain	()Landroid/os/Parcel;
    //   8: astore 6
    //   10: aload 5
    //   12: ldc 24
    //   14: invokevirtual 28	android/os/Parcel:writeInterfaceToken	(Ljava/lang/String;)V
    //   17: aload_1
    //   18: ifnull +82 -> 100
    //   21: aload_1
    //   22: invokeinterface 34 1 0
    //   27: astore 8
    //   29: aload 5
    //   31: aload 8
    //   33: invokevirtual 37	android/os/Parcel:writeStrongBinder	(Landroid/os/IBinder;)V
    //   36: aload 5
    //   38: iload_2
    //   39: invokevirtual 41	android/os/Parcel:writeInt	(I)V
    //   42: aload 5
    //   44: aload_3
    //   45: invokevirtual 57	android/os/Parcel:writeString	(Ljava/lang/String;)V
    //   48: aload 4
    //   50: ifnull +56 -> 106
    //   53: aload 5
    //   55: iconst_1
    //   56: invokevirtual 41	android/os/Parcel:writeInt	(I)V
    //   59: aload 4
    //   61: aload 5
    //   63: iconst_0
    //   64: invokevirtual 64	android/os/Bundle:writeToParcel	(Landroid/os/Parcel;I)V
    //   67: aload_0
    //   68: getfield 15	hR:a	Landroid/os/IBinder;
    //   71: bipush 7
    //   73: aload 5
    //   75: aload 6
    //   77: iconst_0
    //   78: invokeinterface 47 5 0
    //   83: pop
    //   84: aload 6
    //   86: invokevirtual 50	android/os/Parcel:readException	()V
    //   89: aload 6
    //   91: invokevirtual 53	android/os/Parcel:recycle	()V
    //   94: aload 5
    //   96: invokevirtual 53	android/os/Parcel:recycle	()V
    //   99: return
    //   100: aconst_null
    //   101: astore 8
    //   103: goto -74 -> 29
    //   106: aload 5
    //   108: iconst_0
    //   109: invokevirtual 41	android/os/Parcel:writeInt	(I)V
    //   112: goto -45 -> 67
    //   115: astore 7
    //   117: aload 6
    //   119: invokevirtual 53	android/os/Parcel:recycle	()V
    //   122: aload 5
    //   124: invokevirtual 53	android/os/Parcel:recycle	()V
    //   127: aload 7
    //   129: athrow
    // Local variable table:
    //   start	length	slot	name	signature
    //   0	130	0	this	hR
    //   0	130	1	paramhM	hM
    //   0	130	2	paramInt	int
    //   0	130	3	paramString	java.lang.String
    //   0	130	4	paramBundle	android.os.Bundle
    //   3	120	5	localParcel1	android.os.Parcel
    //   8	110	6	localParcel2	android.os.Parcel
    //   115	13	7	localObject	Object
    //   27	75	8	localIBinder	IBinder
    // Exception table:
    //   from	to	target	type
    //   10	89	115	finally
    //   106	112	115	finally
  }
  
  /* Error */
  public void e(hM paramhM, int paramInt, java.lang.String paramString)
  {
    // Byte code:
    //   0: invokestatic 22	android/os/Parcel:obtain	()Landroid/os/Parcel;
    //   3: astore 4
    //   5: invokestatic 22	android/os/Parcel:obtain	()Landroid/os/Parcel;
    //   8: astore 5
    //   10: aload 4
    //   12: ldc 24
    //   14: invokevirtual 28	android/os/Parcel:writeInterfaceToken	(Ljava/lang/String;)V
    //   17: aload_1
    //   18: ifnull +63 -> 81
    //   21: aload_1
    //   22: invokeinterface 34 1 0
    //   27: astore 7
    //   29: aload 4
    //   31: aload 7
    //   33: invokevirtual 37	android/os/Parcel:writeStrongBinder	(Landroid/os/IBinder;)V
    //   36: aload 4
    //   38: iload_2
    //   39: invokevirtual 41	android/os/Parcel:writeInt	(I)V
    //   42: aload 4
    //   44: aload_3
    //   45: invokevirtual 57	android/os/Parcel:writeString	(Ljava/lang/String;)V
    //   48: aload_0
    //   49: getfield 15	hR:a	Landroid/os/IBinder;
    //   52: bipush 26
    //   54: aload 4
    //   56: aload 5
    //   58: iconst_0
    //   59: invokeinterface 47 5 0
    //   64: pop
    //   65: aload 5
    //   67: invokevirtual 50	android/os/Parcel:readException	()V
    //   70: aload 5
    //   72: invokevirtual 53	android/os/Parcel:recycle	()V
    //   75: aload 4
    //   77: invokevirtual 53	android/os/Parcel:recycle	()V
    //   80: return
    //   81: aconst_null
    //   82: astore 7
    //   84: goto -55 -> 29
    //   87: astore 6
    //   89: aload 5
    //   91: invokevirtual 53	android/os/Parcel:recycle	()V
    //   94: aload 4
    //   96: invokevirtual 53	android/os/Parcel:recycle	()V
    //   99: aload 6
    //   101: athrow
    // Local variable table:
    //   start	length	slot	name	signature
    //   0	102	0	this	hR
    //   0	102	1	paramhM	hM
    //   0	102	2	paramInt	int
    //   0	102	3	paramString	java.lang.String
    //   3	92	4	localParcel1	android.os.Parcel
    //   8	82	5	localParcel2	android.os.Parcel
    //   87	13	6	localObject	Object
    //   27	56	7	localIBinder	IBinder
    // Exception table:
    //   from	to	target	type
    //   10	70	87	finally
  }
  
  /* Error */
  public void e(hM paramhM, int paramInt, java.lang.String paramString, android.os.Bundle paramBundle)
  {
    // Byte code:
    //   0: invokestatic 22	android/os/Parcel:obtain	()Landroid/os/Parcel;
    //   3: astore 5
    //   5: invokestatic 22	android/os/Parcel:obtain	()Landroid/os/Parcel;
    //   8: astore 6
    //   10: aload 5
    //   12: ldc 24
    //   14: invokevirtual 28	android/os/Parcel:writeInterfaceToken	(Ljava/lang/String;)V
    //   17: aload_1
    //   18: ifnull +82 -> 100
    //   21: aload_1
    //   22: invokeinterface 34 1 0
    //   27: astore 8
    //   29: aload 5
    //   31: aload 8
    //   33: invokevirtual 37	android/os/Parcel:writeStrongBinder	(Landroid/os/IBinder;)V
    //   36: aload 5
    //   38: iload_2
    //   39: invokevirtual 41	android/os/Parcel:writeInt	(I)V
    //   42: aload 5
    //   44: aload_3
    //   45: invokevirtual 57	android/os/Parcel:writeString	(Ljava/lang/String;)V
    //   48: aload 4
    //   50: ifnull +56 -> 106
    //   53: aload 5
    //   55: iconst_1
    //   56: invokevirtual 41	android/os/Parcel:writeInt	(I)V
    //   59: aload 4
    //   61: aload 5
    //   63: iconst_0
    //   64: invokevirtual 64	android/os/Bundle:writeToParcel	(Landroid/os/Parcel;I)V
    //   67: aload_0
    //   68: getfield 15	hR:a	Landroid/os/IBinder;
    //   71: bipush 8
    //   73: aload 5
    //   75: aload 6
    //   77: iconst_0
    //   78: invokeinterface 47 5 0
    //   83: pop
    //   84: aload 6
    //   86: invokevirtual 50	android/os/Parcel:readException	()V
    //   89: aload 6
    //   91: invokevirtual 53	android/os/Parcel:recycle	()V
    //   94: aload 5
    //   96: invokevirtual 53	android/os/Parcel:recycle	()V
    //   99: return
    //   100: aconst_null
    //   101: astore 8
    //   103: goto -74 -> 29
    //   106: aload 5
    //   108: iconst_0
    //   109: invokevirtual 41	android/os/Parcel:writeInt	(I)V
    //   112: goto -45 -> 67
    //   115: astore 7
    //   117: aload 6
    //   119: invokevirtual 53	android/os/Parcel:recycle	()V
    //   122: aload 5
    //   124: invokevirtual 53	android/os/Parcel:recycle	()V
    //   127: aload 7
    //   129: athrow
    // Local variable table:
    //   start	length	slot	name	signature
    //   0	130	0	this	hR
    //   0	130	1	paramhM	hM
    //   0	130	2	paramInt	int
    //   0	130	3	paramString	java.lang.String
    //   0	130	4	paramBundle	android.os.Bundle
    //   3	120	5	localParcel1	android.os.Parcel
    //   8	110	6	localParcel2	android.os.Parcel
    //   115	13	7	localObject	Object
    //   27	75	8	localIBinder	IBinder
    // Exception table:
    //   from	to	target	type
    //   10	89	115	finally
    //   106	112	115	finally
  }
  
  /* Error */
  public void f(hM paramhM, int paramInt, java.lang.String paramString)
  {
    // Byte code:
    //   0: invokestatic 22	android/os/Parcel:obtain	()Landroid/os/Parcel;
    //   3: astore 4
    //   5: invokestatic 22	android/os/Parcel:obtain	()Landroid/os/Parcel;
    //   8: astore 5
    //   10: aload 4
    //   12: ldc 24
    //   14: invokevirtual 28	android/os/Parcel:writeInterfaceToken	(Ljava/lang/String;)V
    //   17: aload_1
    //   18: ifnull +63 -> 81
    //   21: aload_1
    //   22: invokeinterface 34 1 0
    //   27: astore 7
    //   29: aload 4
    //   31: aload 7
    //   33: invokevirtual 37	android/os/Parcel:writeStrongBinder	(Landroid/os/IBinder;)V
    //   36: aload 4
    //   38: iload_2
    //   39: invokevirtual 41	android/os/Parcel:writeInt	(I)V
    //   42: aload 4
    //   44: aload_3
    //   45: invokevirtual 57	android/os/Parcel:writeString	(Ljava/lang/String;)V
    //   48: aload_0
    //   49: getfield 15	hR:a	Landroid/os/IBinder;
    //   52: bipush 31
    //   54: aload 4
    //   56: aload 5
    //   58: iconst_0
    //   59: invokeinterface 47 5 0
    //   64: pop
    //   65: aload 5
    //   67: invokevirtual 50	android/os/Parcel:readException	()V
    //   70: aload 5
    //   72: invokevirtual 53	android/os/Parcel:recycle	()V
    //   75: aload 4
    //   77: invokevirtual 53	android/os/Parcel:recycle	()V
    //   80: return
    //   81: aconst_null
    //   82: astore 7
    //   84: goto -55 -> 29
    //   87: astore 6
    //   89: aload 5
    //   91: invokevirtual 53	android/os/Parcel:recycle	()V
    //   94: aload 4
    //   96: invokevirtual 53	android/os/Parcel:recycle	()V
    //   99: aload 6
    //   101: athrow
    // Local variable table:
    //   start	length	slot	name	signature
    //   0	102	0	this	hR
    //   0	102	1	paramhM	hM
    //   0	102	2	paramInt	int
    //   0	102	3	paramString	java.lang.String
    //   3	92	4	localParcel1	android.os.Parcel
    //   8	82	5	localParcel2	android.os.Parcel
    //   87	13	6	localObject	Object
    //   27	56	7	localIBinder	IBinder
    // Exception table:
    //   from	to	target	type
    //   10	70	87	finally
  }
  
  /* Error */
  public void f(hM paramhM, int paramInt, java.lang.String paramString, android.os.Bundle paramBundle)
  {
    // Byte code:
    //   0: invokestatic 22	android/os/Parcel:obtain	()Landroid/os/Parcel;
    //   3: astore 5
    //   5: invokestatic 22	android/os/Parcel:obtain	()Landroid/os/Parcel;
    //   8: astore 6
    //   10: aload 5
    //   12: ldc 24
    //   14: invokevirtual 28	android/os/Parcel:writeInterfaceToken	(Ljava/lang/String;)V
    //   17: aload_1
    //   18: ifnull +82 -> 100
    //   21: aload_1
    //   22: invokeinterface 34 1 0
    //   27: astore 8
    //   29: aload 5
    //   31: aload 8
    //   33: invokevirtual 37	android/os/Parcel:writeStrongBinder	(Landroid/os/IBinder;)V
    //   36: aload 5
    //   38: iload_2
    //   39: invokevirtual 41	android/os/Parcel:writeInt	(I)V
    //   42: aload 5
    //   44: aload_3
    //   45: invokevirtual 57	android/os/Parcel:writeString	(Ljava/lang/String;)V
    //   48: aload 4
    //   50: ifnull +56 -> 106
    //   53: aload 5
    //   55: iconst_1
    //   56: invokevirtual 41	android/os/Parcel:writeInt	(I)V
    //   59: aload 4
    //   61: aload 5
    //   63: iconst_0
    //   64: invokevirtual 64	android/os/Bundle:writeToParcel	(Landroid/os/Parcel;I)V
    //   67: aload_0
    //   68: getfield 15	hR:a	Landroid/os/IBinder;
    //   71: bipush 11
    //   73: aload 5
    //   75: aload 6
    //   77: iconst_0
    //   78: invokeinterface 47 5 0
    //   83: pop
    //   84: aload 6
    //   86: invokevirtual 50	android/os/Parcel:readException	()V
    //   89: aload 6
    //   91: invokevirtual 53	android/os/Parcel:recycle	()V
    //   94: aload 5
    //   96: invokevirtual 53	android/os/Parcel:recycle	()V
    //   99: return
    //   100: aconst_null
    //   101: astore 8
    //   103: goto -74 -> 29
    //   106: aload 5
    //   108: iconst_0
    //   109: invokevirtual 41	android/os/Parcel:writeInt	(I)V
    //   112: goto -45 -> 67
    //   115: astore 7
    //   117: aload 6
    //   119: invokevirtual 53	android/os/Parcel:recycle	()V
    //   122: aload 5
    //   124: invokevirtual 53	android/os/Parcel:recycle	()V
    //   127: aload 7
    //   129: athrow
    // Local variable table:
    //   start	length	slot	name	signature
    //   0	130	0	this	hR
    //   0	130	1	paramhM	hM
    //   0	130	2	paramInt	int
    //   0	130	3	paramString	java.lang.String
    //   0	130	4	paramBundle	android.os.Bundle
    //   3	120	5	localParcel1	android.os.Parcel
    //   8	110	6	localParcel2	android.os.Parcel
    //   115	13	7	localObject	Object
    //   27	75	8	localIBinder	IBinder
    // Exception table:
    //   from	to	target	type
    //   10	89	115	finally
    //   106	112	115	finally
  }
  
  /* Error */
  public void g(hM paramhM, int paramInt, java.lang.String paramString)
  {
    // Byte code:
    //   0: invokestatic 22	android/os/Parcel:obtain	()Landroid/os/Parcel;
    //   3: astore 4
    //   5: invokestatic 22	android/os/Parcel:obtain	()Landroid/os/Parcel;
    //   8: astore 5
    //   10: aload 4
    //   12: ldc 24
    //   14: invokevirtual 28	android/os/Parcel:writeInterfaceToken	(Ljava/lang/String;)V
    //   17: aload_1
    //   18: ifnull +63 -> 81
    //   21: aload_1
    //   22: invokeinterface 34 1 0
    //   27: astore 7
    //   29: aload 4
    //   31: aload 7
    //   33: invokevirtual 37	android/os/Parcel:writeStrongBinder	(Landroid/os/IBinder;)V
    //   36: aload 4
    //   38: iload_2
    //   39: invokevirtual 41	android/os/Parcel:writeInt	(I)V
    //   42: aload 4
    //   44: aload_3
    //   45: invokevirtual 57	android/os/Parcel:writeString	(Ljava/lang/String;)V
    //   48: aload_0
    //   49: getfield 15	hR:a	Landroid/os/IBinder;
    //   52: bipush 32
    //   54: aload 4
    //   56: aload 5
    //   58: iconst_0
    //   59: invokeinterface 47 5 0
    //   64: pop
    //   65: aload 5
    //   67: invokevirtual 50	android/os/Parcel:readException	()V
    //   70: aload 5
    //   72: invokevirtual 53	android/os/Parcel:recycle	()V
    //   75: aload 4
    //   77: invokevirtual 53	android/os/Parcel:recycle	()V
    //   80: return
    //   81: aconst_null
    //   82: astore 7
    //   84: goto -55 -> 29
    //   87: astore 6
    //   89: aload 5
    //   91: invokevirtual 53	android/os/Parcel:recycle	()V
    //   94: aload 4
    //   96: invokevirtual 53	android/os/Parcel:recycle	()V
    //   99: aload 6
    //   101: athrow
    // Local variable table:
    //   start	length	slot	name	signature
    //   0	102	0	this	hR
    //   0	102	1	paramhM	hM
    //   0	102	2	paramInt	int
    //   0	102	3	paramString	java.lang.String
    //   3	92	4	localParcel1	android.os.Parcel
    //   8	82	5	localParcel2	android.os.Parcel
    //   87	13	6	localObject	Object
    //   27	56	7	localIBinder	IBinder
    // Exception table:
    //   from	to	target	type
    //   10	70	87	finally
  }
  
  /* Error */
  public void g(hM paramhM, int paramInt, java.lang.String paramString, android.os.Bundle paramBundle)
  {
    // Byte code:
    //   0: invokestatic 22	android/os/Parcel:obtain	()Landroid/os/Parcel;
    //   3: astore 5
    //   5: invokestatic 22	android/os/Parcel:obtain	()Landroid/os/Parcel;
    //   8: astore 6
    //   10: aload 5
    //   12: ldc 24
    //   14: invokevirtual 28	android/os/Parcel:writeInterfaceToken	(Ljava/lang/String;)V
    //   17: aload_1
    //   18: ifnull +82 -> 100
    //   21: aload_1
    //   22: invokeinterface 34 1 0
    //   27: astore 8
    //   29: aload 5
    //   31: aload 8
    //   33: invokevirtual 37	android/os/Parcel:writeStrongBinder	(Landroid/os/IBinder;)V
    //   36: aload 5
    //   38: iload_2
    //   39: invokevirtual 41	android/os/Parcel:writeInt	(I)V
    //   42: aload 5
    //   44: aload_3
    //   45: invokevirtual 57	android/os/Parcel:writeString	(Ljava/lang/String;)V
    //   48: aload 4
    //   50: ifnull +56 -> 106
    //   53: aload 5
    //   55: iconst_1
    //   56: invokevirtual 41	android/os/Parcel:writeInt	(I)V
    //   59: aload 4
    //   61: aload 5
    //   63: iconst_0
    //   64: invokevirtual 64	android/os/Bundle:writeToParcel	(Landroid/os/Parcel;I)V
    //   67: aload_0
    //   68: getfield 15	hR:a	Landroid/os/IBinder;
    //   71: bipush 12
    //   73: aload 5
    //   75: aload 6
    //   77: iconst_0
    //   78: invokeinterface 47 5 0
    //   83: pop
    //   84: aload 6
    //   86: invokevirtual 50	android/os/Parcel:readException	()V
    //   89: aload 6
    //   91: invokevirtual 53	android/os/Parcel:recycle	()V
    //   94: aload 5
    //   96: invokevirtual 53	android/os/Parcel:recycle	()V
    //   99: return
    //   100: aconst_null
    //   101: astore 8
    //   103: goto -74 -> 29
    //   106: aload 5
    //   108: iconst_0
    //   109: invokevirtual 41	android/os/Parcel:writeInt	(I)V
    //   112: goto -45 -> 67
    //   115: astore 7
    //   117: aload 6
    //   119: invokevirtual 53	android/os/Parcel:recycle	()V
    //   122: aload 5
    //   124: invokevirtual 53	android/os/Parcel:recycle	()V
    //   127: aload 7
    //   129: athrow
    // Local variable table:
    //   start	length	slot	name	signature
    //   0	130	0	this	hR
    //   0	130	1	paramhM	hM
    //   0	130	2	paramInt	int
    //   0	130	3	paramString	java.lang.String
    //   0	130	4	paramBundle	android.os.Bundle
    //   3	120	5	localParcel1	android.os.Parcel
    //   8	110	6	localParcel2	android.os.Parcel
    //   115	13	7	localObject	Object
    //   27	75	8	localIBinder	IBinder
    // Exception table:
    //   from	to	target	type
    //   10	89	115	finally
    //   106	112	115	finally
  }
  
  /* Error */
  public void h(hM paramhM, int paramInt, java.lang.String paramString)
  {
    // Byte code:
    //   0: invokestatic 22	android/os/Parcel:obtain	()Landroid/os/Parcel;
    //   3: astore 4
    //   5: invokestatic 22	android/os/Parcel:obtain	()Landroid/os/Parcel;
    //   8: astore 5
    //   10: aload 4
    //   12: ldc 24
    //   14: invokevirtual 28	android/os/Parcel:writeInterfaceToken	(Ljava/lang/String;)V
    //   17: aload_1
    //   18: ifnull +63 -> 81
    //   21: aload_1
    //   22: invokeinterface 34 1 0
    //   27: astore 7
    //   29: aload 4
    //   31: aload 7
    //   33: invokevirtual 37	android/os/Parcel:writeStrongBinder	(Landroid/os/IBinder;)V
    //   36: aload 4
    //   38: iload_2
    //   39: invokevirtual 41	android/os/Parcel:writeInt	(I)V
    //   42: aload 4
    //   44: aload_3
    //   45: invokevirtual 57	android/os/Parcel:writeString	(Ljava/lang/String;)V
    //   48: aload_0
    //   49: getfield 15	hR:a	Landroid/os/IBinder;
    //   52: bipush 35
    //   54: aload 4
    //   56: aload 5
    //   58: iconst_0
    //   59: invokeinterface 47 5 0
    //   64: pop
    //   65: aload 5
    //   67: invokevirtual 50	android/os/Parcel:readException	()V
    //   70: aload 5
    //   72: invokevirtual 53	android/os/Parcel:recycle	()V
    //   75: aload 4
    //   77: invokevirtual 53	android/os/Parcel:recycle	()V
    //   80: return
    //   81: aconst_null
    //   82: astore 7
    //   84: goto -55 -> 29
    //   87: astore 6
    //   89: aload 5
    //   91: invokevirtual 53	android/os/Parcel:recycle	()V
    //   94: aload 4
    //   96: invokevirtual 53	android/os/Parcel:recycle	()V
    //   99: aload 6
    //   101: athrow
    // Local variable table:
    //   start	length	slot	name	signature
    //   0	102	0	this	hR
    //   0	102	1	paramhM	hM
    //   0	102	2	paramInt	int
    //   0	102	3	paramString	java.lang.String
    //   3	92	4	localParcel1	android.os.Parcel
    //   8	82	5	localParcel2	android.os.Parcel
    //   87	13	6	localObject	Object
    //   27	56	7	localIBinder	IBinder
    // Exception table:
    //   from	to	target	type
    //   10	70	87	finally
  }
  
  /* Error */
  public void h(hM paramhM, int paramInt, java.lang.String paramString, android.os.Bundle paramBundle)
  {
    // Byte code:
    //   0: invokestatic 22	android/os/Parcel:obtain	()Landroid/os/Parcel;
    //   3: astore 5
    //   5: invokestatic 22	android/os/Parcel:obtain	()Landroid/os/Parcel;
    //   8: astore 6
    //   10: aload 5
    //   12: ldc 24
    //   14: invokevirtual 28	android/os/Parcel:writeInterfaceToken	(Ljava/lang/String;)V
    //   17: aload_1
    //   18: ifnull +82 -> 100
    //   21: aload_1
    //   22: invokeinterface 34 1 0
    //   27: astore 8
    //   29: aload 5
    //   31: aload 8
    //   33: invokevirtual 37	android/os/Parcel:writeStrongBinder	(Landroid/os/IBinder;)V
    //   36: aload 5
    //   38: iload_2
    //   39: invokevirtual 41	android/os/Parcel:writeInt	(I)V
    //   42: aload 5
    //   44: aload_3
    //   45: invokevirtual 57	android/os/Parcel:writeString	(Ljava/lang/String;)V
    //   48: aload 4
    //   50: ifnull +56 -> 106
    //   53: aload 5
    //   55: iconst_1
    //   56: invokevirtual 41	android/os/Parcel:writeInt	(I)V
    //   59: aload 4
    //   61: aload 5
    //   63: iconst_0
    //   64: invokevirtual 64	android/os/Bundle:writeToParcel	(Landroid/os/Parcel;I)V
    //   67: aload_0
    //   68: getfield 15	hR:a	Landroid/os/IBinder;
    //   71: bipush 13
    //   73: aload 5
    //   75: aload 6
    //   77: iconst_0
    //   78: invokeinterface 47 5 0
    //   83: pop
    //   84: aload 6
    //   86: invokevirtual 50	android/os/Parcel:readException	()V
    //   89: aload 6
    //   91: invokevirtual 53	android/os/Parcel:recycle	()V
    //   94: aload 5
    //   96: invokevirtual 53	android/os/Parcel:recycle	()V
    //   99: return
    //   100: aconst_null
    //   101: astore 8
    //   103: goto -74 -> 29
    //   106: aload 5
    //   108: iconst_0
    //   109: invokevirtual 41	android/os/Parcel:writeInt	(I)V
    //   112: goto -45 -> 67
    //   115: astore 7
    //   117: aload 6
    //   119: invokevirtual 53	android/os/Parcel:recycle	()V
    //   122: aload 5
    //   124: invokevirtual 53	android/os/Parcel:recycle	()V
    //   127: aload 7
    //   129: athrow
    // Local variable table:
    //   start	length	slot	name	signature
    //   0	130	0	this	hR
    //   0	130	1	paramhM	hM
    //   0	130	2	paramInt	int
    //   0	130	3	paramString	java.lang.String
    //   0	130	4	paramBundle	android.os.Bundle
    //   3	120	5	localParcel1	android.os.Parcel
    //   8	110	6	localParcel2	android.os.Parcel
    //   115	13	7	localObject	Object
    //   27	75	8	localIBinder	IBinder
    // Exception table:
    //   from	to	target	type
    //   10	89	115	finally
    //   106	112	115	finally
  }
  
  /* Error */
  public void i(hM paramhM, int paramInt, java.lang.String paramString)
  {
    // Byte code:
    //   0: invokestatic 22	android/os/Parcel:obtain	()Landroid/os/Parcel;
    //   3: astore 4
    //   5: invokestatic 22	android/os/Parcel:obtain	()Landroid/os/Parcel;
    //   8: astore 5
    //   10: aload 4
    //   12: ldc 24
    //   14: invokevirtual 28	android/os/Parcel:writeInterfaceToken	(Ljava/lang/String;)V
    //   17: aload_1
    //   18: ifnull +63 -> 81
    //   21: aload_1
    //   22: invokeinterface 34 1 0
    //   27: astore 7
    //   29: aload 4
    //   31: aload 7
    //   33: invokevirtual 37	android/os/Parcel:writeStrongBinder	(Landroid/os/IBinder;)V
    //   36: aload 4
    //   38: iload_2
    //   39: invokevirtual 41	android/os/Parcel:writeInt	(I)V
    //   42: aload 4
    //   44: aload_3
    //   45: invokevirtual 57	android/os/Parcel:writeString	(Ljava/lang/String;)V
    //   48: aload_0
    //   49: getfield 15	hR:a	Landroid/os/IBinder;
    //   52: bipush 36
    //   54: aload 4
    //   56: aload 5
    //   58: iconst_0
    //   59: invokeinterface 47 5 0
    //   64: pop
    //   65: aload 5
    //   67: invokevirtual 50	android/os/Parcel:readException	()V
    //   70: aload 5
    //   72: invokevirtual 53	android/os/Parcel:recycle	()V
    //   75: aload 4
    //   77: invokevirtual 53	android/os/Parcel:recycle	()V
    //   80: return
    //   81: aconst_null
    //   82: astore 7
    //   84: goto -55 -> 29
    //   87: astore 6
    //   89: aload 5
    //   91: invokevirtual 53	android/os/Parcel:recycle	()V
    //   94: aload 4
    //   96: invokevirtual 53	android/os/Parcel:recycle	()V
    //   99: aload 6
    //   101: athrow
    // Local variable table:
    //   start	length	slot	name	signature
    //   0	102	0	this	hR
    //   0	102	1	paramhM	hM
    //   0	102	2	paramInt	int
    //   0	102	3	paramString	java.lang.String
    //   3	92	4	localParcel1	android.os.Parcel
    //   8	82	5	localParcel2	android.os.Parcel
    //   87	13	6	localObject	Object
    //   27	56	7	localIBinder	IBinder
    // Exception table:
    //   from	to	target	type
    //   10	70	87	finally
  }
  
  /* Error */
  public void i(hM paramhM, int paramInt, java.lang.String paramString, android.os.Bundle paramBundle)
  {
    // Byte code:
    //   0: invokestatic 22	android/os/Parcel:obtain	()Landroid/os/Parcel;
    //   3: astore 5
    //   5: invokestatic 22	android/os/Parcel:obtain	()Landroid/os/Parcel;
    //   8: astore 6
    //   10: aload 5
    //   12: ldc 24
    //   14: invokevirtual 28	android/os/Parcel:writeInterfaceToken	(Ljava/lang/String;)V
    //   17: aload_1
    //   18: ifnull +82 -> 100
    //   21: aload_1
    //   22: invokeinterface 34 1 0
    //   27: astore 8
    //   29: aload 5
    //   31: aload 8
    //   33: invokevirtual 37	android/os/Parcel:writeStrongBinder	(Landroid/os/IBinder;)V
    //   36: aload 5
    //   38: iload_2
    //   39: invokevirtual 41	android/os/Parcel:writeInt	(I)V
    //   42: aload 5
    //   44: aload_3
    //   45: invokevirtual 57	android/os/Parcel:writeString	(Ljava/lang/String;)V
    //   48: aload 4
    //   50: ifnull +56 -> 106
    //   53: aload 5
    //   55: iconst_1
    //   56: invokevirtual 41	android/os/Parcel:writeInt	(I)V
    //   59: aload 4
    //   61: aload 5
    //   63: iconst_0
    //   64: invokevirtual 64	android/os/Bundle:writeToParcel	(Landroid/os/Parcel;I)V
    //   67: aload_0
    //   68: getfield 15	hR:a	Landroid/os/IBinder;
    //   71: bipush 14
    //   73: aload 5
    //   75: aload 6
    //   77: iconst_0
    //   78: invokeinterface 47 5 0
    //   83: pop
    //   84: aload 6
    //   86: invokevirtual 50	android/os/Parcel:readException	()V
    //   89: aload 6
    //   91: invokevirtual 53	android/os/Parcel:recycle	()V
    //   94: aload 5
    //   96: invokevirtual 53	android/os/Parcel:recycle	()V
    //   99: return
    //   100: aconst_null
    //   101: astore 8
    //   103: goto -74 -> 29
    //   106: aload 5
    //   108: iconst_0
    //   109: invokevirtual 41	android/os/Parcel:writeInt	(I)V
    //   112: goto -45 -> 67
    //   115: astore 7
    //   117: aload 6
    //   119: invokevirtual 53	android/os/Parcel:recycle	()V
    //   122: aload 5
    //   124: invokevirtual 53	android/os/Parcel:recycle	()V
    //   127: aload 7
    //   129: athrow
    // Local variable table:
    //   start	length	slot	name	signature
    //   0	130	0	this	hR
    //   0	130	1	paramhM	hM
    //   0	130	2	paramInt	int
    //   0	130	3	paramString	java.lang.String
    //   0	130	4	paramBundle	android.os.Bundle
    //   3	120	5	localParcel1	android.os.Parcel
    //   8	110	6	localParcel2	android.os.Parcel
    //   115	13	7	localObject	Object
    //   27	75	8	localIBinder	IBinder
    // Exception table:
    //   from	to	target	type
    //   10	89	115	finally
    //   106	112	115	finally
  }
  
  /* Error */
  public void j(hM paramhM, int paramInt, java.lang.String paramString)
  {
    // Byte code:
    //   0: invokestatic 22	android/os/Parcel:obtain	()Landroid/os/Parcel;
    //   3: astore 4
    //   5: invokestatic 22	android/os/Parcel:obtain	()Landroid/os/Parcel;
    //   8: astore 5
    //   10: aload 4
    //   12: ldc 24
    //   14: invokevirtual 28	android/os/Parcel:writeInterfaceToken	(Ljava/lang/String;)V
    //   17: aload_1
    //   18: ifnull +63 -> 81
    //   21: aload_1
    //   22: invokeinterface 34 1 0
    //   27: astore 7
    //   29: aload 4
    //   31: aload 7
    //   33: invokevirtual 37	android/os/Parcel:writeStrongBinder	(Landroid/os/IBinder;)V
    //   36: aload 4
    //   38: iload_2
    //   39: invokevirtual 41	android/os/Parcel:writeInt	(I)V
    //   42: aload 4
    //   44: aload_3
    //   45: invokevirtual 57	android/os/Parcel:writeString	(Ljava/lang/String;)V
    //   48: aload_0
    //   49: getfield 15	hR:a	Landroid/os/IBinder;
    //   52: bipush 40
    //   54: aload 4
    //   56: aload 5
    //   58: iconst_0
    //   59: invokeinterface 47 5 0
    //   64: pop
    //   65: aload 5
    //   67: invokevirtual 50	android/os/Parcel:readException	()V
    //   70: aload 5
    //   72: invokevirtual 53	android/os/Parcel:recycle	()V
    //   75: aload 4
    //   77: invokevirtual 53	android/os/Parcel:recycle	()V
    //   80: return
    //   81: aconst_null
    //   82: astore 7
    //   84: goto -55 -> 29
    //   87: astore 6
    //   89: aload 5
    //   91: invokevirtual 53	android/os/Parcel:recycle	()V
    //   94: aload 4
    //   96: invokevirtual 53	android/os/Parcel:recycle	()V
    //   99: aload 6
    //   101: athrow
    // Local variable table:
    //   start	length	slot	name	signature
    //   0	102	0	this	hR
    //   0	102	1	paramhM	hM
    //   0	102	2	paramInt	int
    //   0	102	3	paramString	java.lang.String
    //   3	92	4	localParcel1	android.os.Parcel
    //   8	82	5	localParcel2	android.os.Parcel
    //   87	13	6	localObject	Object
    //   27	56	7	localIBinder	IBinder
    // Exception table:
    //   from	to	target	type
    //   10	70	87	finally
  }
  
  /* Error */
  public void j(hM paramhM, int paramInt, java.lang.String paramString, android.os.Bundle paramBundle)
  {
    // Byte code:
    //   0: invokestatic 22	android/os/Parcel:obtain	()Landroid/os/Parcel;
    //   3: astore 5
    //   5: invokestatic 22	android/os/Parcel:obtain	()Landroid/os/Parcel;
    //   8: astore 6
    //   10: aload 5
    //   12: ldc 24
    //   14: invokevirtual 28	android/os/Parcel:writeInterfaceToken	(Ljava/lang/String;)V
    //   17: aload_1
    //   18: ifnull +82 -> 100
    //   21: aload_1
    //   22: invokeinterface 34 1 0
    //   27: astore 8
    //   29: aload 5
    //   31: aload 8
    //   33: invokevirtual 37	android/os/Parcel:writeStrongBinder	(Landroid/os/IBinder;)V
    //   36: aload 5
    //   38: iload_2
    //   39: invokevirtual 41	android/os/Parcel:writeInt	(I)V
    //   42: aload 5
    //   44: aload_3
    //   45: invokevirtual 57	android/os/Parcel:writeString	(Ljava/lang/String;)V
    //   48: aload 4
    //   50: ifnull +56 -> 106
    //   53: aload 5
    //   55: iconst_1
    //   56: invokevirtual 41	android/os/Parcel:writeInt	(I)V
    //   59: aload 4
    //   61: aload 5
    //   63: iconst_0
    //   64: invokevirtual 64	android/os/Bundle:writeToParcel	(Landroid/os/Parcel;I)V
    //   67: aload_0
    //   68: getfield 15	hR:a	Landroid/os/IBinder;
    //   71: bipush 15
    //   73: aload 5
    //   75: aload 6
    //   77: iconst_0
    //   78: invokeinterface 47 5 0
    //   83: pop
    //   84: aload 6
    //   86: invokevirtual 50	android/os/Parcel:readException	()V
    //   89: aload 6
    //   91: invokevirtual 53	android/os/Parcel:recycle	()V
    //   94: aload 5
    //   96: invokevirtual 53	android/os/Parcel:recycle	()V
    //   99: return
    //   100: aconst_null
    //   101: astore 8
    //   103: goto -74 -> 29
    //   106: aload 5
    //   108: iconst_0
    //   109: invokevirtual 41	android/os/Parcel:writeInt	(I)V
    //   112: goto -45 -> 67
    //   115: astore 7
    //   117: aload 6
    //   119: invokevirtual 53	android/os/Parcel:recycle	()V
    //   122: aload 5
    //   124: invokevirtual 53	android/os/Parcel:recycle	()V
    //   127: aload 7
    //   129: athrow
    // Local variable table:
    //   start	length	slot	name	signature
    //   0	130	0	this	hR
    //   0	130	1	paramhM	hM
    //   0	130	2	paramInt	int
    //   0	130	3	paramString	java.lang.String
    //   0	130	4	paramBundle	android.os.Bundle
    //   3	120	5	localParcel1	android.os.Parcel
    //   8	110	6	localParcel2	android.os.Parcel
    //   115	13	7	localObject	Object
    //   27	75	8	localIBinder	IBinder
    // Exception table:
    //   from	to	target	type
    //   10	89	115	finally
    //   106	112	115	finally
  }
  
  /* Error */
  public void k(hM paramhM, int paramInt, java.lang.String paramString)
  {
    // Byte code:
    //   0: invokestatic 22	android/os/Parcel:obtain	()Landroid/os/Parcel;
    //   3: astore 4
    //   5: invokestatic 22	android/os/Parcel:obtain	()Landroid/os/Parcel;
    //   8: astore 5
    //   10: aload 4
    //   12: ldc 24
    //   14: invokevirtual 28	android/os/Parcel:writeInterfaceToken	(Ljava/lang/String;)V
    //   17: aload_1
    //   18: ifnull +63 -> 81
    //   21: aload_1
    //   22: invokeinterface 34 1 0
    //   27: astore 7
    //   29: aload 4
    //   31: aload 7
    //   33: invokevirtual 37	android/os/Parcel:writeStrongBinder	(Landroid/os/IBinder;)V
    //   36: aload 4
    //   38: iload_2
    //   39: invokevirtual 41	android/os/Parcel:writeInt	(I)V
    //   42: aload 4
    //   44: aload_3
    //   45: invokevirtual 57	android/os/Parcel:writeString	(Ljava/lang/String;)V
    //   48: aload_0
    //   49: getfield 15	hR:a	Landroid/os/IBinder;
    //   52: bipush 42
    //   54: aload 4
    //   56: aload 5
    //   58: iconst_0
    //   59: invokeinterface 47 5 0
    //   64: pop
    //   65: aload 5
    //   67: invokevirtual 50	android/os/Parcel:readException	()V
    //   70: aload 5
    //   72: invokevirtual 53	android/os/Parcel:recycle	()V
    //   75: aload 4
    //   77: invokevirtual 53	android/os/Parcel:recycle	()V
    //   80: return
    //   81: aconst_null
    //   82: astore 7
    //   84: goto -55 -> 29
    //   87: astore 6
    //   89: aload 5
    //   91: invokevirtual 53	android/os/Parcel:recycle	()V
    //   94: aload 4
    //   96: invokevirtual 53	android/os/Parcel:recycle	()V
    //   99: aload 6
    //   101: athrow
    // Local variable table:
    //   start	length	slot	name	signature
    //   0	102	0	this	hR
    //   0	102	1	paramhM	hM
    //   0	102	2	paramInt	int
    //   0	102	3	paramString	java.lang.String
    //   3	92	4	localParcel1	android.os.Parcel
    //   8	82	5	localParcel2	android.os.Parcel
    //   87	13	6	localObject	Object
    //   27	56	7	localIBinder	IBinder
    // Exception table:
    //   from	to	target	type
    //   10	70	87	finally
  }
  
  /* Error */
  public void k(hM paramhM, int paramInt, java.lang.String paramString, android.os.Bundle paramBundle)
  {
    // Byte code:
    //   0: invokestatic 22	android/os/Parcel:obtain	()Landroid/os/Parcel;
    //   3: astore 5
    //   5: invokestatic 22	android/os/Parcel:obtain	()Landroid/os/Parcel;
    //   8: astore 6
    //   10: aload 5
    //   12: ldc 24
    //   14: invokevirtual 28	android/os/Parcel:writeInterfaceToken	(Ljava/lang/String;)V
    //   17: aload_1
    //   18: ifnull +82 -> 100
    //   21: aload_1
    //   22: invokeinterface 34 1 0
    //   27: astore 8
    //   29: aload 5
    //   31: aload 8
    //   33: invokevirtual 37	android/os/Parcel:writeStrongBinder	(Landroid/os/IBinder;)V
    //   36: aload 5
    //   38: iload_2
    //   39: invokevirtual 41	android/os/Parcel:writeInt	(I)V
    //   42: aload 5
    //   44: aload_3
    //   45: invokevirtual 57	android/os/Parcel:writeString	(Ljava/lang/String;)V
    //   48: aload 4
    //   50: ifnull +56 -> 106
    //   53: aload 5
    //   55: iconst_1
    //   56: invokevirtual 41	android/os/Parcel:writeInt	(I)V
    //   59: aload 4
    //   61: aload 5
    //   63: iconst_0
    //   64: invokevirtual 64	android/os/Bundle:writeToParcel	(Landroid/os/Parcel;I)V
    //   67: aload_0
    //   68: getfield 15	hR:a	Landroid/os/IBinder;
    //   71: bipush 16
    //   73: aload 5
    //   75: aload 6
    //   77: iconst_0
    //   78: invokeinterface 47 5 0
    //   83: pop
    //   84: aload 6
    //   86: invokevirtual 50	android/os/Parcel:readException	()V
    //   89: aload 6
    //   91: invokevirtual 53	android/os/Parcel:recycle	()V
    //   94: aload 5
    //   96: invokevirtual 53	android/os/Parcel:recycle	()V
    //   99: return
    //   100: aconst_null
    //   101: astore 8
    //   103: goto -74 -> 29
    //   106: aload 5
    //   108: iconst_0
    //   109: invokevirtual 41	android/os/Parcel:writeInt	(I)V
    //   112: goto -45 -> 67
    //   115: astore 7
    //   117: aload 6
    //   119: invokevirtual 53	android/os/Parcel:recycle	()V
    //   122: aload 5
    //   124: invokevirtual 53	android/os/Parcel:recycle	()V
    //   127: aload 7
    //   129: athrow
    // Local variable table:
    //   start	length	slot	name	signature
    //   0	130	0	this	hR
    //   0	130	1	paramhM	hM
    //   0	130	2	paramInt	int
    //   0	130	3	paramString	java.lang.String
    //   0	130	4	paramBundle	android.os.Bundle
    //   3	120	5	localParcel1	android.os.Parcel
    //   8	110	6	localParcel2	android.os.Parcel
    //   115	13	7	localObject	Object
    //   27	75	8	localIBinder	IBinder
    // Exception table:
    //   from	to	target	type
    //   10	89	115	finally
    //   106	112	115	finally
  }
  
  /* Error */
  public void l(hM paramhM, int paramInt, java.lang.String paramString)
  {
    // Byte code:
    //   0: invokestatic 22	android/os/Parcel:obtain	()Landroid/os/Parcel;
    //   3: astore 4
    //   5: invokestatic 22	android/os/Parcel:obtain	()Landroid/os/Parcel;
    //   8: astore 5
    //   10: aload 4
    //   12: ldc 24
    //   14: invokevirtual 28	android/os/Parcel:writeInterfaceToken	(Ljava/lang/String;)V
    //   17: aload_1
    //   18: ifnull +63 -> 81
    //   21: aload_1
    //   22: invokeinterface 34 1 0
    //   27: astore 7
    //   29: aload 4
    //   31: aload 7
    //   33: invokevirtual 37	android/os/Parcel:writeStrongBinder	(Landroid/os/IBinder;)V
    //   36: aload 4
    //   38: iload_2
    //   39: invokevirtual 41	android/os/Parcel:writeInt	(I)V
    //   42: aload 4
    //   44: aload_3
    //   45: invokevirtual 57	android/os/Parcel:writeString	(Ljava/lang/String;)V
    //   48: aload_0
    //   49: getfield 15	hR:a	Landroid/os/IBinder;
    //   52: bipush 44
    //   54: aload 4
    //   56: aload 5
    //   58: iconst_0
    //   59: invokeinterface 47 5 0
    //   64: pop
    //   65: aload 5
    //   67: invokevirtual 50	android/os/Parcel:readException	()V
    //   70: aload 5
    //   72: invokevirtual 53	android/os/Parcel:recycle	()V
    //   75: aload 4
    //   77: invokevirtual 53	android/os/Parcel:recycle	()V
    //   80: return
    //   81: aconst_null
    //   82: astore 7
    //   84: goto -55 -> 29
    //   87: astore 6
    //   89: aload 5
    //   91: invokevirtual 53	android/os/Parcel:recycle	()V
    //   94: aload 4
    //   96: invokevirtual 53	android/os/Parcel:recycle	()V
    //   99: aload 6
    //   101: athrow
    // Local variable table:
    //   start	length	slot	name	signature
    //   0	102	0	this	hR
    //   0	102	1	paramhM	hM
    //   0	102	2	paramInt	int
    //   0	102	3	paramString	java.lang.String
    //   3	92	4	localParcel1	android.os.Parcel
    //   8	82	5	localParcel2	android.os.Parcel
    //   87	13	6	localObject	Object
    //   27	56	7	localIBinder	IBinder
    // Exception table:
    //   from	to	target	type
    //   10	70	87	finally
  }
  
  /* Error */
  public void l(hM paramhM, int paramInt, java.lang.String paramString, android.os.Bundle paramBundle)
  {
    // Byte code:
    //   0: invokestatic 22	android/os/Parcel:obtain	()Landroid/os/Parcel;
    //   3: astore 5
    //   5: invokestatic 22	android/os/Parcel:obtain	()Landroid/os/Parcel;
    //   8: astore 6
    //   10: aload 5
    //   12: ldc 24
    //   14: invokevirtual 28	android/os/Parcel:writeInterfaceToken	(Ljava/lang/String;)V
    //   17: aload_1
    //   18: ifnull +82 -> 100
    //   21: aload_1
    //   22: invokeinterface 34 1 0
    //   27: astore 8
    //   29: aload 5
    //   31: aload 8
    //   33: invokevirtual 37	android/os/Parcel:writeStrongBinder	(Landroid/os/IBinder;)V
    //   36: aload 5
    //   38: iload_2
    //   39: invokevirtual 41	android/os/Parcel:writeInt	(I)V
    //   42: aload 5
    //   44: aload_3
    //   45: invokevirtual 57	android/os/Parcel:writeString	(Ljava/lang/String;)V
    //   48: aload 4
    //   50: ifnull +56 -> 106
    //   53: aload 5
    //   55: iconst_1
    //   56: invokevirtual 41	android/os/Parcel:writeInt	(I)V
    //   59: aload 4
    //   61: aload 5
    //   63: iconst_0
    //   64: invokevirtual 64	android/os/Bundle:writeToParcel	(Landroid/os/Parcel;I)V
    //   67: aload_0
    //   68: getfield 15	hR:a	Landroid/os/IBinder;
    //   71: bipush 17
    //   73: aload 5
    //   75: aload 6
    //   77: iconst_0
    //   78: invokeinterface 47 5 0
    //   83: pop
    //   84: aload 6
    //   86: invokevirtual 50	android/os/Parcel:readException	()V
    //   89: aload 6
    //   91: invokevirtual 53	android/os/Parcel:recycle	()V
    //   94: aload 5
    //   96: invokevirtual 53	android/os/Parcel:recycle	()V
    //   99: return
    //   100: aconst_null
    //   101: astore 8
    //   103: goto -74 -> 29
    //   106: aload 5
    //   108: iconst_0
    //   109: invokevirtual 41	android/os/Parcel:writeInt	(I)V
    //   112: goto -45 -> 67
    //   115: astore 7
    //   117: aload 6
    //   119: invokevirtual 53	android/os/Parcel:recycle	()V
    //   122: aload 5
    //   124: invokevirtual 53	android/os/Parcel:recycle	()V
    //   127: aload 7
    //   129: athrow
    // Local variable table:
    //   start	length	slot	name	signature
    //   0	130	0	this	hR
    //   0	130	1	paramhM	hM
    //   0	130	2	paramInt	int
    //   0	130	3	paramString	java.lang.String
    //   0	130	4	paramBundle	android.os.Bundle
    //   3	120	5	localParcel1	android.os.Parcel
    //   8	110	6	localParcel2	android.os.Parcel
    //   115	13	7	localObject	Object
    //   27	75	8	localIBinder	IBinder
    // Exception table:
    //   from	to	target	type
    //   10	89	115	finally
    //   106	112	115	finally
  }
  
  /* Error */
  public void m(hM paramhM, int paramInt, java.lang.String paramString, android.os.Bundle paramBundle)
  {
    // Byte code:
    //   0: invokestatic 22	android/os/Parcel:obtain	()Landroid/os/Parcel;
    //   3: astore 5
    //   5: invokestatic 22	android/os/Parcel:obtain	()Landroid/os/Parcel;
    //   8: astore 6
    //   10: aload 5
    //   12: ldc 24
    //   14: invokevirtual 28	android/os/Parcel:writeInterfaceToken	(Ljava/lang/String;)V
    //   17: aload_1
    //   18: ifnull +82 -> 100
    //   21: aload_1
    //   22: invokeinterface 34 1 0
    //   27: astore 8
    //   29: aload 5
    //   31: aload 8
    //   33: invokevirtual 37	android/os/Parcel:writeStrongBinder	(Landroid/os/IBinder;)V
    //   36: aload 5
    //   38: iload_2
    //   39: invokevirtual 41	android/os/Parcel:writeInt	(I)V
    //   42: aload 5
    //   44: aload_3
    //   45: invokevirtual 57	android/os/Parcel:writeString	(Ljava/lang/String;)V
    //   48: aload 4
    //   50: ifnull +56 -> 106
    //   53: aload 5
    //   55: iconst_1
    //   56: invokevirtual 41	android/os/Parcel:writeInt	(I)V
    //   59: aload 4
    //   61: aload 5
    //   63: iconst_0
    //   64: invokevirtual 64	android/os/Bundle:writeToParcel	(Landroid/os/Parcel;I)V
    //   67: aload_0
    //   68: getfield 15	hR:a	Landroid/os/IBinder;
    //   71: bipush 18
    //   73: aload 5
    //   75: aload 6
    //   77: iconst_0
    //   78: invokeinterface 47 5 0
    //   83: pop
    //   84: aload 6
    //   86: invokevirtual 50	android/os/Parcel:readException	()V
    //   89: aload 6
    //   91: invokevirtual 53	android/os/Parcel:recycle	()V
    //   94: aload 5
    //   96: invokevirtual 53	android/os/Parcel:recycle	()V
    //   99: return
    //   100: aconst_null
    //   101: astore 8
    //   103: goto -74 -> 29
    //   106: aload 5
    //   108: iconst_0
    //   109: invokevirtual 41	android/os/Parcel:writeInt	(I)V
    //   112: goto -45 -> 67
    //   115: astore 7
    //   117: aload 6
    //   119: invokevirtual 53	android/os/Parcel:recycle	()V
    //   122: aload 5
    //   124: invokevirtual 53	android/os/Parcel:recycle	()V
    //   127: aload 7
    //   129: athrow
    // Local variable table:
    //   start	length	slot	name	signature
    //   0	130	0	this	hR
    //   0	130	1	paramhM	hM
    //   0	130	2	paramInt	int
    //   0	130	3	paramString	java.lang.String
    //   0	130	4	paramBundle	android.os.Bundle
    //   3	120	5	localParcel1	android.os.Parcel
    //   8	110	6	localParcel2	android.os.Parcel
    //   115	13	7	localObject	Object
    //   27	75	8	localIBinder	IBinder
    // Exception table:
    //   from	to	target	type
    //   10	89	115	finally
    //   106	112	115	finally
  }
  
  /* Error */
  public void n(hM paramhM, int paramInt, java.lang.String paramString, android.os.Bundle paramBundle)
  {
    // Byte code:
    //   0: invokestatic 22	android/os/Parcel:obtain	()Landroid/os/Parcel;
    //   3: astore 5
    //   5: invokestatic 22	android/os/Parcel:obtain	()Landroid/os/Parcel;
    //   8: astore 6
    //   10: aload 5
    //   12: ldc 24
    //   14: invokevirtual 28	android/os/Parcel:writeInterfaceToken	(Ljava/lang/String;)V
    //   17: aload_1
    //   18: ifnull +82 -> 100
    //   21: aload_1
    //   22: invokeinterface 34 1 0
    //   27: astore 8
    //   29: aload 5
    //   31: aload 8
    //   33: invokevirtual 37	android/os/Parcel:writeStrongBinder	(Landroid/os/IBinder;)V
    //   36: aload 5
    //   38: iload_2
    //   39: invokevirtual 41	android/os/Parcel:writeInt	(I)V
    //   42: aload 5
    //   44: aload_3
    //   45: invokevirtual 57	android/os/Parcel:writeString	(Ljava/lang/String;)V
    //   48: aload 4
    //   50: ifnull +56 -> 106
    //   53: aload 5
    //   55: iconst_1
    //   56: invokevirtual 41	android/os/Parcel:writeInt	(I)V
    //   59: aload 4
    //   61: aload 5
    //   63: iconst_0
    //   64: invokevirtual 64	android/os/Bundle:writeToParcel	(Landroid/os/Parcel;I)V
    //   67: aload_0
    //   68: getfield 15	hR:a	Landroid/os/IBinder;
    //   71: bipush 23
    //   73: aload 5
    //   75: aload 6
    //   77: iconst_0
    //   78: invokeinterface 47 5 0
    //   83: pop
    //   84: aload 6
    //   86: invokevirtual 50	android/os/Parcel:readException	()V
    //   89: aload 6
    //   91: invokevirtual 53	android/os/Parcel:recycle	()V
    //   94: aload 5
    //   96: invokevirtual 53	android/os/Parcel:recycle	()V
    //   99: return
    //   100: aconst_null
    //   101: astore 8
    //   103: goto -74 -> 29
    //   106: aload 5
    //   108: iconst_0
    //   109: invokevirtual 41	android/os/Parcel:writeInt	(I)V
    //   112: goto -45 -> 67
    //   115: astore 7
    //   117: aload 6
    //   119: invokevirtual 53	android/os/Parcel:recycle	()V
    //   122: aload 5
    //   124: invokevirtual 53	android/os/Parcel:recycle	()V
    //   127: aload 7
    //   129: athrow
    // Local variable table:
    //   start	length	slot	name	signature
    //   0	130	0	this	hR
    //   0	130	1	paramhM	hM
    //   0	130	2	paramInt	int
    //   0	130	3	paramString	java.lang.String
    //   0	130	4	paramBundle	android.os.Bundle
    //   3	120	5	localParcel1	android.os.Parcel
    //   8	110	6	localParcel2	android.os.Parcel
    //   115	13	7	localObject	Object
    //   27	75	8	localIBinder	IBinder
    // Exception table:
    //   from	to	target	type
    //   10	89	115	finally
    //   106	112	115	finally
  }
  
  /* Error */
  public void o(hM paramhM, int paramInt, java.lang.String paramString, android.os.Bundle paramBundle)
  {
    // Byte code:
    //   0: invokestatic 22	android/os/Parcel:obtain	()Landroid/os/Parcel;
    //   3: astore 5
    //   5: invokestatic 22	android/os/Parcel:obtain	()Landroid/os/Parcel;
    //   8: astore 6
    //   10: aload 5
    //   12: ldc 24
    //   14: invokevirtual 28	android/os/Parcel:writeInterfaceToken	(Ljava/lang/String;)V
    //   17: aload_1
    //   18: ifnull +82 -> 100
    //   21: aload_1
    //   22: invokeinterface 34 1 0
    //   27: astore 8
    //   29: aload 5
    //   31: aload 8
    //   33: invokevirtual 37	android/os/Parcel:writeStrongBinder	(Landroid/os/IBinder;)V
    //   36: aload 5
    //   38: iload_2
    //   39: invokevirtual 41	android/os/Parcel:writeInt	(I)V
    //   42: aload 5
    //   44: aload_3
    //   45: invokevirtual 57	android/os/Parcel:writeString	(Ljava/lang/String;)V
    //   48: aload 4
    //   50: ifnull +56 -> 106
    //   53: aload 5
    //   55: iconst_1
    //   56: invokevirtual 41	android/os/Parcel:writeInt	(I)V
    //   59: aload 4
    //   61: aload 5
    //   63: iconst_0
    //   64: invokevirtual 64	android/os/Bundle:writeToParcel	(Landroid/os/Parcel;I)V
    //   67: aload_0
    //   68: getfield 15	hR:a	Landroid/os/IBinder;
    //   71: bipush 25
    //   73: aload 5
    //   75: aload 6
    //   77: iconst_0
    //   78: invokeinterface 47 5 0
    //   83: pop
    //   84: aload 6
    //   86: invokevirtual 50	android/os/Parcel:readException	()V
    //   89: aload 6
    //   91: invokevirtual 53	android/os/Parcel:recycle	()V
    //   94: aload 5
    //   96: invokevirtual 53	android/os/Parcel:recycle	()V
    //   99: return
    //   100: aconst_null
    //   101: astore 8
    //   103: goto -74 -> 29
    //   106: aload 5
    //   108: iconst_0
    //   109: invokevirtual 41	android/os/Parcel:writeInt	(I)V
    //   112: goto -45 -> 67
    //   115: astore 7
    //   117: aload 6
    //   119: invokevirtual 53	android/os/Parcel:recycle	()V
    //   122: aload 5
    //   124: invokevirtual 53	android/os/Parcel:recycle	()V
    //   127: aload 7
    //   129: athrow
    // Local variable table:
    //   start	length	slot	name	signature
    //   0	130	0	this	hR
    //   0	130	1	paramhM	hM
    //   0	130	2	paramInt	int
    //   0	130	3	paramString	java.lang.String
    //   0	130	4	paramBundle	android.os.Bundle
    //   3	120	5	localParcel1	android.os.Parcel
    //   8	110	6	localParcel2	android.os.Parcel
    //   115	13	7	localObject	Object
    //   27	75	8	localIBinder	IBinder
    // Exception table:
    //   from	to	target	type
    //   10	89	115	finally
    //   106	112	115	finally
  }
  
  /* Error */
  public void p(hM paramhM, int paramInt, java.lang.String paramString, android.os.Bundle paramBundle)
  {
    // Byte code:
    //   0: invokestatic 22	android/os/Parcel:obtain	()Landroid/os/Parcel;
    //   3: astore 5
    //   5: invokestatic 22	android/os/Parcel:obtain	()Landroid/os/Parcel;
    //   8: astore 6
    //   10: aload 5
    //   12: ldc 24
    //   14: invokevirtual 28	android/os/Parcel:writeInterfaceToken	(Ljava/lang/String;)V
    //   17: aload_1
    //   18: ifnull +82 -> 100
    //   21: aload_1
    //   22: invokeinterface 34 1 0
    //   27: astore 8
    //   29: aload 5
    //   31: aload 8
    //   33: invokevirtual 37	android/os/Parcel:writeStrongBinder	(Landroid/os/IBinder;)V
    //   36: aload 5
    //   38: iload_2
    //   39: invokevirtual 41	android/os/Parcel:writeInt	(I)V
    //   42: aload 5
    //   44: aload_3
    //   45: invokevirtual 57	android/os/Parcel:writeString	(Ljava/lang/String;)V
    //   48: aload 4
    //   50: ifnull +56 -> 106
    //   53: aload 5
    //   55: iconst_1
    //   56: invokevirtual 41	android/os/Parcel:writeInt	(I)V
    //   59: aload 4
    //   61: aload 5
    //   63: iconst_0
    //   64: invokevirtual 64	android/os/Bundle:writeToParcel	(Landroid/os/Parcel;I)V
    //   67: aload_0
    //   68: getfield 15	hR:a	Landroid/os/IBinder;
    //   71: bipush 27
    //   73: aload 5
    //   75: aload 6
    //   77: iconst_0
    //   78: invokeinterface 47 5 0
    //   83: pop
    //   84: aload 6
    //   86: invokevirtual 50	android/os/Parcel:readException	()V
    //   89: aload 6
    //   91: invokevirtual 53	android/os/Parcel:recycle	()V
    //   94: aload 5
    //   96: invokevirtual 53	android/os/Parcel:recycle	()V
    //   99: return
    //   100: aconst_null
    //   101: astore 8
    //   103: goto -74 -> 29
    //   106: aload 5
    //   108: iconst_0
    //   109: invokevirtual 41	android/os/Parcel:writeInt	(I)V
    //   112: goto -45 -> 67
    //   115: astore 7
    //   117: aload 6
    //   119: invokevirtual 53	android/os/Parcel:recycle	()V
    //   122: aload 5
    //   124: invokevirtual 53	android/os/Parcel:recycle	()V
    //   127: aload 7
    //   129: athrow
    // Local variable table:
    //   start	length	slot	name	signature
    //   0	130	0	this	hR
    //   0	130	1	paramhM	hM
    //   0	130	2	paramInt	int
    //   0	130	3	paramString	java.lang.String
    //   0	130	4	paramBundle	android.os.Bundle
    //   3	120	5	localParcel1	android.os.Parcel
    //   8	110	6	localParcel2	android.os.Parcel
    //   115	13	7	localObject	Object
    //   27	75	8	localIBinder	IBinder
    // Exception table:
    //   from	to	target	type
    //   10	89	115	finally
    //   106	112	115	finally
  }
  
  /* Error */
  public void q(hM paramhM, int paramInt, java.lang.String paramString, android.os.Bundle paramBundle)
  {
    // Byte code:
    //   0: invokestatic 22	android/os/Parcel:obtain	()Landroid/os/Parcel;
    //   3: astore 5
    //   5: invokestatic 22	android/os/Parcel:obtain	()Landroid/os/Parcel;
    //   8: astore 6
    //   10: aload 5
    //   12: ldc 24
    //   14: invokevirtual 28	android/os/Parcel:writeInterfaceToken	(Ljava/lang/String;)V
    //   17: aload_1
    //   18: ifnull +82 -> 100
    //   21: aload_1
    //   22: invokeinterface 34 1 0
    //   27: astore 8
    //   29: aload 5
    //   31: aload 8
    //   33: invokevirtual 37	android/os/Parcel:writeStrongBinder	(Landroid/os/IBinder;)V
    //   36: aload 5
    //   38: iload_2
    //   39: invokevirtual 41	android/os/Parcel:writeInt	(I)V
    //   42: aload 5
    //   44: aload_3
    //   45: invokevirtual 57	android/os/Parcel:writeString	(Ljava/lang/String;)V
    //   48: aload 4
    //   50: ifnull +56 -> 106
    //   53: aload 5
    //   55: iconst_1
    //   56: invokevirtual 41	android/os/Parcel:writeInt	(I)V
    //   59: aload 4
    //   61: aload 5
    //   63: iconst_0
    //   64: invokevirtual 64	android/os/Bundle:writeToParcel	(Landroid/os/Parcel;I)V
    //   67: aload_0
    //   68: getfield 15	hR:a	Landroid/os/IBinder;
    //   71: bipush 37
    //   73: aload 5
    //   75: aload 6
    //   77: iconst_0
    //   78: invokeinterface 47 5 0
    //   83: pop
    //   84: aload 6
    //   86: invokevirtual 50	android/os/Parcel:readException	()V
    //   89: aload 6
    //   91: invokevirtual 53	android/os/Parcel:recycle	()V
    //   94: aload 5
    //   96: invokevirtual 53	android/os/Parcel:recycle	()V
    //   99: return
    //   100: aconst_null
    //   101: astore 8
    //   103: goto -74 -> 29
    //   106: aload 5
    //   108: iconst_0
    //   109: invokevirtual 41	android/os/Parcel:writeInt	(I)V
    //   112: goto -45 -> 67
    //   115: astore 7
    //   117: aload 6
    //   119: invokevirtual 53	android/os/Parcel:recycle	()V
    //   122: aload 5
    //   124: invokevirtual 53	android/os/Parcel:recycle	()V
    //   127: aload 7
    //   129: athrow
    // Local variable table:
    //   start	length	slot	name	signature
    //   0	130	0	this	hR
    //   0	130	1	paramhM	hM
    //   0	130	2	paramInt	int
    //   0	130	3	paramString	java.lang.String
    //   0	130	4	paramBundle	android.os.Bundle
    //   3	120	5	localParcel1	android.os.Parcel
    //   8	110	6	localParcel2	android.os.Parcel
    //   115	13	7	localObject	Object
    //   27	75	8	localIBinder	IBinder
    // Exception table:
    //   from	to	target	type
    //   10	89	115	finally
    //   106	112	115	finally
  }
  
  /* Error */
  public void r(hM paramhM, int paramInt, java.lang.String paramString, android.os.Bundle paramBundle)
  {
    // Byte code:
    //   0: invokestatic 22	android/os/Parcel:obtain	()Landroid/os/Parcel;
    //   3: astore 5
    //   5: invokestatic 22	android/os/Parcel:obtain	()Landroid/os/Parcel;
    //   8: astore 6
    //   10: aload 5
    //   12: ldc 24
    //   14: invokevirtual 28	android/os/Parcel:writeInterfaceToken	(Ljava/lang/String;)V
    //   17: aload_1
    //   18: ifnull +82 -> 100
    //   21: aload_1
    //   22: invokeinterface 34 1 0
    //   27: astore 8
    //   29: aload 5
    //   31: aload 8
    //   33: invokevirtual 37	android/os/Parcel:writeStrongBinder	(Landroid/os/IBinder;)V
    //   36: aload 5
    //   38: iload_2
    //   39: invokevirtual 41	android/os/Parcel:writeInt	(I)V
    //   42: aload 5
    //   44: aload_3
    //   45: invokevirtual 57	android/os/Parcel:writeString	(Ljava/lang/String;)V
    //   48: aload 4
    //   50: ifnull +56 -> 106
    //   53: aload 5
    //   55: iconst_1
    //   56: invokevirtual 41	android/os/Parcel:writeInt	(I)V
    //   59: aload 4
    //   61: aload 5
    //   63: iconst_0
    //   64: invokevirtual 64	android/os/Bundle:writeToParcel	(Landroid/os/Parcel;I)V
    //   67: aload_0
    //   68: getfield 15	hR:a	Landroid/os/IBinder;
    //   71: bipush 38
    //   73: aload 5
    //   75: aload 6
    //   77: iconst_0
    //   78: invokeinterface 47 5 0
    //   83: pop
    //   84: aload 6
    //   86: invokevirtual 50	android/os/Parcel:readException	()V
    //   89: aload 6
    //   91: invokevirtual 53	android/os/Parcel:recycle	()V
    //   94: aload 5
    //   96: invokevirtual 53	android/os/Parcel:recycle	()V
    //   99: return
    //   100: aconst_null
    //   101: astore 8
    //   103: goto -74 -> 29
    //   106: aload 5
    //   108: iconst_0
    //   109: invokevirtual 41	android/os/Parcel:writeInt	(I)V
    //   112: goto -45 -> 67
    //   115: astore 7
    //   117: aload 6
    //   119: invokevirtual 53	android/os/Parcel:recycle	()V
    //   122: aload 5
    //   124: invokevirtual 53	android/os/Parcel:recycle	()V
    //   127: aload 7
    //   129: athrow
    // Local variable table:
    //   start	length	slot	name	signature
    //   0	130	0	this	hR
    //   0	130	1	paramhM	hM
    //   0	130	2	paramInt	int
    //   0	130	3	paramString	java.lang.String
    //   0	130	4	paramBundle	android.os.Bundle
    //   3	120	5	localParcel1	android.os.Parcel
    //   8	110	6	localParcel2	android.os.Parcel
    //   115	13	7	localObject	Object
    //   27	75	8	localIBinder	IBinder
    // Exception table:
    //   from	to	target	type
    //   10	89	115	finally
    //   106	112	115	finally
  }
  
  /* Error */
  public void s(hM paramhM, int paramInt, java.lang.String paramString, android.os.Bundle paramBundle)
  {
    // Byte code:
    //   0: invokestatic 22	android/os/Parcel:obtain	()Landroid/os/Parcel;
    //   3: astore 5
    //   5: invokestatic 22	android/os/Parcel:obtain	()Landroid/os/Parcel;
    //   8: astore 6
    //   10: aload 5
    //   12: ldc 24
    //   14: invokevirtual 28	android/os/Parcel:writeInterfaceToken	(Ljava/lang/String;)V
    //   17: aload_1
    //   18: ifnull +82 -> 100
    //   21: aload_1
    //   22: invokeinterface 34 1 0
    //   27: astore 8
    //   29: aload 5
    //   31: aload 8
    //   33: invokevirtual 37	android/os/Parcel:writeStrongBinder	(Landroid/os/IBinder;)V
    //   36: aload 5
    //   38: iload_2
    //   39: invokevirtual 41	android/os/Parcel:writeInt	(I)V
    //   42: aload 5
    //   44: aload_3
    //   45: invokevirtual 57	android/os/Parcel:writeString	(Ljava/lang/String;)V
    //   48: aload 4
    //   50: ifnull +56 -> 106
    //   53: aload 5
    //   55: iconst_1
    //   56: invokevirtual 41	android/os/Parcel:writeInt	(I)V
    //   59: aload 4
    //   61: aload 5
    //   63: iconst_0
    //   64: invokevirtual 64	android/os/Bundle:writeToParcel	(Landroid/os/Parcel;I)V
    //   67: aload_0
    //   68: getfield 15	hR:a	Landroid/os/IBinder;
    //   71: bipush 41
    //   73: aload 5
    //   75: aload 6
    //   77: iconst_0
    //   78: invokeinterface 47 5 0
    //   83: pop
    //   84: aload 6
    //   86: invokevirtual 50	android/os/Parcel:readException	()V
    //   89: aload 6
    //   91: invokevirtual 53	android/os/Parcel:recycle	()V
    //   94: aload 5
    //   96: invokevirtual 53	android/os/Parcel:recycle	()V
    //   99: return
    //   100: aconst_null
    //   101: astore 8
    //   103: goto -74 -> 29
    //   106: aload 5
    //   108: iconst_0
    //   109: invokevirtual 41	android/os/Parcel:writeInt	(I)V
    //   112: goto -45 -> 67
    //   115: astore 7
    //   117: aload 6
    //   119: invokevirtual 53	android/os/Parcel:recycle	()V
    //   122: aload 5
    //   124: invokevirtual 53	android/os/Parcel:recycle	()V
    //   127: aload 7
    //   129: athrow
    // Local variable table:
    //   start	length	slot	name	signature
    //   0	130	0	this	hR
    //   0	130	1	paramhM	hM
    //   0	130	2	paramInt	int
    //   0	130	3	paramString	java.lang.String
    //   0	130	4	paramBundle	android.os.Bundle
    //   3	120	5	localParcel1	android.os.Parcel
    //   8	110	6	localParcel2	android.os.Parcel
    //   115	13	7	localObject	Object
    //   27	75	8	localIBinder	IBinder
    // Exception table:
    //   from	to	target	type
    //   10	89	115	finally
    //   106	112	115	finally
  }
  
  /* Error */
  public void t(hM paramhM, int paramInt, java.lang.String paramString, android.os.Bundle paramBundle)
  {
    // Byte code:
    //   0: invokestatic 22	android/os/Parcel:obtain	()Landroid/os/Parcel;
    //   3: astore 5
    //   5: invokestatic 22	android/os/Parcel:obtain	()Landroid/os/Parcel;
    //   8: astore 6
    //   10: aload 5
    //   12: ldc 24
    //   14: invokevirtual 28	android/os/Parcel:writeInterfaceToken	(Ljava/lang/String;)V
    //   17: aload_1
    //   18: ifnull +82 -> 100
    //   21: aload_1
    //   22: invokeinterface 34 1 0
    //   27: astore 8
    //   29: aload 5
    //   31: aload 8
    //   33: invokevirtual 37	android/os/Parcel:writeStrongBinder	(Landroid/os/IBinder;)V
    //   36: aload 5
    //   38: iload_2
    //   39: invokevirtual 41	android/os/Parcel:writeInt	(I)V
    //   42: aload 5
    //   44: aload_3
    //   45: invokevirtual 57	android/os/Parcel:writeString	(Ljava/lang/String;)V
    //   48: aload 4
    //   50: ifnull +56 -> 106
    //   53: aload 5
    //   55: iconst_1
    //   56: invokevirtual 41	android/os/Parcel:writeInt	(I)V
    //   59: aload 4
    //   61: aload 5
    //   63: iconst_0
    //   64: invokevirtual 64	android/os/Bundle:writeToParcel	(Landroid/os/Parcel;I)V
    //   67: aload_0
    //   68: getfield 15	hR:a	Landroid/os/IBinder;
    //   71: bipush 43
    //   73: aload 5
    //   75: aload 6
    //   77: iconst_0
    //   78: invokeinterface 47 5 0
    //   83: pop
    //   84: aload 6
    //   86: invokevirtual 50	android/os/Parcel:readException	()V
    //   89: aload 6
    //   91: invokevirtual 53	android/os/Parcel:recycle	()V
    //   94: aload 5
    //   96: invokevirtual 53	android/os/Parcel:recycle	()V
    //   99: return
    //   100: aconst_null
    //   101: astore 8
    //   103: goto -74 -> 29
    //   106: aload 5
    //   108: iconst_0
    //   109: invokevirtual 41	android/os/Parcel:writeInt	(I)V
    //   112: goto -45 -> 67
    //   115: astore 7
    //   117: aload 6
    //   119: invokevirtual 53	android/os/Parcel:recycle	()V
    //   122: aload 5
    //   124: invokevirtual 53	android/os/Parcel:recycle	()V
    //   127: aload 7
    //   129: athrow
    // Local variable table:
    //   start	length	slot	name	signature
    //   0	130	0	this	hR
    //   0	130	1	paramhM	hM
    //   0	130	2	paramInt	int
    //   0	130	3	paramString	java.lang.String
    //   0	130	4	paramBundle	android.os.Bundle
    //   3	120	5	localParcel1	android.os.Parcel
    //   8	110	6	localParcel2	android.os.Parcel
    //   115	13	7	localObject	Object
    //   27	75	8	localIBinder	IBinder
    // Exception table:
    //   from	to	target	type
    //   10	89	115	finally
    //   106	112	115	finally
  }
}


/* Location:           C:\Users\dreadiscool\Desktop\tools\classes-dex2jar.jar
 * Qualified Name:     hR
 * JD-Core Version:    0.7.0.1
 */