import android.content.Context;

class IZ
  implements Jd
{
  private final Context a;
  
  public IZ(Context paramContext)
  {
    this.a = paramContext.getApplicationContext();
  }
  
  /* Error */
  public IV a()
  {
    // Byte code:
    //   0: aconst_null
    //   1: astore_1
    //   2: invokestatic 32	android/os/Looper:myLooper	()Landroid/os/Looper;
    //   5: invokestatic 35	android/os/Looper:getMainLooper	()Landroid/os/Looper;
    //   8: if_acmpne +9 -> 17
    //   11: invokestatic 41	IC:g	()LIO;
    //   14: pop
    //   15: aload_1
    //   16: areturn
    //   17: aload_0
    //   18: getfield 21	IZ:a	Landroid/content/Context;
    //   21: invokevirtual 45	android/content/Context:getPackageManager	()Landroid/content/pm/PackageManager;
    //   24: ldc 47
    //   26: iconst_0
    //   27: invokevirtual 53	android/content/pm/PackageManager:getPackageInfo	(Ljava/lang/String;I)Landroid/content/pm/PackageInfo;
    //   30: pop
    //   31: new 55	Jb
    //   34: dup
    //   35: aconst_null
    //   36: invokespecial 58	Jb:<init>	(LJa;)V
    //   39: astore 5
    //   41: new 60	android/content/Intent
    //   44: dup
    //   45: ldc 62
    //   47: invokespecial 65	android/content/Intent:<init>	(Ljava/lang/String;)V
    //   50: astore 6
    //   52: aload 6
    //   54: ldc 67
    //   56: invokevirtual 71	android/content/Intent:setPackage	(Ljava/lang/String;)Landroid/content/Intent;
    //   59: pop
    //   60: aload_0
    //   61: getfield 21	IZ:a	Landroid/content/Context;
    //   64: aload 6
    //   66: aload 5
    //   68: iconst_1
    //   69: invokevirtual 75	android/content/Context:bindService	(Landroid/content/Intent;Landroid/content/ServiceConnection;I)Z
    //   72: istore 10
    //   74: iload 10
    //   76: ifeq +100 -> 176
    //   79: new 77	Jc
    //   82: dup
    //   83: aload 5
    //   85: invokevirtual 80	Jb:a	()Landroid/os/IBinder;
    //   88: invokespecial 83	Jc:<init>	(Landroid/os/IBinder;)V
    //   91: astore 12
    //   93: new 85	IV
    //   96: dup
    //   97: aload 12
    //   99: invokevirtual 88	Jc:a	()Ljava/lang/String;
    //   102: aload 12
    //   104: invokevirtual 92	Jc:b	()Z
    //   107: invokespecial 95	IV:<init>	(Ljava/lang/String;Z)V
    //   110: astore 13
    //   112: aload_0
    //   113: getfield 21	IZ:a	Landroid/content/Context;
    //   116: aload 5
    //   118: invokevirtual 99	android/content/Context:unbindService	(Landroid/content/ServiceConnection;)V
    //   121: aload 13
    //   123: astore_1
    //   124: goto -109 -> 15
    //   127: astore_2
    //   128: invokestatic 41	IC:g	()LIO;
    //   131: pop
    //   132: goto -117 -> 15
    //   135: astore 15
    //   137: invokestatic 41	IC:g	()LIO;
    //   140: pop
    //   141: aload_0
    //   142: getfield 21	IZ:a	Landroid/content/Context;
    //   145: aload 5
    //   147: invokevirtual 99	android/content/Context:unbindService	(Landroid/content/ServiceConnection;)V
    //   150: goto -135 -> 15
    //   153: astore 8
    //   155: invokestatic 41	IC:g	()LIO;
    //   158: pop
    //   159: goto -144 -> 15
    //   162: astore 14
    //   164: aload_0
    //   165: getfield 21	IZ:a	Landroid/content/Context;
    //   168: aload 5
    //   170: invokevirtual 99	android/content/Context:unbindService	(Landroid/content/ServiceConnection;)V
    //   173: aload 14
    //   175: athrow
    //   176: invokestatic 41	IC:g	()LIO;
    //   179: pop
    //   180: goto -165 -> 15
    // Local variable table:
    //   start	length	slot	name	signature
    //   0	183	0	this	IZ
    //   1	123	1	localObject1	Object
    //   127	1	2	localException1	java.lang.Exception
    //   39	130	5	localJb	Jb
    //   50	15	6	localIntent	android.content.Intent
    //   153	1	8	localThrowable	java.lang.Throwable
    //   72	3	10	bool	boolean
    //   91	12	12	localJc	Jc
    //   110	12	13	localIV	IV
    //   162	12	14	localObject2	Object
    //   135	1	15	localException2	java.lang.Exception
    // Exception table:
    //   from	to	target	type
    //   17	31	127	java/lang/Exception
    //   79	112	135	java/lang/Exception
    //   60	74	153	java/lang/Throwable
    //   112	121	153	java/lang/Throwable
    //   141	150	153	java/lang/Throwable
    //   164	180	153	java/lang/Throwable
    //   79	112	162	finally
    //   137	141	162	finally
  }
}


/* Location:           C:\Users\dreadiscool\Desktop\tools\classes-dex2jar.jar
 * Qualified Name:     IZ
 * JD-Core Version:    0.7.0.1
 */