import android.os.IBinder;
import android.os.Parcel;

class mB
  implements mz
{
  private IBinder a;
  
  mB(IBinder paramIBinder)
  {
    this.a = paramIBinder;
  }
  
  public void a()
  {
    Parcel localParcel1 = Parcel.obtain();
    Parcel localParcel2 = Parcel.obtain();
    try
    {
      localParcel1.writeInterfaceToken("com.google.android.gms.maps.model.internal.ICircleDelegate");
      this.a.transact(1, localParcel1, localParcel2, 0);
      localParcel2.readException();
      return;
    }
    finally
    {
      localParcel2.recycle();
      localParcel1.recycle();
    }
  }
  
  public void a(double paramDouble)
  {
    Parcel localParcel1 = Parcel.obtain();
    Parcel localParcel2 = Parcel.obtain();
    try
    {
      localParcel1.writeInterfaceToken("com.google.android.gms.maps.model.internal.ICircleDelegate");
      localParcel1.writeDouble(paramDouble);
      this.a.transact(5, localParcel1, localParcel2, 0);
      localParcel2.readException();
      return;
    }
    finally
    {
      localParcel2.recycle();
      localParcel1.recycle();
    }
  }
  
  public void a(float paramFloat)
  {
    Parcel localParcel1 = Parcel.obtain();
    Parcel localParcel2 = Parcel.obtain();
    try
    {
      localParcel1.writeInterfaceToken("com.google.android.gms.maps.model.internal.ICircleDelegate");
      localParcel1.writeFloat(paramFloat);
      this.a.transact(7, localParcel1, localParcel2, 0);
      localParcel2.readException();
      return;
    }
    finally
    {
      localParcel2.recycle();
      localParcel1.recycle();
    }
  }
  
  public void a(int paramInt)
  {
    Parcel localParcel1 = Parcel.obtain();
    Parcel localParcel2 = Parcel.obtain();
    try
    {
      localParcel1.writeInterfaceToken("com.google.android.gms.maps.model.internal.ICircleDelegate");
      localParcel1.writeInt(paramInt);
      this.a.transact(9, localParcel1, localParcel2, 0);
      localParcel2.readException();
      return;
    }
    finally
    {
      localParcel2.recycle();
      localParcel1.recycle();
    }
  }
  
  /* Error */
  public void a(com.google.android.gms.maps.model.LatLng paramLatLng)
  {
    // Byte code:
    //   0: invokestatic 21	android/os/Parcel:obtain	()Landroid/os/Parcel;
    //   3: astore_2
    //   4: invokestatic 21	android/os/Parcel:obtain	()Landroid/os/Parcel;
    //   7: astore_3
    //   8: aload_2
    //   9: ldc 23
    //   11: invokevirtual 27	android/os/Parcel:writeInterfaceToken	(Ljava/lang/String;)V
    //   14: aload_1
    //   15: ifnull +41 -> 56
    //   18: aload_2
    //   19: iconst_1
    //   20: invokevirtual 51	android/os/Parcel:writeInt	(I)V
    //   23: aload_1
    //   24: aload_2
    //   25: iconst_0
    //   26: invokevirtual 58	com/google/android/gms/maps/model/LatLng:writeToParcel	(Landroid/os/Parcel;I)V
    //   29: aload_0
    //   30: getfield 15	mB:a	Landroid/os/IBinder;
    //   33: iconst_3
    //   34: aload_2
    //   35: aload_3
    //   36: iconst_0
    //   37: invokeinterface 33 5 0
    //   42: pop
    //   43: aload_3
    //   44: invokevirtual 36	android/os/Parcel:readException	()V
    //   47: aload_3
    //   48: invokevirtual 39	android/os/Parcel:recycle	()V
    //   51: aload_2
    //   52: invokevirtual 39	android/os/Parcel:recycle	()V
    //   55: return
    //   56: aload_2
    //   57: iconst_0
    //   58: invokevirtual 51	android/os/Parcel:writeInt	(I)V
    //   61: goto -32 -> 29
    //   64: astore 4
    //   66: aload_3
    //   67: invokevirtual 39	android/os/Parcel:recycle	()V
    //   70: aload_2
    //   71: invokevirtual 39	android/os/Parcel:recycle	()V
    //   74: aload 4
    //   76: athrow
    // Local variable table:
    //   start	length	slot	name	signature
    //   0	77	0	this	mB
    //   0	77	1	paramLatLng	com.google.android.gms.maps.model.LatLng
    //   3	68	2	localParcel1	Parcel
    //   7	60	3	localParcel2	Parcel
    //   64	11	4	localObject	Object
    // Exception table:
    //   from	to	target	type
    //   8	47	64	finally
    //   56	61	64	finally
  }
  
  public void a(boolean paramBoolean)
  {
    int i = 0;
    Parcel localParcel1 = Parcel.obtain();
    Parcel localParcel2 = Parcel.obtain();
    try
    {
      localParcel1.writeInterfaceToken("com.google.android.gms.maps.model.internal.ICircleDelegate");
      if (paramBoolean) {
        i = 1;
      }
      localParcel1.writeInt(i);
      this.a.transact(15, localParcel1, localParcel2, 0);
      localParcel2.readException();
      return;
    }
    finally
    {
      localParcel2.recycle();
      localParcel1.recycle();
    }
  }
  
  /* Error */
  public boolean a(mz parammz)
  {
    // Byte code:
    //   0: iconst_0
    //   1: istore_2
    //   2: invokestatic 21	android/os/Parcel:obtain	()Landroid/os/Parcel;
    //   5: astore_3
    //   6: invokestatic 21	android/os/Parcel:obtain	()Landroid/os/Parcel;
    //   9: astore 4
    //   11: aload_3
    //   12: ldc 23
    //   14: invokevirtual 27	android/os/Parcel:writeInterfaceToken	(Ljava/lang/String;)V
    //   17: aload_1
    //   18: ifnull +63 -> 81
    //   21: aload_1
    //   22: invokeinterface 64 1 0
    //   27: astore 6
    //   29: aload_3
    //   30: aload 6
    //   32: invokevirtual 67	android/os/Parcel:writeStrongBinder	(Landroid/os/IBinder;)V
    //   35: aload_0
    //   36: getfield 15	mB:a	Landroid/os/IBinder;
    //   39: bipush 17
    //   41: aload_3
    //   42: aload 4
    //   44: iconst_0
    //   45: invokeinterface 33 5 0
    //   50: pop
    //   51: aload 4
    //   53: invokevirtual 36	android/os/Parcel:readException	()V
    //   56: aload 4
    //   58: invokevirtual 71	android/os/Parcel:readInt	()I
    //   61: istore 8
    //   63: iload 8
    //   65: ifeq +5 -> 70
    //   68: iconst_1
    //   69: istore_2
    //   70: aload 4
    //   72: invokevirtual 39	android/os/Parcel:recycle	()V
    //   75: aload_3
    //   76: invokevirtual 39	android/os/Parcel:recycle	()V
    //   79: iload_2
    //   80: ireturn
    //   81: aconst_null
    //   82: astore 6
    //   84: goto -55 -> 29
    //   87: astore 5
    //   89: aload 4
    //   91: invokevirtual 39	android/os/Parcel:recycle	()V
    //   94: aload_3
    //   95: invokevirtual 39	android/os/Parcel:recycle	()V
    //   98: aload 5
    //   100: athrow
    // Local variable table:
    //   start	length	slot	name	signature
    //   0	101	0	this	mB
    //   0	101	1	parammz	mz
    //   1	79	2	bool	boolean
    //   5	90	3	localParcel1	Parcel
    //   9	81	4	localParcel2	Parcel
    //   87	12	5	localObject	Object
    //   27	56	6	localIBinder	IBinder
    //   61	3	8	i	int
    // Exception table:
    //   from	to	target	type
    //   11	63	87	finally
  }
  
  public IBinder asBinder()
  {
    return this.a;
  }
  
  public String b()
  {
    Parcel localParcel1 = Parcel.obtain();
    Parcel localParcel2 = Parcel.obtain();
    try
    {
      localParcel1.writeInterfaceToken("com.google.android.gms.maps.model.internal.ICircleDelegate");
      this.a.transact(2, localParcel1, localParcel2, 0);
      localParcel2.readException();
      String str = localParcel2.readString();
      return str;
    }
    finally
    {
      localParcel2.recycle();
      localParcel1.recycle();
    }
  }
  
  public void b(float paramFloat)
  {
    Parcel localParcel1 = Parcel.obtain();
    Parcel localParcel2 = Parcel.obtain();
    try
    {
      localParcel1.writeInterfaceToken("com.google.android.gms.maps.model.internal.ICircleDelegate");
      localParcel1.writeFloat(paramFloat);
      this.a.transact(13, localParcel1, localParcel2, 0);
      localParcel2.readException();
      return;
    }
    finally
    {
      localParcel2.recycle();
      localParcel1.recycle();
    }
  }
  
  public void b(int paramInt)
  {
    Parcel localParcel1 = Parcel.obtain();
    Parcel localParcel2 = Parcel.obtain();
    try
    {
      localParcel1.writeInterfaceToken("com.google.android.gms.maps.model.internal.ICircleDelegate");
      localParcel1.writeInt(paramInt);
      this.a.transact(11, localParcel1, localParcel2, 0);
      localParcel2.readException();
      return;
    }
    finally
    {
      localParcel2.recycle();
      localParcel1.recycle();
    }
  }
  
  /* Error */
  public com.google.android.gms.maps.model.LatLng c()
  {
    // Byte code:
    //   0: invokestatic 21	android/os/Parcel:obtain	()Landroid/os/Parcel;
    //   3: astore_1
    //   4: invokestatic 21	android/os/Parcel:obtain	()Landroid/os/Parcel;
    //   7: astore_2
    //   8: aload_1
    //   9: ldc 23
    //   11: invokevirtual 27	android/os/Parcel:writeInterfaceToken	(Ljava/lang/String;)V
    //   14: aload_0
    //   15: getfield 15	mB:a	Landroid/os/IBinder;
    //   18: iconst_4
    //   19: aload_1
    //   20: aload_2
    //   21: iconst_0
    //   22: invokeinterface 33 5 0
    //   27: pop
    //   28: aload_2
    //   29: invokevirtual 36	android/os/Parcel:readException	()V
    //   32: aload_2
    //   33: invokevirtual 71	android/os/Parcel:readInt	()I
    //   36: ifeq +27 -> 63
    //   39: getstatic 82	com/google/android/gms/maps/model/LatLng:CREATOR	Lmp;
    //   42: aload_2
    //   43: invokevirtual 87	mp:a	(Landroid/os/Parcel;)Lcom/google/android/gms/maps/model/LatLng;
    //   46: astore 6
    //   48: aload 6
    //   50: astore 5
    //   52: aload_2
    //   53: invokevirtual 39	android/os/Parcel:recycle	()V
    //   56: aload_1
    //   57: invokevirtual 39	android/os/Parcel:recycle	()V
    //   60: aload 5
    //   62: areturn
    //   63: aconst_null
    //   64: astore 5
    //   66: goto -14 -> 52
    //   69: astore_3
    //   70: aload_2
    //   71: invokevirtual 39	android/os/Parcel:recycle	()V
    //   74: aload_1
    //   75: invokevirtual 39	android/os/Parcel:recycle	()V
    //   78: aload_3
    //   79: athrow
    // Local variable table:
    //   start	length	slot	name	signature
    //   0	80	0	this	mB
    //   3	72	1	localParcel1	Parcel
    //   7	64	2	localParcel2	Parcel
    //   69	10	3	localObject	Object
    //   50	15	5	localLatLng1	com.google.android.gms.maps.model.LatLng
    //   46	3	6	localLatLng2	com.google.android.gms.maps.model.LatLng
    // Exception table:
    //   from	to	target	type
    //   8	48	69	finally
  }
  
  public double d()
  {
    Parcel localParcel1 = Parcel.obtain();
    Parcel localParcel2 = Parcel.obtain();
    try
    {
      localParcel1.writeInterfaceToken("com.google.android.gms.maps.model.internal.ICircleDelegate");
      this.a.transact(6, localParcel1, localParcel2, 0);
      localParcel2.readException();
      double d = localParcel2.readDouble();
      return d;
    }
    finally
    {
      localParcel2.recycle();
      localParcel1.recycle();
    }
  }
  
  public float e()
  {
    Parcel localParcel1 = Parcel.obtain();
    Parcel localParcel2 = Parcel.obtain();
    try
    {
      localParcel1.writeInterfaceToken("com.google.android.gms.maps.model.internal.ICircleDelegate");
      this.a.transact(8, localParcel1, localParcel2, 0);
      localParcel2.readException();
      float f = localParcel2.readFloat();
      return f;
    }
    finally
    {
      localParcel2.recycle();
      localParcel1.recycle();
    }
  }
  
  public int f()
  {
    Parcel localParcel1 = Parcel.obtain();
    Parcel localParcel2 = Parcel.obtain();
    try
    {
      localParcel1.writeInterfaceToken("com.google.android.gms.maps.model.internal.ICircleDelegate");
      this.a.transact(10, localParcel1, localParcel2, 0);
      localParcel2.readException();
      int i = localParcel2.readInt();
      return i;
    }
    finally
    {
      localParcel2.recycle();
      localParcel1.recycle();
    }
  }
  
  public int g()
  {
    Parcel localParcel1 = Parcel.obtain();
    Parcel localParcel2 = Parcel.obtain();
    try
    {
      localParcel1.writeInterfaceToken("com.google.android.gms.maps.model.internal.ICircleDelegate");
      this.a.transact(12, localParcel1, localParcel2, 0);
      localParcel2.readException();
      int i = localParcel2.readInt();
      return i;
    }
    finally
    {
      localParcel2.recycle();
      localParcel1.recycle();
    }
  }
  
  public float h()
  {
    Parcel localParcel1 = Parcel.obtain();
    Parcel localParcel2 = Parcel.obtain();
    try
    {
      localParcel1.writeInterfaceToken("com.google.android.gms.maps.model.internal.ICircleDelegate");
      this.a.transact(14, localParcel1, localParcel2, 0);
      localParcel2.readException();
      float f = localParcel2.readFloat();
      return f;
    }
    finally
    {
      localParcel2.recycle();
      localParcel1.recycle();
    }
  }
  
  public boolean i()
  {
    boolean bool = false;
    Parcel localParcel1 = Parcel.obtain();
    Parcel localParcel2 = Parcel.obtain();
    try
    {
      localParcel1.writeInterfaceToken("com.google.android.gms.maps.model.internal.ICircleDelegate");
      this.a.transact(16, localParcel1, localParcel2, 0);
      localParcel2.readException();
      int i = localParcel2.readInt();
      if (i != 0) {
        bool = true;
      }
      return bool;
    }
    finally
    {
      localParcel2.recycle();
      localParcel1.recycle();
    }
  }
  
  public int j()
  {
    Parcel localParcel1 = Parcel.obtain();
    Parcel localParcel2 = Parcel.obtain();
    try
    {
      localParcel1.writeInterfaceToken("com.google.android.gms.maps.model.internal.ICircleDelegate");
      this.a.transact(18, localParcel1, localParcel2, 0);
      localParcel2.readException();
      int i = localParcel2.readInt();
      return i;
    }
    finally
    {
      localParcel2.recycle();
      localParcel1.recycle();
    }
  }
}


/* Location:           C:\Users\dreadiscool\Desktop\tools\classes-dex2jar.jar
 * Qualified Name:     mB
 * JD-Core Version:    0.7.0.1
 */