class sy
{
  private final sE a;
  private final sg b;
  private rZ c;
  private volatile sE d;
  
  /* Error */
  private void b()
  {
    // Byte code:
    //   0: aload_0
    //   1: getfield 16	sy:d	LsE;
    //   4: ifnull +4 -> 8
    //   7: return
    //   8: aload_0
    //   9: monitorenter
    //   10: aload_0
    //   11: getfield 16	sy:d	LsE;
    //   14: ifnull +13 -> 27
    //   17: aload_0
    //   18: monitorexit
    //   19: goto -12 -> 7
    //   22: astore_1
    //   23: aload_0
    //   24: monitorexit
    //   25: aload_1
    //   26: athrow
    //   27: aload_0
    //   28: getfield 18	sy:c	LrZ;
    //   31: ifnull +32 -> 63
    //   34: aload_0
    //   35: aload_0
    //   36: getfield 20	sy:a	LsE;
    //   39: invokeinterface 25 1 0
    //   44: aload_0
    //   45: getfield 18	sy:c	LrZ;
    //   48: aload_0
    //   49: getfield 27	sy:b	Lsg;
    //   52: invokeinterface 32 3 0
    //   57: checkcast 22	sE
    //   60: putfield 16	sy:d	LsE;
    //   63: aload_0
    //   64: monitorexit
    //   65: goto -58 -> 7
    //   68: astore_2
    //   69: goto -6 -> 63
    // Local variable table:
    //   start	length	slot	name	signature
    //   0	72	0	this	sy
    //   22	4	1	localObject	Object
    //   68	1	2	localIOException	java.io.IOException
    // Exception table:
    //   from	to	target	type
    //   10	25	22	finally
    //   27	63	22	finally
    //   63	65	22	finally
    //   27	63	68	java/io/IOException
  }
  
  public sE a()
  {
    b();
    return this.d;
  }
  
  public boolean equals(Object paramObject)
  {
    b();
    return this.d.equals(paramObject);
  }
  
  public int hashCode()
  {
    b();
    return this.d.hashCode();
  }
  
  public String toString()
  {
    b();
    return this.d.toString();
  }
}


/* Location:           C:\Users\dreadiscool\Desktop\tools\classes-dex2jar.jar
 * Qualified Name:     sy
 * JD-Core Version:    0.7.0.1
 */