class tx
  implements Runnable
{
  private tx(tv paramtv) {}
  
  /* Error */
  public void run()
  {
    // Byte code:
    //   0: invokestatic 29	java/lang/Thread:currentThread	()Ljava/lang/Thread;
    //   3: ldc 31
    //   5: invokevirtual 35	java/lang/Thread:setName	(Ljava/lang/String;)V
    //   8: invokestatic 39	java/lang/Thread:interrupted	()Z
    //   11: ifne +65 -> 76
    //   14: aload_0
    //   15: getfield 12	tx:a	Ltv;
    //   18: invokestatic 44	tv:a	(Ltv;)Ltt;
    //   21: getfield 50	tt:f	Ljava/util/concurrent/BlockingQueue;
    //   24: invokeinterface 56 1 0
    //   29: checkcast 58	java/nio/ByteBuffer
    //   32: astore_3
    //   33: aload_0
    //   34: getfield 12	tx:a	Ltv;
    //   37: invokestatic 62	tv:b	(Ltv;)Ljava/io/OutputStream;
    //   40: aload_3
    //   41: invokevirtual 66	java/nio/ByteBuffer:array	()[B
    //   44: iconst_0
    //   45: aload_3
    //   46: invokevirtual 70	java/nio/ByteBuffer:limit	()I
    //   49: invokevirtual 76	java/io/OutputStream:write	([BII)V
    //   52: aload_0
    //   53: getfield 12	tx:a	Ltv;
    //   56: invokestatic 62	tv:b	(Ltv;)Ljava/io/OutputStream;
    //   59: invokevirtual 79	java/io/OutputStream:flush	()V
    //   62: goto -54 -> 8
    //   65: astore_2
    //   66: aload_0
    //   67: getfield 12	tx:a	Ltv;
    //   70: invokestatic 44	tv:a	(Ltv;)Ltt;
    //   73: invokevirtual 81	tt:b	()V
    //   76: return
    //   77: astore_1
    //   78: goto -2 -> 76
    // Local variable table:
    //   start	length	slot	name	signature
    //   0	81	0	this	tx
    //   77	1	1	localInterruptedException	java.lang.InterruptedException
    //   65	1	2	localIOException	java.io.IOException
    //   32	14	3	localByteBuffer	java.nio.ByteBuffer
    // Exception table:
    //   from	to	target	type
    //   8	62	65	java/io/IOException
    //   8	62	77	java/lang/InterruptedException
  }
}


/* Location:           C:\Users\dreadiscool\Desktop\tools\classes-dex2jar.jar
 * Qualified Name:     tx
 * JD-Core Version:    0.7.0.1
 */