import java.io.IOException;
import java.io.UnsupportedEncodingException;

public class uc
{
  private static final byte[] b;
  private static final byte[] c;
  private static final byte[] d;
  private static final byte[] e;
  private static final byte[] f;
  private static final byte[] g;
  
  static
  {
    if (!uc.class.desiredAssertionStatus()) {}
    for (boolean bool = true;; bool = false)
    {
      a = bool;
      byte[] arrayOfByte1 = new byte[64];
      arrayOfByte1[0] = 65;
      arrayOfByte1[1] = 66;
      arrayOfByte1[2] = 67;
      arrayOfByte1[3] = 68;
      arrayOfByte1[4] = 69;
      arrayOfByte1[5] = 70;
      arrayOfByte1[6] = 71;
      arrayOfByte1[7] = 72;
      arrayOfByte1[8] = 73;
      arrayOfByte1[9] = 74;
      arrayOfByte1[10] = 75;
      arrayOfByte1[11] = 76;
      arrayOfByte1[12] = 77;
      arrayOfByte1[13] = 78;
      arrayOfByte1[14] = 79;
      arrayOfByte1[15] = 80;
      arrayOfByte1[16] = 81;
      arrayOfByte1[17] = 82;
      arrayOfByte1[18] = 83;
      arrayOfByte1[19] = 84;
      arrayOfByte1[20] = 85;
      arrayOfByte1[21] = 86;
      arrayOfByte1[22] = 87;
      arrayOfByte1[23] = 88;
      arrayOfByte1[24] = 89;
      arrayOfByte1[25] = 90;
      arrayOfByte1[26] = 97;
      arrayOfByte1[27] = 98;
      arrayOfByte1[28] = 99;
      arrayOfByte1[29] = 100;
      arrayOfByte1[30] = 101;
      arrayOfByte1[31] = 102;
      arrayOfByte1[32] = 103;
      arrayOfByte1[33] = 104;
      arrayOfByte1[34] = 105;
      arrayOfByte1[35] = 106;
      arrayOfByte1[36] = 107;
      arrayOfByte1[37] = 108;
      arrayOfByte1[38] = 109;
      arrayOfByte1[39] = 110;
      arrayOfByte1[40] = 111;
      arrayOfByte1[41] = 112;
      arrayOfByte1[42] = 113;
      arrayOfByte1[43] = 114;
      arrayOfByte1[44] = 115;
      arrayOfByte1[45] = 116;
      arrayOfByte1[46] = 117;
      arrayOfByte1[47] = 118;
      arrayOfByte1[48] = 119;
      arrayOfByte1[49] = 120;
      arrayOfByte1[50] = 121;
      arrayOfByte1[51] = 122;
      arrayOfByte1[52] = 48;
      arrayOfByte1[53] = 49;
      arrayOfByte1[54] = 50;
      arrayOfByte1[55] = 51;
      arrayOfByte1[56] = 52;
      arrayOfByte1[57] = 53;
      arrayOfByte1[58] = 54;
      arrayOfByte1[59] = 55;
      arrayOfByte1[60] = 56;
      arrayOfByte1[61] = 57;
      arrayOfByte1[62] = 43;
      arrayOfByte1[63] = 47;
      b = arrayOfByte1;
      byte[] arrayOfByte2 = new byte[256];
      arrayOfByte2[0] = -9;
      arrayOfByte2[1] = -9;
      arrayOfByte2[2] = -9;
      arrayOfByte2[3] = -9;
      arrayOfByte2[4] = -9;
      arrayOfByte2[5] = -9;
      arrayOfByte2[6] = -9;
      arrayOfByte2[7] = -9;
      arrayOfByte2[8] = -9;
      arrayOfByte2[9] = -5;
      arrayOfByte2[10] = -5;
      arrayOfByte2[11] = -9;
      arrayOfByte2[12] = -9;
      arrayOfByte2[13] = -5;
      arrayOfByte2[14] = -9;
      arrayOfByte2[15] = -9;
      arrayOfByte2[16] = -9;
      arrayOfByte2[17] = -9;
      arrayOfByte2[18] = -9;
      arrayOfByte2[19] = -9;
      arrayOfByte2[20] = -9;
      arrayOfByte2[21] = -9;
      arrayOfByte2[22] = -9;
      arrayOfByte2[23] = -9;
      arrayOfByte2[24] = -9;
      arrayOfByte2[25] = -9;
      arrayOfByte2[26] = -9;
      arrayOfByte2[27] = -9;
      arrayOfByte2[28] = -9;
      arrayOfByte2[29] = -9;
      arrayOfByte2[30] = -9;
      arrayOfByte2[31] = -9;
      arrayOfByte2[32] = -5;
      arrayOfByte2[33] = -9;
      arrayOfByte2[34] = -9;
      arrayOfByte2[35] = -9;
      arrayOfByte2[36] = -9;
      arrayOfByte2[37] = -9;
      arrayOfByte2[38] = -9;
      arrayOfByte2[39] = -9;
      arrayOfByte2[40] = -9;
      arrayOfByte2[41] = -9;
      arrayOfByte2[42] = -9;
      arrayOfByte2[43] = 62;
      arrayOfByte2[44] = -9;
      arrayOfByte2[45] = -9;
      arrayOfByte2[46] = -9;
      arrayOfByte2[47] = 63;
      arrayOfByte2[48] = 52;
      arrayOfByte2[49] = 53;
      arrayOfByte2[50] = 54;
      arrayOfByte2[51] = 55;
      arrayOfByte2[52] = 56;
      arrayOfByte2[53] = 57;
      arrayOfByte2[54] = 58;
      arrayOfByte2[55] = 59;
      arrayOfByte2[56] = 60;
      arrayOfByte2[57] = 61;
      arrayOfByte2[58] = -9;
      arrayOfByte2[59] = -9;
      arrayOfByte2[60] = -9;
      arrayOfByte2[61] = -1;
      arrayOfByte2[62] = -9;
      arrayOfByte2[63] = -9;
      arrayOfByte2[64] = -9;
      arrayOfByte2[65] = 0;
      arrayOfByte2[66] = 1;
      arrayOfByte2[67] = 2;
      arrayOfByte2[68] = 3;
      arrayOfByte2[69] = 4;
      arrayOfByte2[70] = 5;
      arrayOfByte2[71] = 6;
      arrayOfByte2[72] = 7;
      arrayOfByte2[73] = 8;
      arrayOfByte2[74] = 9;
      arrayOfByte2[75] = 10;
      arrayOfByte2[76] = 11;
      arrayOfByte2[77] = 12;
      arrayOfByte2[78] = 13;
      arrayOfByte2[79] = 14;
      arrayOfByte2[80] = 15;
      arrayOfByte2[81] = 16;
      arrayOfByte2[82] = 17;
      arrayOfByte2[83] = 18;
      arrayOfByte2[84] = 19;
      arrayOfByte2[85] = 20;
      arrayOfByte2[86] = 21;
      arrayOfByte2[87] = 22;
      arrayOfByte2[88] = 23;
      arrayOfByte2[89] = 24;
      arrayOfByte2[90] = 25;
      arrayOfByte2[91] = -9;
      arrayOfByte2[92] = -9;
      arrayOfByte2[93] = -9;
      arrayOfByte2[94] = -9;
      arrayOfByte2[95] = -9;
      arrayOfByte2[96] = -9;
      arrayOfByte2[97] = 26;
      arrayOfByte2[98] = 27;
      arrayOfByte2[99] = 28;
      arrayOfByte2[100] = 29;
      arrayOfByte2[101] = 30;
      arrayOfByte2[102] = 31;
      arrayOfByte2[103] = 32;
      arrayOfByte2[104] = 33;
      arrayOfByte2[105] = 34;
      arrayOfByte2[106] = 35;
      arrayOfByte2[107] = 36;
      arrayOfByte2[108] = 37;
      arrayOfByte2[109] = 38;
      arrayOfByte2[110] = 39;
      arrayOfByte2[111] = 40;
      arrayOfByte2[112] = 41;
      arrayOfByte2[113] = 42;
      arrayOfByte2[114] = 43;
      arrayOfByte2[115] = 44;
      arrayOfByte2[116] = 45;
      arrayOfByte2[117] = 46;
      arrayOfByte2[118] = 47;
      arrayOfByte2[119] = 48;
      arrayOfByte2[120] = 49;
      arrayOfByte2[121] = 50;
      arrayOfByte2[122] = 51;
      arrayOfByte2[123] = -9;
      arrayOfByte2[124] = -9;
      arrayOfByte2[125] = -9;
      arrayOfByte2[126] = -9;
      arrayOfByte2[127] = -9;
      arrayOfByte2[''] = -9;
      arrayOfByte2[''] = -9;
      arrayOfByte2[''] = -9;
      arrayOfByte2[''] = -9;
      arrayOfByte2[''] = -9;
      arrayOfByte2[''] = -9;
      arrayOfByte2[''] = -9;
      arrayOfByte2[''] = -9;
      arrayOfByte2[''] = -9;
      arrayOfByte2[''] = -9;
      arrayOfByte2[''] = -9;
      arrayOfByte2[''] = -9;
      arrayOfByte2[''] = -9;
      arrayOfByte2[''] = -9;
      arrayOfByte2[''] = -9;
      arrayOfByte2[''] = -9;
      arrayOfByte2[''] = -9;
      arrayOfByte2[''] = -9;
      arrayOfByte2[''] = -9;
      arrayOfByte2[''] = -9;
      arrayOfByte2[''] = -9;
      arrayOfByte2[''] = -9;
      arrayOfByte2[''] = -9;
      arrayOfByte2[''] = -9;
      arrayOfByte2[''] = -9;
      arrayOfByte2[''] = -9;
      arrayOfByte2[''] = -9;
      arrayOfByte2[''] = -9;
      arrayOfByte2[''] = -9;
      arrayOfByte2[''] = -9;
      arrayOfByte2[''] = -9;
      arrayOfByte2[''] = -9;
      arrayOfByte2[' '] = -9;
      arrayOfByte2['¡'] = -9;
      arrayOfByte2['¢'] = -9;
      arrayOfByte2['£'] = -9;
      arrayOfByte2['¤'] = -9;
      arrayOfByte2['¥'] = -9;
      arrayOfByte2['¦'] = -9;
      arrayOfByte2['§'] = -9;
      arrayOfByte2['¨'] = -9;
      arrayOfByte2['©'] = -9;
      arrayOfByte2['ª'] = -9;
      arrayOfByte2['«'] = -9;
      arrayOfByte2['¬'] = -9;
      arrayOfByte2['­'] = -9;
      arrayOfByte2['®'] = -9;
      arrayOfByte2['¯'] = -9;
      arrayOfByte2['°'] = -9;
      arrayOfByte2['±'] = -9;
      arrayOfByte2['²'] = -9;
      arrayOfByte2['³'] = -9;
      arrayOfByte2['´'] = -9;
      arrayOfByte2['µ'] = -9;
      arrayOfByte2['¶'] = -9;
      arrayOfByte2['·'] = -9;
      arrayOfByte2['¸'] = -9;
      arrayOfByte2['¹'] = -9;
      arrayOfByte2['º'] = -9;
      arrayOfByte2['»'] = -9;
      arrayOfByte2['¼'] = -9;
      arrayOfByte2['½'] = -9;
      arrayOfByte2['¾'] = -9;
      arrayOfByte2['¿'] = -9;
      arrayOfByte2['À'] = -9;
      arrayOfByte2['Á'] = -9;
      arrayOfByte2['Â'] = -9;
      arrayOfByte2['Ã'] = -9;
      arrayOfByte2['Ä'] = -9;
      arrayOfByte2['Å'] = -9;
      arrayOfByte2['Æ'] = -9;
      arrayOfByte2['Ç'] = -9;
      arrayOfByte2['È'] = -9;
      arrayOfByte2['É'] = -9;
      arrayOfByte2['Ê'] = -9;
      arrayOfByte2['Ë'] = -9;
      arrayOfByte2['Ì'] = -9;
      arrayOfByte2['Í'] = -9;
      arrayOfByte2['Î'] = -9;
      arrayOfByte2['Ï'] = -9;
      arrayOfByte2['Ð'] = -9;
      arrayOfByte2['Ñ'] = -9;
      arrayOfByte2['Ò'] = -9;
      arrayOfByte2['Ó'] = -9;
      arrayOfByte2['Ô'] = -9;
      arrayOfByte2['Õ'] = -9;
      arrayOfByte2['Ö'] = -9;
      arrayOfByte2['×'] = -9;
      arrayOfByte2['Ø'] = -9;
      arrayOfByte2['Ù'] = -9;
      arrayOfByte2['Ú'] = -9;
      arrayOfByte2['Û'] = -9;
      arrayOfByte2['Ü'] = -9;
      arrayOfByte2['Ý'] = -9;
      arrayOfByte2['Þ'] = -9;
      arrayOfByte2['ß'] = -9;
      arrayOfByte2['à'] = -9;
      arrayOfByte2['á'] = -9;
      arrayOfByte2['â'] = -9;
      arrayOfByte2['ã'] = -9;
      arrayOfByte2['ä'] = -9;
      arrayOfByte2['å'] = -9;
      arrayOfByte2['æ'] = -9;
      arrayOfByte2['ç'] = -9;
      arrayOfByte2['è'] = -9;
      arrayOfByte2['é'] = -9;
      arrayOfByte2['ê'] = -9;
      arrayOfByte2['ë'] = -9;
      arrayOfByte2['ì'] = -9;
      arrayOfByte2['í'] = -9;
      arrayOfByte2['î'] = -9;
      arrayOfByte2['ï'] = -9;
      arrayOfByte2['ð'] = -9;
      arrayOfByte2['ñ'] = -9;
      arrayOfByte2['ò'] = -9;
      arrayOfByte2['ó'] = -9;
      arrayOfByte2['ô'] = -9;
      arrayOfByte2['õ'] = -9;
      arrayOfByte2['ö'] = -9;
      arrayOfByte2['÷'] = -9;
      arrayOfByte2['ø'] = -9;
      arrayOfByte2['ù'] = -9;
      arrayOfByte2['ú'] = -9;
      arrayOfByte2['û'] = -9;
      arrayOfByte2['ü'] = -9;
      arrayOfByte2['ý'] = -9;
      arrayOfByte2['þ'] = -9;
      arrayOfByte2['ÿ'] = -9;
      c = arrayOfByte2;
      byte[] arrayOfByte3 = new byte[64];
      arrayOfByte3[0] = 65;
      arrayOfByte3[1] = 66;
      arrayOfByte3[2] = 67;
      arrayOfByte3[3] = 68;
      arrayOfByte3[4] = 69;
      arrayOfByte3[5] = 70;
      arrayOfByte3[6] = 71;
      arrayOfByte3[7] = 72;
      arrayOfByte3[8] = 73;
      arrayOfByte3[9] = 74;
      arrayOfByte3[10] = 75;
      arrayOfByte3[11] = 76;
      arrayOfByte3[12] = 77;
      arrayOfByte3[13] = 78;
      arrayOfByte3[14] = 79;
      arrayOfByte3[15] = 80;
      arrayOfByte3[16] = 81;
      arrayOfByte3[17] = 82;
      arrayOfByte3[18] = 83;
      arrayOfByte3[19] = 84;
      arrayOfByte3[20] = 85;
      arrayOfByte3[21] = 86;
      arrayOfByte3[22] = 87;
      arrayOfByte3[23] = 88;
      arrayOfByte3[24] = 89;
      arrayOfByte3[25] = 90;
      arrayOfByte3[26] = 97;
      arrayOfByte3[27] = 98;
      arrayOfByte3[28] = 99;
      arrayOfByte3[29] = 100;
      arrayOfByte3[30] = 101;
      arrayOfByte3[31] = 102;
      arrayOfByte3[32] = 103;
      arrayOfByte3[33] = 104;
      arrayOfByte3[34] = 105;
      arrayOfByte3[35] = 106;
      arrayOfByte3[36] = 107;
      arrayOfByte3[37] = 108;
      arrayOfByte3[38] = 109;
      arrayOfByte3[39] = 110;
      arrayOfByte3[40] = 111;
      arrayOfByte3[41] = 112;
      arrayOfByte3[42] = 113;
      arrayOfByte3[43] = 114;
      arrayOfByte3[44] = 115;
      arrayOfByte3[45] = 116;
      arrayOfByte3[46] = 117;
      arrayOfByte3[47] = 118;
      arrayOfByte3[48] = 119;
      arrayOfByte3[49] = 120;
      arrayOfByte3[50] = 121;
      arrayOfByte3[51] = 122;
      arrayOfByte3[52] = 48;
      arrayOfByte3[53] = 49;
      arrayOfByte3[54] = 50;
      arrayOfByte3[55] = 51;
      arrayOfByte3[56] = 52;
      arrayOfByte3[57] = 53;
      arrayOfByte3[58] = 54;
      arrayOfByte3[59] = 55;
      arrayOfByte3[60] = 56;
      arrayOfByte3[61] = 57;
      arrayOfByte3[62] = 45;
      arrayOfByte3[63] = 95;
      d = arrayOfByte3;
      byte[] arrayOfByte4 = new byte[256];
      arrayOfByte4[0] = -9;
      arrayOfByte4[1] = -9;
      arrayOfByte4[2] = -9;
      arrayOfByte4[3] = -9;
      arrayOfByte4[4] = -9;
      arrayOfByte4[5] = -9;
      arrayOfByte4[6] = -9;
      arrayOfByte4[7] = -9;
      arrayOfByte4[8] = -9;
      arrayOfByte4[9] = -5;
      arrayOfByte4[10] = -5;
      arrayOfByte4[11] = -9;
      arrayOfByte4[12] = -9;
      arrayOfByte4[13] = -5;
      arrayOfByte4[14] = -9;
      arrayOfByte4[15] = -9;
      arrayOfByte4[16] = -9;
      arrayOfByte4[17] = -9;
      arrayOfByte4[18] = -9;
      arrayOfByte4[19] = -9;
      arrayOfByte4[20] = -9;
      arrayOfByte4[21] = -9;
      arrayOfByte4[22] = -9;
      arrayOfByte4[23] = -9;
      arrayOfByte4[24] = -9;
      arrayOfByte4[25] = -9;
      arrayOfByte4[26] = -9;
      arrayOfByte4[27] = -9;
      arrayOfByte4[28] = -9;
      arrayOfByte4[29] = -9;
      arrayOfByte4[30] = -9;
      arrayOfByte4[31] = -9;
      arrayOfByte4[32] = -5;
      arrayOfByte4[33] = -9;
      arrayOfByte4[34] = -9;
      arrayOfByte4[35] = -9;
      arrayOfByte4[36] = -9;
      arrayOfByte4[37] = -9;
      arrayOfByte4[38] = -9;
      arrayOfByte4[39] = -9;
      arrayOfByte4[40] = -9;
      arrayOfByte4[41] = -9;
      arrayOfByte4[42] = -9;
      arrayOfByte4[43] = -9;
      arrayOfByte4[44] = -9;
      arrayOfByte4[45] = 62;
      arrayOfByte4[46] = -9;
      arrayOfByte4[47] = -9;
      arrayOfByte4[48] = 52;
      arrayOfByte4[49] = 53;
      arrayOfByte4[50] = 54;
      arrayOfByte4[51] = 55;
      arrayOfByte4[52] = 56;
      arrayOfByte4[53] = 57;
      arrayOfByte4[54] = 58;
      arrayOfByte4[55] = 59;
      arrayOfByte4[56] = 60;
      arrayOfByte4[57] = 61;
      arrayOfByte4[58] = -9;
      arrayOfByte4[59] = -9;
      arrayOfByte4[60] = -9;
      arrayOfByte4[61] = -1;
      arrayOfByte4[62] = -9;
      arrayOfByte4[63] = -9;
      arrayOfByte4[64] = -9;
      arrayOfByte4[65] = 0;
      arrayOfByte4[66] = 1;
      arrayOfByte4[67] = 2;
      arrayOfByte4[68] = 3;
      arrayOfByte4[69] = 4;
      arrayOfByte4[70] = 5;
      arrayOfByte4[71] = 6;
      arrayOfByte4[72] = 7;
      arrayOfByte4[73] = 8;
      arrayOfByte4[74] = 9;
      arrayOfByte4[75] = 10;
      arrayOfByte4[76] = 11;
      arrayOfByte4[77] = 12;
      arrayOfByte4[78] = 13;
      arrayOfByte4[79] = 14;
      arrayOfByte4[80] = 15;
      arrayOfByte4[81] = 16;
      arrayOfByte4[82] = 17;
      arrayOfByte4[83] = 18;
      arrayOfByte4[84] = 19;
      arrayOfByte4[85] = 20;
      arrayOfByte4[86] = 21;
      arrayOfByte4[87] = 22;
      arrayOfByte4[88] = 23;
      arrayOfByte4[89] = 24;
      arrayOfByte4[90] = 25;
      arrayOfByte4[91] = -9;
      arrayOfByte4[92] = -9;
      arrayOfByte4[93] = -9;
      arrayOfByte4[94] = -9;
      arrayOfByte4[95] = 63;
      arrayOfByte4[96] = -9;
      arrayOfByte4[97] = 26;
      arrayOfByte4[98] = 27;
      arrayOfByte4[99] = 28;
      arrayOfByte4[100] = 29;
      arrayOfByte4[101] = 30;
      arrayOfByte4[102] = 31;
      arrayOfByte4[103] = 32;
      arrayOfByte4[104] = 33;
      arrayOfByte4[105] = 34;
      arrayOfByte4[106] = 35;
      arrayOfByte4[107] = 36;
      arrayOfByte4[108] = 37;
      arrayOfByte4[109] = 38;
      arrayOfByte4[110] = 39;
      arrayOfByte4[111] = 40;
      arrayOfByte4[112] = 41;
      arrayOfByte4[113] = 42;
      arrayOfByte4[114] = 43;
      arrayOfByte4[115] = 44;
      arrayOfByte4[116] = 45;
      arrayOfByte4[117] = 46;
      arrayOfByte4[118] = 47;
      arrayOfByte4[119] = 48;
      arrayOfByte4[120] = 49;
      arrayOfByte4[121] = 50;
      arrayOfByte4[122] = 51;
      arrayOfByte4[123] = -9;
      arrayOfByte4[124] = -9;
      arrayOfByte4[125] = -9;
      arrayOfByte4[126] = -9;
      arrayOfByte4[127] = -9;
      arrayOfByte4[''] = -9;
      arrayOfByte4[''] = -9;
      arrayOfByte4[''] = -9;
      arrayOfByte4[''] = -9;
      arrayOfByte4[''] = -9;
      arrayOfByte4[''] = -9;
      arrayOfByte4[''] = -9;
      arrayOfByte4[''] = -9;
      arrayOfByte4[''] = -9;
      arrayOfByte4[''] = -9;
      arrayOfByte4[''] = -9;
      arrayOfByte4[''] = -9;
      arrayOfByte4[''] = -9;
      arrayOfByte4[''] = -9;
      arrayOfByte4[''] = -9;
      arrayOfByte4[''] = -9;
      arrayOfByte4[''] = -9;
      arrayOfByte4[''] = -9;
      arrayOfByte4[''] = -9;
      arrayOfByte4[''] = -9;
      arrayOfByte4[''] = -9;
      arrayOfByte4[''] = -9;
      arrayOfByte4[''] = -9;
      arrayOfByte4[''] = -9;
      arrayOfByte4[''] = -9;
      arrayOfByte4[''] = -9;
      arrayOfByte4[''] = -9;
      arrayOfByte4[''] = -9;
      arrayOfByte4[''] = -9;
      arrayOfByte4[''] = -9;
      arrayOfByte4[''] = -9;
      arrayOfByte4[''] = -9;
      arrayOfByte4[' '] = -9;
      arrayOfByte4['¡'] = -9;
      arrayOfByte4['¢'] = -9;
      arrayOfByte4['£'] = -9;
      arrayOfByte4['¤'] = -9;
      arrayOfByte4['¥'] = -9;
      arrayOfByte4['¦'] = -9;
      arrayOfByte4['§'] = -9;
      arrayOfByte4['¨'] = -9;
      arrayOfByte4['©'] = -9;
      arrayOfByte4['ª'] = -9;
      arrayOfByte4['«'] = -9;
      arrayOfByte4['¬'] = -9;
      arrayOfByte4['­'] = -9;
      arrayOfByte4['®'] = -9;
      arrayOfByte4['¯'] = -9;
      arrayOfByte4['°'] = -9;
      arrayOfByte4['±'] = -9;
      arrayOfByte4['²'] = -9;
      arrayOfByte4['³'] = -9;
      arrayOfByte4['´'] = -9;
      arrayOfByte4['µ'] = -9;
      arrayOfByte4['¶'] = -9;
      arrayOfByte4['·'] = -9;
      arrayOfByte4['¸'] = -9;
      arrayOfByte4['¹'] = -9;
      arrayOfByte4['º'] = -9;
      arrayOfByte4['»'] = -9;
      arrayOfByte4['¼'] = -9;
      arrayOfByte4['½'] = -9;
      arrayOfByte4['¾'] = -9;
      arrayOfByte4['¿'] = -9;
      arrayOfByte4['À'] = -9;
      arrayOfByte4['Á'] = -9;
      arrayOfByte4['Â'] = -9;
      arrayOfByte4['Ã'] = -9;
      arrayOfByte4['Ä'] = -9;
      arrayOfByte4['Å'] = -9;
      arrayOfByte4['Æ'] = -9;
      arrayOfByte4['Ç'] = -9;
      arrayOfByte4['È'] = -9;
      arrayOfByte4['É'] = -9;
      arrayOfByte4['Ê'] = -9;
      arrayOfByte4['Ë'] = -9;
      arrayOfByte4['Ì'] = -9;
      arrayOfByte4['Í'] = -9;
      arrayOfByte4['Î'] = -9;
      arrayOfByte4['Ï'] = -9;
      arrayOfByte4['Ð'] = -9;
      arrayOfByte4['Ñ'] = -9;
      arrayOfByte4['Ò'] = -9;
      arrayOfByte4['Ó'] = -9;
      arrayOfByte4['Ô'] = -9;
      arrayOfByte4['Õ'] = -9;
      arrayOfByte4['Ö'] = -9;
      arrayOfByte4['×'] = -9;
      arrayOfByte4['Ø'] = -9;
      arrayOfByte4['Ù'] = -9;
      arrayOfByte4['Ú'] = -9;
      arrayOfByte4['Û'] = -9;
      arrayOfByte4['Ü'] = -9;
      arrayOfByte4['Ý'] = -9;
      arrayOfByte4['Þ'] = -9;
      arrayOfByte4['ß'] = -9;
      arrayOfByte4['à'] = -9;
      arrayOfByte4['á'] = -9;
      arrayOfByte4['â'] = -9;
      arrayOfByte4['ã'] = -9;
      arrayOfByte4['ä'] = -9;
      arrayOfByte4['å'] = -9;
      arrayOfByte4['æ'] = -9;
      arrayOfByte4['ç'] = -9;
      arrayOfByte4['è'] = -9;
      arrayOfByte4['é'] = -9;
      arrayOfByte4['ê'] = -9;
      arrayOfByte4['ë'] = -9;
      arrayOfByte4['ì'] = -9;
      arrayOfByte4['í'] = -9;
      arrayOfByte4['î'] = -9;
      arrayOfByte4['ï'] = -9;
      arrayOfByte4['ð'] = -9;
      arrayOfByte4['ñ'] = -9;
      arrayOfByte4['ò'] = -9;
      arrayOfByte4['ó'] = -9;
      arrayOfByte4['ô'] = -9;
      arrayOfByte4['õ'] = -9;
      arrayOfByte4['ö'] = -9;
      arrayOfByte4['÷'] = -9;
      arrayOfByte4['ø'] = -9;
      arrayOfByte4['ù'] = -9;
      arrayOfByte4['ú'] = -9;
      arrayOfByte4['û'] = -9;
      arrayOfByte4['ü'] = -9;
      arrayOfByte4['ý'] = -9;
      arrayOfByte4['þ'] = -9;
      arrayOfByte4['ÿ'] = -9;
      e = arrayOfByte4;
      byte[] arrayOfByte5 = new byte[64];
      arrayOfByte5[0] = 45;
      arrayOfByte5[1] = 48;
      arrayOfByte5[2] = 49;
      arrayOfByte5[3] = 50;
      arrayOfByte5[4] = 51;
      arrayOfByte5[5] = 52;
      arrayOfByte5[6] = 53;
      arrayOfByte5[7] = 54;
      arrayOfByte5[8] = 55;
      arrayOfByte5[9] = 56;
      arrayOfByte5[10] = 57;
      arrayOfByte5[11] = 65;
      arrayOfByte5[12] = 66;
      arrayOfByte5[13] = 67;
      arrayOfByte5[14] = 68;
      arrayOfByte5[15] = 69;
      arrayOfByte5[16] = 70;
      arrayOfByte5[17] = 71;
      arrayOfByte5[18] = 72;
      arrayOfByte5[19] = 73;
      arrayOfByte5[20] = 74;
      arrayOfByte5[21] = 75;
      arrayOfByte5[22] = 76;
      arrayOfByte5[23] = 77;
      arrayOfByte5[24] = 78;
      arrayOfByte5[25] = 79;
      arrayOfByte5[26] = 80;
      arrayOfByte5[27] = 81;
      arrayOfByte5[28] = 82;
      arrayOfByte5[29] = 83;
      arrayOfByte5[30] = 84;
      arrayOfByte5[31] = 85;
      arrayOfByte5[32] = 86;
      arrayOfByte5[33] = 87;
      arrayOfByte5[34] = 88;
      arrayOfByte5[35] = 89;
      arrayOfByte5[36] = 90;
      arrayOfByte5[37] = 95;
      arrayOfByte5[38] = 97;
      arrayOfByte5[39] = 98;
      arrayOfByte5[40] = 99;
      arrayOfByte5[41] = 100;
      arrayOfByte5[42] = 101;
      arrayOfByte5[43] = 102;
      arrayOfByte5[44] = 103;
      arrayOfByte5[45] = 104;
      arrayOfByte5[46] = 105;
      arrayOfByte5[47] = 106;
      arrayOfByte5[48] = 107;
      arrayOfByte5[49] = 108;
      arrayOfByte5[50] = 109;
      arrayOfByte5[51] = 110;
      arrayOfByte5[52] = 111;
      arrayOfByte5[53] = 112;
      arrayOfByte5[54] = 113;
      arrayOfByte5[55] = 114;
      arrayOfByte5[56] = 115;
      arrayOfByte5[57] = 116;
      arrayOfByte5[58] = 117;
      arrayOfByte5[59] = 118;
      arrayOfByte5[60] = 119;
      arrayOfByte5[61] = 120;
      arrayOfByte5[62] = 121;
      arrayOfByte5[63] = 122;
      f = arrayOfByte5;
      byte[] arrayOfByte6 = new byte[257];
      arrayOfByte6[0] = -9;
      arrayOfByte6[1] = -9;
      arrayOfByte6[2] = -9;
      arrayOfByte6[3] = -9;
      arrayOfByte6[4] = -9;
      arrayOfByte6[5] = -9;
      arrayOfByte6[6] = -9;
      arrayOfByte6[7] = -9;
      arrayOfByte6[8] = -9;
      arrayOfByte6[9] = -5;
      arrayOfByte6[10] = -5;
      arrayOfByte6[11] = -9;
      arrayOfByte6[12] = -9;
      arrayOfByte6[13] = -5;
      arrayOfByte6[14] = -9;
      arrayOfByte6[15] = -9;
      arrayOfByte6[16] = -9;
      arrayOfByte6[17] = -9;
      arrayOfByte6[18] = -9;
      arrayOfByte6[19] = -9;
      arrayOfByte6[20] = -9;
      arrayOfByte6[21] = -9;
      arrayOfByte6[22] = -9;
      arrayOfByte6[23] = -9;
      arrayOfByte6[24] = -9;
      arrayOfByte6[25] = -9;
      arrayOfByte6[26] = -9;
      arrayOfByte6[27] = -9;
      arrayOfByte6[28] = -9;
      arrayOfByte6[29] = -9;
      arrayOfByte6[30] = -9;
      arrayOfByte6[31] = -9;
      arrayOfByte6[32] = -5;
      arrayOfByte6[33] = -9;
      arrayOfByte6[34] = -9;
      arrayOfByte6[35] = -9;
      arrayOfByte6[36] = -9;
      arrayOfByte6[37] = -9;
      arrayOfByte6[38] = -9;
      arrayOfByte6[39] = -9;
      arrayOfByte6[40] = -9;
      arrayOfByte6[41] = -9;
      arrayOfByte6[42] = -9;
      arrayOfByte6[43] = -9;
      arrayOfByte6[44] = -9;
      arrayOfByte6[45] = 0;
      arrayOfByte6[46] = -9;
      arrayOfByte6[47] = -9;
      arrayOfByte6[48] = 1;
      arrayOfByte6[49] = 2;
      arrayOfByte6[50] = 3;
      arrayOfByte6[51] = 4;
      arrayOfByte6[52] = 5;
      arrayOfByte6[53] = 6;
      arrayOfByte6[54] = 7;
      arrayOfByte6[55] = 8;
      arrayOfByte6[56] = 9;
      arrayOfByte6[57] = 10;
      arrayOfByte6[58] = -9;
      arrayOfByte6[59] = -9;
      arrayOfByte6[60] = -9;
      arrayOfByte6[61] = -1;
      arrayOfByte6[62] = -9;
      arrayOfByte6[63] = -9;
      arrayOfByte6[64] = -9;
      arrayOfByte6[65] = 11;
      arrayOfByte6[66] = 12;
      arrayOfByte6[67] = 13;
      arrayOfByte6[68] = 14;
      arrayOfByte6[69] = 15;
      arrayOfByte6[70] = 16;
      arrayOfByte6[71] = 17;
      arrayOfByte6[72] = 18;
      arrayOfByte6[73] = 19;
      arrayOfByte6[74] = 20;
      arrayOfByte6[75] = 21;
      arrayOfByte6[76] = 22;
      arrayOfByte6[77] = 23;
      arrayOfByte6[78] = 24;
      arrayOfByte6[79] = 25;
      arrayOfByte6[80] = 26;
      arrayOfByte6[81] = 27;
      arrayOfByte6[82] = 28;
      arrayOfByte6[83] = 29;
      arrayOfByte6[84] = 30;
      arrayOfByte6[85] = 31;
      arrayOfByte6[86] = 32;
      arrayOfByte6[87] = 33;
      arrayOfByte6[88] = 34;
      arrayOfByte6[89] = 35;
      arrayOfByte6[90] = 36;
      arrayOfByte6[91] = -9;
      arrayOfByte6[92] = -9;
      arrayOfByte6[93] = -9;
      arrayOfByte6[94] = -9;
      arrayOfByte6[95] = 37;
      arrayOfByte6[96] = -9;
      arrayOfByte6[97] = 38;
      arrayOfByte6[98] = 39;
      arrayOfByte6[99] = 40;
      arrayOfByte6[100] = 41;
      arrayOfByte6[101] = 42;
      arrayOfByte6[102] = 43;
      arrayOfByte6[103] = 44;
      arrayOfByte6[104] = 45;
      arrayOfByte6[105] = 46;
      arrayOfByte6[106] = 47;
      arrayOfByte6[107] = 48;
      arrayOfByte6[108] = 49;
      arrayOfByte6[109] = 50;
      arrayOfByte6[110] = 51;
      arrayOfByte6[111] = 52;
      arrayOfByte6[112] = 53;
      arrayOfByte6[113] = 54;
      arrayOfByte6[114] = 55;
      arrayOfByte6[115] = 56;
      arrayOfByte6[116] = 57;
      arrayOfByte6[117] = 58;
      arrayOfByte6[118] = 59;
      arrayOfByte6[119] = 60;
      arrayOfByte6[120] = 61;
      arrayOfByte6[121] = 62;
      arrayOfByte6[122] = 63;
      arrayOfByte6[123] = -9;
      arrayOfByte6[124] = -9;
      arrayOfByte6[125] = -9;
      arrayOfByte6[126] = -9;
      arrayOfByte6[127] = -9;
      arrayOfByte6[''] = -9;
      arrayOfByte6[''] = -9;
      arrayOfByte6[''] = -9;
      arrayOfByte6[''] = -9;
      arrayOfByte6[''] = -9;
      arrayOfByte6[''] = -9;
      arrayOfByte6[''] = -9;
      arrayOfByte6[''] = -9;
      arrayOfByte6[''] = -9;
      arrayOfByte6[''] = -9;
      arrayOfByte6[''] = -9;
      arrayOfByte6[''] = -9;
      arrayOfByte6[''] = -9;
      arrayOfByte6[''] = -9;
      arrayOfByte6[''] = -9;
      arrayOfByte6[''] = -9;
      arrayOfByte6[''] = -9;
      arrayOfByte6[''] = -9;
      arrayOfByte6[''] = -9;
      arrayOfByte6[''] = -9;
      arrayOfByte6[''] = -9;
      arrayOfByte6[''] = -9;
      arrayOfByte6[''] = -9;
      arrayOfByte6[''] = -9;
      arrayOfByte6[''] = -9;
      arrayOfByte6[''] = -9;
      arrayOfByte6[''] = -9;
      arrayOfByte6[''] = -9;
      arrayOfByte6[''] = -9;
      arrayOfByte6[''] = -9;
      arrayOfByte6[''] = -9;
      arrayOfByte6[''] = -9;
      arrayOfByte6[' '] = -9;
      arrayOfByte6['¡'] = -9;
      arrayOfByte6['¢'] = -9;
      arrayOfByte6['£'] = -9;
      arrayOfByte6['¤'] = -9;
      arrayOfByte6['¥'] = -9;
      arrayOfByte6['¦'] = -9;
      arrayOfByte6['§'] = -9;
      arrayOfByte6['¨'] = -9;
      arrayOfByte6['©'] = -9;
      arrayOfByte6['ª'] = -9;
      arrayOfByte6['«'] = -9;
      arrayOfByte6['¬'] = -9;
      arrayOfByte6['­'] = -9;
      arrayOfByte6['®'] = -9;
      arrayOfByte6['¯'] = -9;
      arrayOfByte6['°'] = -9;
      arrayOfByte6['±'] = -9;
      arrayOfByte6['²'] = -9;
      arrayOfByte6['³'] = -9;
      arrayOfByte6['´'] = -9;
      arrayOfByte6['µ'] = -9;
      arrayOfByte6['¶'] = -9;
      arrayOfByte6['·'] = -9;
      arrayOfByte6['¸'] = -9;
      arrayOfByte6['¹'] = -9;
      arrayOfByte6['º'] = -9;
      arrayOfByte6['»'] = -9;
      arrayOfByte6['¼'] = -9;
      arrayOfByte6['½'] = -9;
      arrayOfByte6['¾'] = -9;
      arrayOfByte6['¿'] = -9;
      arrayOfByte6['À'] = -9;
      arrayOfByte6['Á'] = -9;
      arrayOfByte6['Â'] = -9;
      arrayOfByte6['Ã'] = -9;
      arrayOfByte6['Ä'] = -9;
      arrayOfByte6['Å'] = -9;
      arrayOfByte6['Æ'] = -9;
      arrayOfByte6['Ç'] = -9;
      arrayOfByte6['È'] = -9;
      arrayOfByte6['É'] = -9;
      arrayOfByte6['Ê'] = -9;
      arrayOfByte6['Ë'] = -9;
      arrayOfByte6['Ì'] = -9;
      arrayOfByte6['Í'] = -9;
      arrayOfByte6['Î'] = -9;
      arrayOfByte6['Ï'] = -9;
      arrayOfByte6['Ð'] = -9;
      arrayOfByte6['Ñ'] = -9;
      arrayOfByte6['Ò'] = -9;
      arrayOfByte6['Ó'] = -9;
      arrayOfByte6['Ô'] = -9;
      arrayOfByte6['Õ'] = -9;
      arrayOfByte6['Ö'] = -9;
      arrayOfByte6['×'] = -9;
      arrayOfByte6['Ø'] = -9;
      arrayOfByte6['Ù'] = -9;
      arrayOfByte6['Ú'] = -9;
      arrayOfByte6['Û'] = -9;
      arrayOfByte6['Ü'] = -9;
      arrayOfByte6['Ý'] = -9;
      arrayOfByte6['Þ'] = -9;
      arrayOfByte6['ß'] = -9;
      arrayOfByte6['à'] = -9;
      arrayOfByte6['á'] = -9;
      arrayOfByte6['â'] = -9;
      arrayOfByte6['ã'] = -9;
      arrayOfByte6['ä'] = -9;
      arrayOfByte6['å'] = -9;
      arrayOfByte6['æ'] = -9;
      arrayOfByte6['ç'] = -9;
      arrayOfByte6['è'] = -9;
      arrayOfByte6['é'] = -9;
      arrayOfByte6['ê'] = -9;
      arrayOfByte6['ë'] = -9;
      arrayOfByte6['ì'] = -9;
      arrayOfByte6['í'] = -9;
      arrayOfByte6['î'] = -9;
      arrayOfByte6['ï'] = -9;
      arrayOfByte6['ð'] = -9;
      arrayOfByte6['ñ'] = -9;
      arrayOfByte6['ò'] = -9;
      arrayOfByte6['ó'] = -9;
      arrayOfByte6['ô'] = -9;
      arrayOfByte6['õ'] = -9;
      arrayOfByte6['ö'] = -9;
      arrayOfByte6['÷'] = -9;
      arrayOfByte6['ø'] = -9;
      arrayOfByte6['ù'] = -9;
      arrayOfByte6['ú'] = -9;
      arrayOfByte6['û'] = -9;
      arrayOfByte6['ü'] = -9;
      arrayOfByte6['ý'] = -9;
      arrayOfByte6['þ'] = -9;
      arrayOfByte6['ÿ'] = -9;
      arrayOfByte6[256] = -9;
      g = arrayOfByte6;
      return;
    }
  }
  
  public static String a(byte[] paramArrayOfByte)
  {
    Object localObject = null;
    try
    {
      String str = a(paramArrayOfByte, 0, paramArrayOfByte.length, 0);
      localObject = str;
    }
    catch (IOException localIOException)
    {
      while (a) {}
      throw new AssertionError(localIOException.getMessage());
    }
    if ((!a) && (localObject == null)) {
      throw new AssertionError();
    }
    return localObject;
  }
  
  public static String a(byte[] paramArrayOfByte, int paramInt1, int paramInt2, int paramInt3)
  {
    byte[] arrayOfByte = b(paramArrayOfByte, paramInt1, paramInt2, paramInt3);
    try
    {
      str = new String(arrayOfByte, "US-ASCII");
      return str;
    }
    catch (UnsupportedEncodingException localUnsupportedEncodingException)
    {
      for (;;)
      {
        String str = new String(arrayOfByte);
      }
    }
  }
  
  private static byte[] a(byte[] paramArrayOfByte1, int paramInt1, int paramInt2, byte[] paramArrayOfByte2, int paramInt3, int paramInt4)
  {
    int i = 0;
    byte[] arrayOfByte = b(paramInt4);
    int j;
    int k;
    label43:
    int n;
    if (paramInt2 > 0)
    {
      j = paramArrayOfByte1[paramInt1] << 24 >>> 8;
      if (paramInt2 <= 1) {
        break label112;
      }
      k = paramArrayOfByte1[(paramInt1 + 1)] << 24 >>> 16;
      int m = k | j;
      if (paramInt2 > 2) {
        i = paramArrayOfByte1[(paramInt1 + 2)] << 24 >>> 24;
      }
      n = i | m;
      switch (paramInt2)
      {
      }
    }
    for (;;)
    {
      return paramArrayOfByte2;
      j = 0;
      break;
      label112:
      k = 0;
      break label43;
      paramArrayOfByte2[paramInt3] = arrayOfByte[(n >>> 18)];
      paramArrayOfByte2[(paramInt3 + 1)] = arrayOfByte[(0x3F & n >>> 12)];
      paramArrayOfByte2[(paramInt3 + 2)] = arrayOfByte[(0x3F & n >>> 6)];
      paramArrayOfByte2[(paramInt3 + 3)] = arrayOfByte[(n & 0x3F)];
      continue;
      paramArrayOfByte2[paramInt3] = arrayOfByte[(n >>> 18)];
      paramArrayOfByte2[(paramInt3 + 1)] = arrayOfByte[(0x3F & n >>> 12)];
      paramArrayOfByte2[(paramInt3 + 2)] = arrayOfByte[(0x3F & n >>> 6)];
      paramArrayOfByte2[(paramInt3 + 3)] = 61;
      continue;
      paramArrayOfByte2[paramInt3] = arrayOfByte[(n >>> 18)];
      paramArrayOfByte2[(paramInt3 + 1)] = arrayOfByte[(0x3F & n >>> 12)];
      paramArrayOfByte2[(paramInt3 + 2)] = 61;
      paramArrayOfByte2[(paramInt3 + 3)] = 61;
    }
  }
  
  private static int b(byte[] paramArrayOfByte1, int paramInt1, byte[] paramArrayOfByte2, int paramInt2, int paramInt3)
  {
    int i = 1;
    if (paramArrayOfByte1 == null) {
      throw new NullPointerException("Source array was null.");
    }
    if (paramArrayOfByte2 == null) {
      throw new NullPointerException("Destination array was null.");
    }
    if ((paramInt1 < 0) || (paramInt1 + 3 >= paramArrayOfByte1.length))
    {
      Object[] arrayOfObject1 = new Object[2];
      arrayOfObject1[0] = Integer.valueOf(paramArrayOfByte1.length);
      arrayOfObject1[i] = Integer.valueOf(paramInt1);
      throw new IllegalArgumentException(String.format("Source array with length %d cannot have offset of %d and still process four bytes.", arrayOfObject1));
    }
    if ((paramInt2 < 0) || (paramInt2 + 2 >= paramArrayOfByte2.length))
    {
      Object[] arrayOfObject2 = new Object[2];
      arrayOfObject2[0] = Integer.valueOf(paramArrayOfByte2.length);
      arrayOfObject2[i] = Integer.valueOf(paramInt2);
      throw new IllegalArgumentException(String.format("Destination array with length %d cannot have offset of %d and still store three bytes.", arrayOfObject2));
    }
    byte[] arrayOfByte = c(paramInt3);
    if (paramArrayOfByte1[(paramInt1 + 2)] == 61) {
      paramArrayOfByte2[paramInt2] = ((byte)(((0xFF & arrayOfByte[paramArrayOfByte1[paramInt1]]) << 18 | (0xFF & arrayOfByte[paramArrayOfByte1[(paramInt1 + 1)]]) << 12) >>> 16));
    }
    for (;;)
    {
      return i;
      if (paramArrayOfByte1[(paramInt1 + 3)] == 61)
      {
        int k = (0xFF & arrayOfByte[paramArrayOfByte1[paramInt1]]) << 18 | (0xFF & arrayOfByte[paramArrayOfByte1[(paramInt1 + 1)]]) << 12 | (0xFF & arrayOfByte[paramArrayOfByte1[(paramInt1 + 2)]]) << 6;
        paramArrayOfByte2[paramInt2] = ((byte)(k >>> 16));
        paramArrayOfByte2[(paramInt2 + 1)] = ((byte)(k >>> 8));
        i = 2;
      }
      else
      {
        int j = (0xFF & arrayOfByte[paramArrayOfByte1[paramInt1]]) << 18 | (0xFF & arrayOfByte[paramArrayOfByte1[(paramInt1 + 1)]]) << 12 | (0xFF & arrayOfByte[paramArrayOfByte1[(paramInt1 + 2)]]) << 6 | 0xFF & arrayOfByte[paramArrayOfByte1[(paramInt1 + 3)]];
        paramArrayOfByte2[paramInt2] = ((byte)(j >> 16));
        paramArrayOfByte2[(paramInt2 + 1)] = ((byte)(j >> 8));
        paramArrayOfByte2[(paramInt2 + 2)] = ((byte)j);
        i = 3;
      }
    }
  }
  
  private static final byte[] b(int paramInt)
  {
    byte[] arrayOfByte;
    if ((paramInt & 0x10) == 16) {
      arrayOfByte = d;
    }
    for (;;)
    {
      return arrayOfByte;
      if ((paramInt & 0x20) == 32) {
        arrayOfByte = f;
      } else {
        arrayOfByte = b;
      }
    }
  }
  
  /* Error */
  public static byte[] b(byte[] paramArrayOfByte, int paramInt1, int paramInt2, int paramInt3)
  {
    // Byte code:
    //   0: aconst_null
    //   1: astore 4
    //   3: aload_0
    //   4: ifnonnull +13 -> 17
    //   7: new 203	java/lang/NullPointerException
    //   10: dup
    //   11: ldc 231
    //   13: invokespecial 208	java/lang/NullPointerException:<init>	(Ljava/lang/String;)V
    //   16: athrow
    //   17: iload_1
    //   18: ifge +30 -> 48
    //   21: new 218	java/lang/IllegalArgumentException
    //   24: dup
    //   25: new 233	java/lang/StringBuilder
    //   28: dup
    //   29: invokespecial 234	java/lang/StringBuilder:<init>	()V
    //   32: ldc 236
    //   34: invokevirtual 240	java/lang/StringBuilder:append	(Ljava/lang/String;)Ljava/lang/StringBuilder;
    //   37: iload_1
    //   38: invokevirtual 243	java/lang/StringBuilder:append	(I)Ljava/lang/StringBuilder;
    //   41: invokevirtual 246	java/lang/StringBuilder:toString	()Ljava/lang/String;
    //   44: invokespecial 225	java/lang/IllegalArgumentException:<init>	(Ljava/lang/String;)V
    //   47: athrow
    //   48: iload_2
    //   49: ifge +30 -> 79
    //   52: new 218	java/lang/IllegalArgumentException
    //   55: dup
    //   56: new 233	java/lang/StringBuilder
    //   59: dup
    //   60: invokespecial 234	java/lang/StringBuilder:<init>	()V
    //   63: ldc 248
    //   65: invokevirtual 240	java/lang/StringBuilder:append	(Ljava/lang/String;)Ljava/lang/StringBuilder;
    //   68: iload_2
    //   69: invokevirtual 243	java/lang/StringBuilder:append	(I)Ljava/lang/StringBuilder;
    //   72: invokevirtual 246	java/lang/StringBuilder:toString	()Ljava/lang/String;
    //   75: invokespecial 225	java/lang/IllegalArgumentException:<init>	(Ljava/lang/String;)V
    //   78: athrow
    //   79: iload_1
    //   80: iload_2
    //   81: iadd
    //   82: aload_0
    //   83: arraylength
    //   84: if_icmple +49 -> 133
    //   87: iconst_3
    //   88: anewarray 4	java/lang/Object
    //   91: astore 31
    //   93: aload 31
    //   95: iconst_0
    //   96: iload_1
    //   97: invokestatic 216	java/lang/Integer:valueOf	(I)Ljava/lang/Integer;
    //   100: aastore
    //   101: aload 31
    //   103: iconst_1
    //   104: iload_2
    //   105: invokestatic 216	java/lang/Integer:valueOf	(I)Ljava/lang/Integer;
    //   108: aastore
    //   109: aload 31
    //   111: iconst_2
    //   112: aload_0
    //   113: arraylength
    //   114: invokestatic 216	java/lang/Integer:valueOf	(I)Ljava/lang/Integer;
    //   117: aastore
    //   118: new 218	java/lang/IllegalArgumentException
    //   121: dup
    //   122: ldc 250
    //   124: aload 31
    //   126: invokestatic 224	java/lang/String:format	(Ljava/lang/String;[Ljava/lang/Object;)Ljava/lang/String;
    //   129: invokespecial 225	java/lang/IllegalArgumentException:<init>	(Ljava/lang/String;)V
    //   132: athrow
    //   133: iload_3
    //   134: iconst_2
    //   135: iand
    //   136: ifeq +110 -> 246
    //   139: new 252	java/io/ByteArrayOutputStream
    //   142: dup
    //   143: invokespecial 253	java/io/ByteArrayOutputStream:<init>	()V
    //   146: astore 19
    //   148: new 255	ud
    //   151: dup
    //   152: aload 19
    //   154: iload_3
    //   155: iconst_1
    //   156: ior
    //   157: invokespecial 258	ud:<init>	(Ljava/io/OutputStream;I)V
    //   160: astore 20
    //   162: new 260	java/util/zip/GZIPOutputStream
    //   165: dup
    //   166: aload 20
    //   168: invokespecial 263	java/util/zip/GZIPOutputStream:<init>	(Ljava/io/OutputStream;)V
    //   171: astore 21
    //   173: aload 21
    //   175: aload_0
    //   176: iload_1
    //   177: iload_2
    //   178: invokevirtual 267	java/util/zip/GZIPOutputStream:write	([BII)V
    //   181: aload 21
    //   183: invokevirtual 270	java/util/zip/GZIPOutputStream:close	()V
    //   186: aload 21
    //   188: invokevirtual 270	java/util/zip/GZIPOutputStream:close	()V
    //   191: aload 20
    //   193: invokevirtual 271	ud:close	()V
    //   196: aload 19
    //   198: invokevirtual 272	java/io/ByteArrayOutputStream:close	()V
    //   201: aload 19
    //   203: invokevirtual 276	java/io/ByteArrayOutputStream:toByteArray	()[B
    //   206: astore 9
    //   208: aload 9
    //   210: areturn
    //   211: astore 22
    //   213: aconst_null
    //   214: astore 20
    //   216: aconst_null
    //   217: astore 23
    //   219: aload 22
    //   221: athrow
    //   222: astore 24
    //   224: aload 23
    //   226: astore 19
    //   228: aload 4
    //   230: invokevirtual 270	java/util/zip/GZIPOutputStream:close	()V
    //   233: aload 20
    //   235: invokevirtual 271	ud:close	()V
    //   238: aload 19
    //   240: invokevirtual 272	java/io/ByteArrayOutputStream:close	()V
    //   243: aload 24
    //   245: athrow
    //   246: iload_3
    //   247: bipush 8
    //   249: iand
    //   250: ifeq +139 -> 389
    //   253: iconst_1
    //   254: istore 5
    //   256: iconst_4
    //   257: iload_2
    //   258: iconst_3
    //   259: idiv
    //   260: imul
    //   261: istore 6
    //   263: iload_2
    //   264: iconst_3
    //   265: irem
    //   266: ifle +129 -> 395
    //   269: iconst_4
    //   270: istore 7
    //   272: iload 7
    //   274: iload 6
    //   276: iadd
    //   277: istore 8
    //   279: iload 5
    //   281: ifeq +13 -> 294
    //   284: iload 8
    //   286: iload 8
    //   288: bipush 76
    //   290: idiv
    //   291: iadd
    //   292: istore 8
    //   294: iload 8
    //   296: newarray byte
    //   298: astore 9
    //   300: iload_2
    //   301: iconst_2
    //   302: isub
    //   303: istore 10
    //   305: iconst_0
    //   306: istore 11
    //   308: iconst_0
    //   309: istore 12
    //   311: iconst_0
    //   312: istore 13
    //   314: iload 13
    //   316: iload 10
    //   318: if_icmpge +83 -> 401
    //   321: aload_0
    //   322: iload 13
    //   324: iload_1
    //   325: iadd
    //   326: iconst_3
    //   327: aload 9
    //   329: iload 12
    //   331: iload_3
    //   332: invokestatic 278	uc:a	([BII[BII)[B
    //   335: pop
    //   336: iload 11
    //   338: iconst_4
    //   339: iadd
    //   340: istore 17
    //   342: iload 5
    //   344: ifeq +25 -> 369
    //   347: iload 17
    //   349: bipush 76
    //   351: if_icmplt +18 -> 369
    //   354: aload 9
    //   356: iload 12
    //   358: iconst_4
    //   359: iadd
    //   360: bipush 10
    //   362: bastore
    //   363: iinc 12 1
    //   366: iconst_0
    //   367: istore 17
    //   369: iload 13
    //   371: iconst_3
    //   372: iadd
    //   373: istore 18
    //   375: iinc 12 4
    //   378: iload 17
    //   380: istore 11
    //   382: iload 18
    //   384: istore 13
    //   386: goto -72 -> 314
    //   389: iconst_0
    //   390: istore 5
    //   392: goto -136 -> 256
    //   395: iconst_0
    //   396: istore 7
    //   398: goto -126 -> 272
    //   401: iload 13
    //   403: iload_2
    //   404: if_icmpge +24 -> 428
    //   407: aload_0
    //   408: iload 13
    //   410: iload_1
    //   411: iadd
    //   412: iload_2
    //   413: iload 13
    //   415: isub
    //   416: aload 9
    //   418: iload 12
    //   420: iload_3
    //   421: invokestatic 278	uc:a	([BII[BII)[B
    //   424: pop
    //   425: iinc 12 4
    //   428: iload 12
    //   430: bipush 255
    //   432: aload 9
    //   434: arraylength
    //   435: iadd
    //   436: if_icmpgt -228 -> 208
    //   439: iload 12
    //   441: newarray byte
    //   443: astore 14
    //   445: aload 9
    //   447: iconst_0
    //   448: aload 14
    //   450: iconst_0
    //   451: iload 12
    //   453: invokestatic 284	java/lang/System:arraycopy	(Ljava/lang/Object;ILjava/lang/Object;II)V
    //   456: aload 14
    //   458: astore 9
    //   460: goto -252 -> 208
    //   463: astore 28
    //   465: goto -274 -> 191
    //   468: astore 29
    //   470: goto -274 -> 196
    //   473: astore 30
    //   475: goto -274 -> 201
    //   478: astore 25
    //   480: goto -247 -> 233
    //   483: astore 26
    //   485: goto -247 -> 238
    //   488: astore 27
    //   490: goto -247 -> 243
    //   493: astore 24
    //   495: aconst_null
    //   496: astore 20
    //   498: aconst_null
    //   499: astore 19
    //   501: goto -273 -> 228
    //   504: astore 24
    //   506: aconst_null
    //   507: astore 20
    //   509: goto -281 -> 228
    //   512: astore 24
    //   514: goto -286 -> 228
    //   517: astore 24
    //   519: aload 21
    //   521: astore 4
    //   523: goto -295 -> 228
    //   526: astore 22
    //   528: aconst_null
    //   529: astore 20
    //   531: aload 19
    //   533: astore 23
    //   535: goto -316 -> 219
    //   538: astore 22
    //   540: aload 19
    //   542: astore 23
    //   544: goto -325 -> 219
    //   547: astore 22
    //   549: aload 21
    //   551: astore 4
    //   553: aload 19
    //   555: astore 23
    //   557: goto -338 -> 219
    // Local variable table:
    //   start	length	slot	name	signature
    //   0	560	0	paramArrayOfByte	byte[]
    //   0	560	1	paramInt1	int
    //   0	560	2	paramInt2	int
    //   0	560	3	paramInt3	int
    //   1	551	4	localObject1	Object
    //   254	137	5	i	int
    //   261	16	6	j	int
    //   270	127	7	k	int
    //   277	18	8	m	int
    //   206	253	9	localObject2	Object
    //   303	16	10	n	int
    //   306	75	11	i1	int
    //   309	143	12	i2	int
    //   312	104	13	i3	int
    //   443	14	14	arrayOfByte	byte[]
    //   340	39	17	i4	int
    //   373	10	18	i5	int
    //   146	408	19	localObject3	Object
    //   160	370	20	localud	ud
    //   171	379	21	localGZIPOutputStream	java.util.zip.GZIPOutputStream
    //   211	9	22	localIOException1	IOException
    //   526	1	22	localIOException2	IOException
    //   538	1	22	localIOException3	IOException
    //   547	1	22	localIOException4	IOException
    //   217	339	23	localObject4	Object
    //   222	22	24	localObject5	Object
    //   493	1	24	localObject6	Object
    //   504	1	24	localObject7	Object
    //   512	1	24	localObject8	Object
    //   517	1	24	localObject9	Object
    //   478	1	25	localException1	java.lang.Exception
    //   483	1	26	localException2	java.lang.Exception
    //   488	1	27	localException3	java.lang.Exception
    //   463	1	28	localException4	java.lang.Exception
    //   468	1	29	localException5	java.lang.Exception
    //   473	1	30	localException6	java.lang.Exception
    //   91	34	31	arrayOfObject	Object[]
    // Exception table:
    //   from	to	target	type
    //   139	148	211	java/io/IOException
    //   219	222	222	finally
    //   186	191	463	java/lang/Exception
    //   191	196	468	java/lang/Exception
    //   196	201	473	java/lang/Exception
    //   228	233	478	java/lang/Exception
    //   233	238	483	java/lang/Exception
    //   238	243	488	java/lang/Exception
    //   139	148	493	finally
    //   148	162	504	finally
    //   162	173	512	finally
    //   173	186	517	finally
    //   148	162	526	java/io/IOException
    //   162	173	538	java/io/IOException
    //   173	186	547	java/io/IOException
  }
  
  private static byte[] b(byte[] paramArrayOfByte1, byte[] paramArrayOfByte2, int paramInt1, int paramInt2)
  {
    a(paramArrayOfByte2, 0, paramInt1, paramArrayOfByte1, 0, paramInt2);
    return paramArrayOfByte1;
  }
  
  private static final byte[] c(int paramInt)
  {
    byte[] arrayOfByte;
    if ((paramInt & 0x10) == 16) {
      arrayOfByte = e;
    }
    for (;;)
    {
      return arrayOfByte;
      if ((paramInt & 0x20) == 32) {
        arrayOfByte = g;
      } else {
        arrayOfByte = c;
      }
    }
  }
}


/* Location:           C:\Users\dreadiscool\Desktop\tools\classes-dex2jar.jar
 * Qualified Name:     uc
 * JD-Core Version:    0.7.0.1
 */