final class vX
  implements Runnable
{
  private vX(vV paramvV) {}
  
  /* Error */
  public void run()
  {
    // Byte code:
    //   0: invokestatic 25	java/lang/System:currentTimeMillis	()J
    //   3: lstore_1
    //   4: aload_0
    //   5: getfield 12	vX:a	LvV;
    //   8: invokestatic 30	vV:a	(LvV;)Ljava/util/Map;
    //   11: astore_3
    //   12: aload_3
    //   13: monitorenter
    //   14: aload_0
    //   15: getfield 12	vX:a	LvV;
    //   18: invokestatic 30	vV:a	(LvV;)Ljava/util/Map;
    //   21: invokeinterface 36 1 0
    //   26: invokeinterface 42 1 0
    //   31: astore 5
    //   33: aload 5
    //   35: invokeinterface 48 1 0
    //   40: ifeq +74 -> 114
    //   43: aload 5
    //   45: invokeinterface 52 1 0
    //   50: checkcast 54	java/util/Map$Entry
    //   53: invokeinterface 57 1 0
    //   58: checkcast 59	vZ
    //   61: astore 7
    //   63: lload_1
    //   64: aload 7
    //   66: getfield 62	vZ:a	J
    //   69: lsub
    //   70: ldc2_w 63
    //   73: lcmp
    //   74: ifle -41 -> 33
    //   77: aload_0
    //   78: getfield 12	vX:a	LvV;
    //   81: invokestatic 68	vV:b	(LvV;)Lcom/mixpanel/android/mpmetrics/MixpanelAPI;
    //   84: aload 7
    //   86: getfield 71	vZ:b	Ljava/lang/String;
    //   89: aload 7
    //   91: getfield 75	vZ:c	Lorg/json/JSONObject;
    //   94: invokevirtual 81	com/mixpanel/android/mpmetrics/MixpanelAPI:track	(Ljava/lang/String;Lorg/json/JSONObject;)V
    //   97: aload 5
    //   99: invokeinterface 84 1 0
    //   104: goto -71 -> 33
    //   107: astore 4
    //   109: aload_3
    //   110: monitorexit
    //   111: aload 4
    //   113: athrow
    //   114: aload_0
    //   115: getfield 12	vX:a	LvV;
    //   118: invokestatic 30	vV:a	(LvV;)Ljava/util/Map;
    //   121: invokeinterface 87 1 0
    //   126: ifne +18 -> 144
    //   129: aload_0
    //   130: getfield 12	vX:a	LvV;
    //   133: invokestatic 90	vV:c	(LvV;)Landroid/os/Handler;
    //   136: aload_0
    //   137: ldc2_w 91
    //   140: invokevirtual 98	android/os/Handler:postDelayed	(Ljava/lang/Runnable;J)Z
    //   143: pop
    //   144: aload_3
    //   145: monitorexit
    //   146: return
    // Local variable table:
    //   start	length	slot	name	signature
    //   0	147	0	this	vX
    //   3	61	1	l	long
    //   11	134	3	localMap	java.util.Map
    //   107	5	4	localObject	Object
    //   31	67	5	localIterator	java.util.Iterator
    //   61	29	7	localvZ	vZ
    // Exception table:
    //   from	to	target	type
    //   14	111	107	finally
    //   114	146	107	finally
  }
}


/* Location:           C:\Users\dreadiscool\Desktop\tools\classes-dex2jar.jar
 * Qualified Name:     vX
 * JD-Core Version:    0.7.0.1
 */