import java.io.File;
import java.io.IOException;

public final class yL
{
  final zT a = new yM(this);
  private final zL b;
  private int c;
  private int d;
  private int e;
  private int f;
  private int g;
  
  public yL(File paramFile, long paramLong)
  {
    this.b = zL.a(paramFile, 201105, 2, paramLong);
  }
  
  private Ai a(zF paramzF)
  {
    Object localObject = null;
    String str = paramzF.a().d();
    if (AB.a(paramzF.a().d())) {}
    try
    {
      c(paramzF.a());
      for (;;)
      {
        label31:
        return localObject;
        if ((str.equals("GET")) && (!AD.b(paramzF)))
        {
          yR localyR = new yR(paramzF);
          try
          {
            localzO2 = this.b.b(b(paramzF.a()));
            if (localzO2 == null) {}
          }
          catch (IOException localIOException1)
          {
            try
            {
              localyR.a(localzO2);
              yN localyN = new yN(this, localzO2);
              localObject = localyN;
            }
            catch (IOException localIOException2)
            {
              for (;;)
              {
                zO localzO2;
                zO localzO1 = localzO2;
              }
            }
            localIOException1 = localIOException1;
            localzO1 = null;
            a(localzO1);
          }
        }
      }
    }
    catch (IOException localIOException3)
    {
      break label31;
    }
  }
  
  private void a()
  {
    try
    {
      this.f = (1 + this.f);
      return;
    }
    finally
    {
      localObject = finally;
      throw localObject;
    }
  }
  
  /* Error */
  private void a(Aj paramAj)
  {
    // Byte code:
    //   0: aload_0
    //   1: monitorenter
    //   2: aload_0
    //   3: iconst_1
    //   4: aload_0
    //   5: getfield 99	yL:g	I
    //   8: iadd
    //   9: putfield 99	yL:g	I
    //   12: aload_1
    //   13: getfield 104	Aj:a	Lzz;
    //   16: ifnull +16 -> 32
    //   19: aload_0
    //   20: iconst_1
    //   21: aload_0
    //   22: getfield 106	yL:e	I
    //   25: iadd
    //   26: putfield 106	yL:e	I
    //   29: aload_0
    //   30: monitorexit
    //   31: return
    //   32: aload_1
    //   33: getfield 109	Aj:b	LzF;
    //   36: ifnull -7 -> 29
    //   39: aload_0
    //   40: iconst_1
    //   41: aload_0
    //   42: getfield 96	yL:f	I
    //   45: iadd
    //   46: putfield 96	yL:f	I
    //   49: goto -20 -> 29
    //   52: astore_2
    //   53: aload_0
    //   54: monitorexit
    //   55: aload_2
    //   56: athrow
    // Local variable table:
    //   start	length	slot	name	signature
    //   0	57	0	this	yL
    //   0	57	1	paramAj	Aj
    //   52	4	2	localObject	Object
    // Exception table:
    //   from	to	target	type
    //   2	29	52	finally
    //   32	49	52	finally
  }
  
  private void a(zF paramzF1, zF paramzF2)
  {
    yR localyR = new yR(paramzF2);
    zR localzR = yP.a((yP)paramzF1.h());
    zO localzO = null;
    try
    {
      localzO = localzR.a();
      if (localzO != null)
      {
        localyR.a(localzO);
        localzO.a();
      }
      return;
    }
    catch (IOException localIOException)
    {
      for (;;)
      {
        a(localzO);
      }
    }
  }
  
  private void a(zO paramzO)
  {
    if (paramzO != null) {}
    try
    {
      paramzO.b();
      label8:
      return;
    }
    catch (IOException localIOException)
    {
      break label8;
    }
  }
  
  private static int b(LD paramLD)
  {
    String str = paramLD.q();
    try
    {
      int i = Integer.parseInt(str);
      return i;
    }
    catch (NumberFormatException localNumberFormatException)
    {
      throw new IOException("Expected an integer but was \"" + str + "\"");
    }
  }
  
  private static String b(zz paramzz)
  {
    return Ae.b(paramzz.c());
  }
  
  private void c(zz paramzz)
  {
    this.b.c(b(paramzz));
  }
  
  zF a(zz paramzz)
  {
    Object localObject = null;
    String str = b(paramzz);
    for (;;)
    {
      try
      {
        localzR = this.b.a(str);
        if (localzR != null) {
          continue;
        }
      }
      catch (IOException localIOException1)
      {
        zR localzR;
        zF localzF;
        continue;
      }
      return localObject;
      try
      {
        yR localyR = new yR(localzR.a(0));
        localzF = localyR.a(paramzz, localzR);
        if (localyR.a(paramzz, localzF)) {
          continue;
        }
        Ae.a(localzF.h());
      }
      catch (IOException localIOException2)
      {
        Ae.a(localzR);
      }
      continue;
      localObject = localzF;
    }
  }
}


/* Location:           C:\Users\dreadiscool\Desktop\tools\classes-dex2jar.jar
 * Qualified Name:     yL
 * JD-Core Version:    0.7.0.1
 */